Workbook

Sheet INDEX
B2: #VALUE!
B4: DCF VALUATION & FINANCIAL ANALYSIS DASHBOARD
B6: Current Share Price | F6: DCF Value / Share | J6: Discount / (Premium) | N6: WACC
B7: {=_FV(B2,"Open")} -> 1158.1 | F7: =Valuation!$J$37 -> 1028.5768 | J7: =Valuation!J39 -> -0.14993657 | N7: =Valuation!C45 -> 0.12882212
B10: MODEL NAVIGATION | F10: VALUATION SNAPSHOT | J10: KEY DCF ASSUMPTIONS
B11: =HYPERLINK("#'Assumptions'!A1","Assumptions") -> Assumptions | C11: Working | D11: Financial Statements | F11: Enterprise / Operating Assets | G11: =Valuation!J31 -> 2746577.9 | J11: Risk-Free Rate | K11: =Assumptions!C102 -> 0.071
B12: Income Statement | C12: Balance Sheet | D12: Cash Flow | F12: Equity Value | G12: =Valuation!J35 -> 2719556.9 | J12: Beta | K12: =Assumptions!C104 -> 0.92
B13: Valuation | C13: =HYPERLINK("#CCA!B2","CCA") -> CCA | D13: Ratio | F13: Shares Outstanding | G13: =Valuation!J36 -> 2644 | J13: Market Risk Premium | K13: =Assumptions!C103 -> 0.065
J14: Terminal Growth | K14: =Assumptions!C109 -> 0.04
B16: Revenue & EBITDA Trend | J16: PROFITABILITY MARGINS
B27: ROC AND ROCE | J27: Valuation Summary
J28: Valuation Method | K28: Implied Value / Share | N28: Reference
J29: DCF | K29: =Valuation!J37 -> 1028.5768 | N29: Primary DCF valuation
J30: EV / Revenue | K30: =CCA!G62 -> 2466.8951 | N30: Peer median multiple
J31: EV / EBITDA | K31: =CCA!G63 -> 685.48681 | N31: Peer median multiple
J32: EV / EBIT | K32: =CCA!G64 -> 589.84843 | N32: Peer median multiple
J33: P / E | K33: =CCA!G65 -> 581.65017 | N33: Peer median multiple
J35: WORKING CAPITAL EFFICIENCY
B38: FCFF VS FCFE
B48: COMPANY OVERVIEW | I48: Investment & Financial Overview
B49: United Breweries Limited (UBL) is one of India’s leading beer companies and is best known for its flagship Kingfisher brand. The company operates in the alcoholic beverages industry, with its business primarily focused on beer. UBL has an established distribution network and a strong presence across the Indian market. | H49: This dashboard presents a DCF-based valuation and financial analysis of UBL, covering historical performance from FY2021–FY2025 and forecasts through FY2035. The analysis evaluates revenue growth, profitability, liquidity, leverage, working-capital efficiency and return ratios. The valuation section uses FCFF/DCF methodology, supported by WACC, terminal growth and sensitivity analysis. Relative valuation through EV/Revenue, EV/EBITDA, EV/EBIT and P/E multiples is also presented to provide a comparison with selected listed peers.
P52: =[1]FS!R4 -> FY2035
P53: =[1]FS!R8 -> 0
P54: =[1]FS!R26 -> 0
P55: =[1]FS!R18 -> 0
P56: =P54+P55 -> 0
B61: Key Takeaway
B62: Revenue growth normalizes toward 5% in the later forecast years, reflecting a more mature growth profile.
B63: EBITDA margin expands from 4.4% in FY2025A to 14.4% by FY2035E, indicating significant operating leverage.
B64: EBIT margin improves from 3.2% in FY2025A to 12.9% by FY2035E, supported by margin expansion and operating efficiencies.
B65: PAT margin increases from 2.3% in FY2025A to 8.9% by FY2035E, reflecting stronger operating profitability.
B66: Current Ratio improves from 1.41x in FY2025A to 2.99x by FY2035E, indicating strengthening liquidity.
B67: Debt/Equity declines from 0.14x in FY2025A to 0.06x by FY2035E, reflecting limited reliance on debt.
B68: Interest Coverage increases from 66.17x in FY2025A to 154.46x by FY2035E as EBIT grows faster than finance costs.
B69: Cash Conversion Cycle remains elevated at approximately 95 days during the forecast period, indicating continued working-capital requirements.
B70: ROE increases from 10.1% in FY2025A to approximately 25% in the later forecast years, reflecting stronger earnings generation.
B71: ROCE rises from 13.9% in FY2025A to approximately 38% during the forecast period, indicating improved returns on capital employed.
B72: FCFF increases from ₹59,940 lakh in FY2026E to ₹296,032 lakh by FY2035E, supporting higher operating cash generation.
... B108: FILL THE INPUT TABLES BELOW WITH YOUR FINAL HISTORICAL + FORECAST VALUES. THE CHARTS ABOVE WILL UPDATE AUTOMATICALLY.

Sheet CHARTS
A1: United Breweries Limited
A2: Working
C3: Period Start | H3: 43922 | I3: 44287 | J3: 44652 | K3: 45017 | L3: 45383 | M3: 45748 | N3: 46113 | O3: 46478 | P3: 46844 | Q3: 47209 | R3: 47574 | S3: 47939 | T3: 48305 | U3: 48670 | V3: 49035
C4: Period End | H4: 44286 | I4: 44651 | J4: 45016 | K4: 45382 | L4: 45747 | M4: 46112 | N4: 46477 | O4: 46843 | P4: 47208 | Q4: 47573 | R4: 47938 | S4: 48304 | T4: 48669 | U4: 49034 | V4: 49399
C5: Period Type | H5: Historical | I5: Historical | J5: Historical | K5: Historical | L5: Historical | M5: Forecast | N5: Forecast | O5: Forecast | P5: Forecast | Q5: Forecast | R5: Forecast | S5: Forecast | T5: Forecast | U5: Forecast | V5: Forecast
C6: Days | H6: =H4-H3+1 -> 365 | I6: =I4-I3+1 -> 365 | J6: =J4-J3+1 -> 365 | K6: =K4-K3+1 -> 366 | L6: =L4-L3+1 -> 365 | M6: =M4-M3+1 -> 365 | N6: =N4-N3+1 -> 365 | O6: =O4-O3+1 -> 366 | ... V6: =V4-V3+1 -> 365
A7: Timing
A9: Model Start Date | B9: Date | C9: 43922
A10: Months in a period | B10: # | C10: 12
A11: Start of Forecast Period | B11: Date | C11: 45748
A12: Number of Forecast Period | B12: # | C12: 10
A15: Revenue
A16: Revenue from Contracts with Customers
A17: Revenue from contracts with customers (including excise duty) | B17: ₹ Lakhs | H17: ='Income Statement-Historic'!C12 -> 1018576 | I17: ='Income Statement-Historic'!D12 -> 1312392 | J17: ='Income Statement-Historic'!E12 -> 1665109 | K17: ='Income Statement-Historic'!F12 -> 1837953 | L17: ='Income Statement-Historic'!G12 -> 1940854 | M17: =L17*(1+M18) -> 2076713.8 | N17: =M17*(1+N18) -> 2222083.7 | O17: =N17*(1+O18) -> 2366519.2 | P17: =O17*(1+P18) -> 2520342.9 | Q17: =P17*(1+Q18) -> 2671563.5 | R17: =Q17*(1+R18) -> 2831857.3 | S17: =R17*(1+S18) -> 2987609.5 | T17: =S17*(1+T18) -> 3151928 | ... V17: =U17*(1+V18) -> 3475000.6
A18: Revenue Growth Rate | B18: % | I18: =I17/H17-1 -> 0.28845761 | J18: =J17/I17-1 -> 0.26875888 | K18: =K17/J17-1 -> 0.10380341 | L18: =L17/K17-1 -> 0.055986742 | M18: 0.07 | N18: 0.07 | O18: 0.065 | P18: 0.065 | Q18: 0.06 | R18: 0.06 | S18: 0.055 | T18: 0.055 | U18: 0.05 | V18: 0.05
A19: Other income | B19: ₹ Lakhs | H19: ='Income Statement-Historic'!C13 -> 5025 | I19: ='Income Statement-Historic'!D13 -> 2979 | J19: ='Income Statement-Historic'!E13 -> 4943 | K19: ='Income Statement-Historic'!F13 -> 7374 | L19: ='Income Statement-Historic'!G13 -> 3590 | M19: =M17*M20 -> 6659.4424 | N19: =N17*N20 -> 7125.6034 | O19: =O17*O20 -> 7588.7676 | P19: =P17*P20 -> 8082.0375 | Q19: =Q17*Q20 -> 8566.9598 | R19: =R17*R20 -> 9080.9774 | S19: =S17*S20 -> 9580.4311 | T19: =T17*T20 -> 10107.355 | ... V19: =V17*V20 -> 11143.359
A20: Other Income % of Revenue | B20: % | H20: =H19/H17 -> 0.0049333579 | I20: =I19/I17 -> 0.0022699011 | J20: =J19/J17 -> 0.0029685744 | K20: =K19/K17 -> 0.0040120721 | L20: =L19/L17 -> 0.0018497012 | M20: =AVERAGE(H20:L20) -> 0.0032067214 | N20: =$M$20 -> 0.0032067214 | O20: =$M$20 -> 0.0032067214 | P20: =$M$20 -> 0.0032067214 | Q20: =$M$20 -> 0.0032067214 | R20: =$M$20 -> 0.0032067214 | S20: =$M$20 -> 0.0032067214 | T20: =$M$20 -> 0.0032067214 | U20: =$M$20 -> 0.0032067214 | V20: =$M$20 -> 0.0032067214
A21: Total Revenue | H21: =SUM(H19,H17) -> 1023601 | I21: =SUM(I19,I17) -> 1315371 | J21: =SUM(J19,J17) -> 1670052 | K21: =SUM(K19,K17) -> 1845327 | L21: =SUM(L19,L17) -> 1944444 | M21: =SUM(M19,M17) -> 2083373.2 | N21: =SUM(N19,N17) -> 2229209.3 | O21: =SUM(O19,O17) -> 2374108 | ... V21: =SUM(V19,V17) -> 3486144
A23: Cost
A24: Cost of Sales
A25: Cost of materials consumed | B25: ₹ Lakhs | H25: ='Income Statement-Historic'!C17 -> 196516 | I25: ='Income Statement-Historic'!D17 -> 270729 | J25: ='Income Statement-Historic'!E17 -> 422476 | K25: ='Income Statement-Historic'!F17 -> 456755 | L25: ='Income Statement-Historic'!G17 -> 493673 | M25: =M17*M26 -> 480058.57 | N25: =N17*N26 -> 503389.42 | O25: =O17*O26 -> 509304.25 | P25: =P17*P26 -> 520712.66 | Q25: =Q17*Q26 -> 529877.21 | R25: =R17*R26 -> 539203.04 | S25: =S17*S26 -> 568859.21 | T25: =T17*T26 -> 600146.47 | ... V25: =V17*V26 -> 661661.48
A26: Cost as % of Revenue | B26: % of Revenue | H26: =H25/H17 -> 0.19293209 | I26: =I25/I17 -> 0.20628669 | J26: =J25/J17 -> 0.25372273 | K26: =K25/K17 -> 0.24851288 | L26: =L25/L17 -> 0.25435865 | M26: =AVERAGE(H26:L26) -> 0.23116261 | N26: =M26-(M26*2%) -> 0.22653936 | O26: =N26-(N26*5%) -> 0.21521239 | P26: =O26-(O26*4%) -> 0.20660389 | Q26: =P26-(P26*4%) -> 0.19833974 | R26: =Q26-(Q26*4%) -> 0.19040615 | S26: =R26 -> 0.19040615 | T26: =S26 -> 0.19040615 | U26: =T26 -> 0.19040615 | V26: =U26 -> 0.19040615
A27: Purchase of stock-in-trade / traded goods | B27: ₹ Lakhs | H27: ='Income Statement-Historic'!C18 -> 7371 | I27: ='Income Statement-Historic'!D18 -> 19582 | J27: ='Income Statement-Historic'!E18 -> 9247 | K27: ='Income Statement-Historic'!F18 -> 11825 | L27: ='Income Statement-Historic'!G18 -> 18174 | M27: =M17*M28 -> 18070.948 | N27: =N17*N28 -> 19335.914 | O27: =O17*O28 -> 20592.748 | P27: =P17*P28 -> 21931.277 | Q27: =Q17*Q28 -> 23247.154 | R27: =R17*R28 -> 24641.983 | S27: =S17*S28 -> 25997.292 | T27: =T17*T28 -> 27427.143 | ... V27: =V17*V28 -> 30238.425
A28: Cost as % of Revenue | B28: % of Revenue | H28: =H27/H17 -> 0.0072365734 | I28: =I27/I17 -> 0.014920847 | J28: =J27/J17 -> 0.0055533902 | K28: =K27/K17 -> 0.006433788 | L28: =L27/L17 -> 0.0093639192 | M28: =AVERAGE(H28:L28) -> 0.0087017035 | N28: =$M$28 -> 0.0087017035 | O28: =$M$28 -> 0.0087017035 | P28: =$M$28 -> 0.0087017035 | Q28: =$M$28 -> 0.0087017035 | R28: =$M$28 -> 0.0087017035 | S28: =$M$28 -> 0.0087017035 | T28: =$M$28 -> 0.0087017035 | U28: =$M$28 -> 0.0087017035 | V28: =$M$28 -> 0.0087017035
A29: Changes in inventories of finished goods, work-in-progress and stock-in-trade | B29: ₹ Lakhs | H29: ='Income Statement-Historic'!C19 -> -950 | I29: ='Income Statement-Historic'!D19 -> 2301 | J29: ='Income Statement-Historic'!E19 -> -5187 | K29: ='Income Statement-Historic'!F19 -> -3345 | L29: ='Income Statement-Historic'!G19 -> -4996 | M29: =M17*M30 -> -5345.72 | N29: =N17*N30 -> -5719.9204 | O29: =O17*O30 -> -6091.7152 | P29: =P17*P30 -> -6487.6767 | Q29: =Q17*Q30 -> -6876.9373 | R29: =R17*R30 -> -7289.5536 | S29: =S17*S30 -> -7690.479 | T29: =T17*T30 -> -8113.4553 | ... V29: =V17*V30 -> -8945.0845
A30: Changes in Inventories as % of Revenue | B30: % of Revenue | H30: =H29/H17 -> -0.00093267464 | I30: =I29/I17 -> 0.0017532871 | J30: =J29/J17 -> -0.0031151114 | K30: =K29/K17 -> -0.0018199595 | L30: =L29/L17 -> -0.0025741246 | M30: =L30 -> -0.0025741246 | N30: =M30 -> -0.0025741246 | O30: =N30 -> -0.0025741246 | P30: =O30 -> -0.0025741246 | Q30: =P30 -> -0.0025741246 | R30: =Q30 -> -0.0025741246 | S30: =R30 -> -0.0025741246 | T30: =S30 -> -0.0025741246 | ... V30: =U30 -> -0.0025741246
A31: Excise duty on sale of goods/products | B31: ₹ Lakhs | H31: ='Income Statement-Historic'!C20 -> 594267 | I31: ='Income Statement-Historic'!D20 -> 728548 | J31: ='Income Statement-Historic'!E20 -> 915117 | K31: ='Income Statement-Historic'!F20 -> 1025685 | L31: ='Income Statement-Historic'!G20 -> 1049345 | M31: =M17*M32 -> 1157503.3 | N31: =N17*N32 -> 1238528.5 | O31: =O17*O32 -> 1305842.5 | P31: =P17*P32 -> 1376815 | Q31: =Q17*Q32 -> 1444829.7 | R31: =R17*R32 -> 1516204.3 | S31: =S17*S32 -> 1583599.6 | T31: =T17*T32 -> 1653990.6 | ... V31: =V17*V32 -> 1787236.5
A32: Excise Duty as % of Revenue | B32: % of Revenue | H32: =H31/H17 -> 0.58342922 | I32: =I31/I17 -> 0.55512987 | J32: =J31/J17 -> 0.54958384 | K32: =K31/K17 -> 0.55805834 | L32: =L31/L17 -> 0.54066148 | M32: =AVERAGE(H32:L32) -> 0.55737255 | N32: =M32 -> 0.55737255 | O32: =N32-(N32*1%) -> 0.55179882 | P32: =O32-(O32*1%) -> 0.54628084 | Q32: =P32-(P32*1%) -> 0.54081803 | R32: =Q32-(Q32*1%) -> 0.53540985 | S32: =R32-(R32*1%) -> 0.53005575 | T32: =S32-(S32*1%) -> 0.52475519 | U32: =T32-(T32*1%) -> 0.51950764 | V32: =U32-(U32*1%) -> 0.51431256
A33: COGS | H33: =SUM(H25+H27+H29) -> 202937 | I33: =SUM(I25+I27+I29) -> 292612 | J33: =SUM(J25+J27+J29) -> 426536 | K33: =SUM(K25+K27+K29) -> 465235 | L33: =SUM(L25+L27+L29) -> 506851 | M33: =SUM(M25+M27+M29) -> 492783.8 | N33: =SUM(N25+N27+N29) -> 517005.42 | O33: =SUM(O25+O27+O29) -> 523805.28 | ... V33: =SUM(V25+V27+V29) -> 682954.82
A35: Employee Costs
A36: Employee benefits expense | B36: ₹ Lakhs | H36: ='Income Statement-Historic'!C21 -> 48549 | I36: ='Income Statement-Historic'!D21 -> 52312 | J36: ='Income Statement-Historic'!E21 -> 41183 | K36: ='Income Statement-Historic'!F21 -> 45210 | L36: ='Income Statement-Historic'!G21 -> 52180 | M36: =M17*M37 -> 68008.077 | N36: =N17*N37 -> 72768.642 | O36: =O17*O37 -> 77498.604 | P36: =P17*P37 -> 82536.013 | Q36: =Q17*Q37 -> 87488.174 | R36: =R17*R37 -> 92737.464 | S36: =S17*S37 -> 97838.025 | T36: =T17*T37 -> 103219.12 | ... V36: =V17*V37 -> 113799.08
A37: Employee Benefits Expense as % of Revenue | B37: % of Revenue | H37: =H36/H17 -> 0.047663601 | I37: =I36/I17 -> 0.039860042 | J37: =J36/J17 -> 0.024732915 | K37: =K36/K17 -> 0.024598017 | L37: =L36/L17 -> 0.026885072 | M37: =AVERAGE(H37:L37) -> 0.03274793 | N37: =M37 -> 0.03274793 | O37: =N37 -> 0.03274793 | P37: =O37 -> 0.03274793 | Q37: =P37 -> 0.03274793 | R37: =Q37 -> 0.03274793 | S37: =R37 -> 0.03274793 | T37: =S37 -> 0.03274793 | U37: =T37 -> 0.03274793 | V37: =U37 -> 0.03274793
A38: Contract employee expense | B38: ₹ Lakhs | H38: ='Income Statement-Historic'!C22 -> — | I38: ='Income Statement-Historic'!D22 -> — | J38: ='Income Statement-Historic'!E22 -> 18368 | K38: ='Income Statement-Historic'!F22 -> 19525 | L38: ='Income Statement-Historic'!G22 -> 19666 | M38: =M17*M39 -> 22004.163 | N38: =N17*N39 -> 23544.454 | O38: =O17*O39 -> 25074.844 | P38: =P17*P39 -> 26704.709 | Q38: =Q17*Q39 -> 28306.991 | R38: =R17*R39 -> 30005.411 | S38: =S17*S39 -> 31655.708 | T38: =T17*T39 -> 33396.772 | ... V38: =V17*V39 -> 36819.941
A39: Contract Employee Expense as % of Revenue | B39: % of Revenue | J39: =J38/J17 -> 0.01103111 | K39: =K38/K17 -> 0.010623231 | L39: =L38/L17 -> 0.010132653 | M39: =AVERAGE(J39:L39) -> 0.010595665 | N39: =M39 -> 0.010595665 | O39: =N39 -> 0.010595665 | P39: =O39 -> 0.010595665 | Q39: =P39 -> 0.010595665 | R39: =Q39 -> 0.010595665 | S39: =R39 -> 0.010595665 | T39: =S39 -> 0.010595665 | U39: =T39 -> 0.010595665 | V39: =U39 -> 0.010595665
A41: Other Operating Expenses
A42: Other expenses | B42: ₹ Lakhs | H42: ='Income Statement-Historic'!C25 -> 134717 | I42: ='Income Statement-Historic'!D25 -> 169258 | J42: ='Income Statement-Historic'!E25 -> 202282 | K42: ='Income Statement-Historic'!F25 -> 212679 | L42: ='Income Statement-Historic'!G25 -> 228731 | M42: =M17*M43 -> 255966.52 | N42: =N17*N43 -> 273884.18 | O42: =O17*O43 -> 288769.78 | P42: =P17*P43 -> 304464.42 | Q42: =Q17*Q43 -> 319504.96 | R42: =R17*R43 -> 335288.51 | S42: =S17*S43 -> 343117.5 | T42: =T17*T43 -> 351129.29 | ... V42: =V17*V43 -> 364241.25
A43: Other Expenses as % of Revenue | B43: % of Revenue | H43: =H42/H17 -> 0.13226014 | I43: =I42/I17 -> 0.12896909 | J43: =J42/J17 -> 0.12148274 | K43: =K42/K17 -> 0.11571515 | L43: =L42/L17 -> 0.1178507 | M43: =AVERAGE(H43:L43) -> 0.12325556 | N43: =M43 -> 0.12325556 | O43: =N43-(N43*1%) -> 0.12202301 | P43: =O43-(O43*1%) -> 0.12080278 | Q43: =P43-(P43*1%) -> 0.11959475 | R43: =Q43-(Q43*1%) -> 0.1183988 | S43: =R43-(R43*3%) -> 0.11484684 | T43: =S43-(S43*3%) -> 0.11140143 | U43: =T43-(T43*3%) -> 0.10805939 | V43: =U43-(U43*3%) -> 0.10481761
A44: Finance Cost
A45: Finance Cost | B45: ₹ Lakhs | H45: ='Income Statement-Historic'!C23 -> 2267 | I45: ='Income Statement-Historic'!D23 -> 1478 | J45: ='Income Statement-Historic'!E23 -> 464 | K45: ='Income Statement-Historic'!F23 -> 689 | L45: ='Income Statement-Historic'!G23 -> 1286 | M45: =M46*M17 -> 1938.8088 | N45: =N46*N17 -> 2074.5254 | O45: =O46*O17 -> 2209.3696 | P45: =P46*P17 -> 2352.9786 | Q45: =Q46*Q17 -> 2494.1573 | R45: =R46*R17 -> 2643.8067 | S45: =S46*S17 -> 2789.2161 | T45: =T46*T17 -> 2942.623 | ... V45: =V46*V17 -> 3244.2418
A46: Finacne cost as % of Revenue | B46: % of Revenue | H46: =H45/H17 -> 0.0022256562 | I46: =I45/I17 -> 0.0011261879 | J46: =J45/J17 -> 0.00027866044 | K46: =K45/K17 -> 0.00037487357 | L46: =L45/L17 -> 0.00066259492 | M46: =AVERAGE(H46:L46) -> 0.00093359461 | N46: =M46 -> 0.00093359461 | O46: =N46 -> 0.00093359461 | P46: =O46 -> 0.00093359461 | Q46: =P46 -> 0.00093359461 | R46: =Q46 -> 0.00093359461 | S46: =R46 -> 0.00093359461 | T46: =S46 -> 0.00093359461 | U46: =T46 -> 0.00093359461 | V46: =U46 -> 0.00093359461
A47: Depreciation & Amortisation
A48: Depreciation and amortisation expense | B48: ₹ Lakhs | H48: ='Income Statement-Historic'!C24 -> 23201 | I48: ='Income Statement-Historic'!D24 -> 21719 | J48: ='Income Statement-Historic'!E24 -> 21059 | K48: ='Income Statement-Historic'!F24 -> 21190 | L48: ='Income Statement-Historic'!G24 -> 23298 | M48: =M49*M17 -> 31361.449 | N48: =N49*N17 -> 33556.751 | O48: =O49*O17 -> 35737.939 | P48: =P49*P17 -> 38060.905 | Q48: =Q49*Q17 -> 40344.56 | R48: =R49*R17 -> 42765.233 | S48: =S49*S17 -> 45117.321 | T48: =T49*T17 -> 47598.774 | ... V48: =V49*V17 -> 52477.648
A49: D&A as % of Revenue | B49: % of Revenue | H49: =H48/H17 -> 0.022777878 | I49: =I48/I17 -> 0.016549171 | J49: =J48/J17 -> 0.01264722 | K49: =K48/K17 -> 0.011529131 | L49: =L48/L17 -> 0.012003994 | M49: =AVERAGE(H49:L49) -> 0.015101479 | N49: =M49 -> 0.015101479 | O49: =N49 -> 0.015101479 | P49: =O49 -> 0.015101479 | Q49: =P49 -> 0.015101479 | R49: =Q49 -> 0.015101479 | S49: =R49 -> 0.015101479 | T49: =S49 -> 0.015101479 | U49: =T49 -> 0.015101479 | V49: =U49 -> 0.015101479
A50: Total Expenses | H50: =-SUM(H48,H45,H42,H36,H38,H31,H29,H27,H25) -> -1005938 | I50: =-SUM(I48,I45,I42,I36,I38,I31,I29,I27,I25) -> -1265927 | J50: =-SUM(J48,J45,J42,J36,J38,J31,J29,J27,J25) -> -1625009 | K50: =-SUM(K48,K45,K42,K36,K38,K31,K29,K27,K25) -> -1790213 | L50: =-SUM(L48,L45,L42,L36,L38,L31,L29,L27,L25) -> -1881357 | M50: =-SUM(M48,M45,M42,M36,M38,M31,M29,M27,M25) -> -2029566.1 | N50: =-SUM(N48,N45,N42,N36,N38,N31,N29,N27,N25) -> -2161362.5 | O50: =-SUM(O48,O45,O42,O36,O38,O31,O29,O27,O25) -> -2258938.3 | ... V50: =-SUM(V48,V45,V42,V36,V38,V31,V29,V27,V25) -> -3040773.5
A52: PAT | H52: =FS!D25 -> 11383 | I52: =FS!E25 -> 36608 | J52: =FS!F25 -> 30468 | K52: =FS!G25 -> 41086 | L52: =FS!H25 -> 44241 | M52: =FS!I25 -> 37665.001 | N52: =FS!J25 -> 47492.828 | O52: =FS!K25 -> 80618.739 | ... V52: =FS!R25 -> 311759.37
I53: =(I52/H52)-1 -> 2.2160239 | J53: =(J52/I52)-1 -> -0.1677229 | K53: =(K52/J52)-1 -> 0.34849678 | L53: =(L52/K52)-1 -> 0.076790147 | M53: =(M52/L52)-1 -> -0.14864038 | N53: =(N52/M52)-1 -> 0.26092731 | O53: =(O52/N52)-1 -> 0.69749291 | P53: =(P52/O52)-1 -> 0.4008436 | ... V53: =(V52/U52)-1 -> 0.12399065
A54: EBIT | H54: =FS!D26 -> 19208 | I54: =FS!E26 -> 50922 | J54: =FS!F26 -> 42195 | K54: =FS!G26 -> 55803 | L54: =FS!H26 -> 61797 | M54: =FS!I26 -> 55745.953 | N54: =FS!J26 -> 69921.423 | O54: =FS!K26 -> 117379 | ... V54: =FS!R26 -> 448614.76
I55: =(I54/H54)-1 -> 1.6510829 | J55: =(J54/I54)-1 -> -0.17137976 | K55: =(K54/J54)-1 -> 0.32250267 | L55: =(L54/K54)-1 -> 0.10741358 | M55: =(M54/L54)-1 -> -0.097918139 | N55: =(N54/M54)-1 -> 0.25428698 | O55: =(O54/N54)-1 -> 0.67872723 | P55: =(P54/O54)-1 -> 0.39452217 | ... V55: =(V54/U54)-1 -> 0.12341816
A56: EBITDA | H56: =H54+H48 -> 42409 | I56: =I54+I48 -> 72641 | J56: =J54+J48 -> 63254 | K56: =K54+K48 -> 76993 | L56: =L54+L48 -> 85095 | M56: =M54+M48 -> 87107.402 | N56: =N54+N48 -> 103478.17 | O56: =O54+O48 -> 153116.94 | ... V56: =V54+V48 -> 501092.41
I57: =(I56/H56)-1 -> 0.71286755 | J57: =(J56/I56)-1 -> -0.12922454 | K57: =(K56/J56)-1 -> 0.21720366 | L57: =(L56/K56)-1 -> 0.10523035 | M57: =(M56/L56)-1 -> 0.023648886 | N57: =(N56/M56)-1 -> 0.18793778 | O57: =(O56/N56)-1 -> 0.47970273 | P57: =(P56/O56)-1 -> 0.31761073 | ... V57: =(V56/U56)-1 -> 0.11525152
A58: GROSS | H58: =D210 -> 17663
A60: Working Capital
A61: Working Capital Assumptions
A62: Days in Period | B62: Days | H62: =H6 -> 365 | I62: =I6 -> 365 | J62: =J6 -> 365 | K62: =K6 -> 366 | L62: =L6 -> 365 | M62: =M6 -> 365 | N62: =N6 -> 365 | O62: =O6 -> 366 | ... V62: =V6 -> 365
A63: Trade Receivables Days | B63: Days | H63: ='Balance Sheet- Historic'!C21/'Working '!H17*'Working '!H62 -> 49.988548 | I63: ='Balance Sheet- Historic'!D21/'Working '!I17*'Working '!I62 -> 34.899931 | J63: ='Balance Sheet- Historic'!E21/'Working '!J17*'Working '!J62 -> 30.84914 | K63: ='Balance Sheet- Historic'!F21/'Working '!K17*'Working '!K62 -> 46.076556 | L63: ='Balance Sheet- Historic'!G21/'Working '!L17*'Working '!L62 -> 53.797449 | M63: =AVERAGE(H63:L63) -> 43.122325 | N63: =M63 -> 43.122325 | O63: =N63 -> 43.122325 | P63: =O63 -> 43.122325 | Q63: =P63 -> 43.122325 | R63: =Q63 -> 43.122325 | S63: =R63 -> 43.122325 | T63: =S63 -> 43.122325 | U63: =T63 -> 43.122325 | V63: =U63 -> 43.122325
A64: Inventory Days | B64: Days | H64: ='Balance Sheet- Historic'!C20/('Working '!H25+'Working '!H27+'Working '!H29)*'Working '!H62 -> 204.44187 | I64: ='Balance Sheet- Historic'!D20/('Working '!I25+'Working '!I27+'Working '!I29)*'Working '!I62 -> 116.73159 | J64: ='Balance Sheet- Historic'!E20/('Working '!J25+'Working '!J27+'Working '!J29)*'Working '!J62 -> 122.1821 | K64: ='Balance Sheet- Historic'!F20/('Working '!K25+'Working '!K27+'Working '!K29)*'Working '!K62 -> 107.67867 | L64: ='Balance Sheet- Historic'!G20/('Working '!L25+'Working '!L27+'Working '!L29)*'Working '!L62 -> 116.40442 | M64: =AVERAGE(H64:L64) -> 133.48773 | N64: =M64 -> 133.48773 | O64: =N64 -> 133.48773 | P64: =O64 -> 133.48773 | Q64: =P64 -> 133.48773 | R64: =Q64 -> 133.48773 | S64: =R64 -> 133.48773 | T64: =S64 -> 133.48773 | U64: =T64 -> 133.48773 | V64: =U64 -> 133.48773
A65: Trade Payables Days | B65: Days | H65: =SUM('Balance Sheet- Historic'!C46:C47)/SUM('Working '!H25,'Working '!H27)*'Working '!H62 -> 110.64913 | I65: =SUM('Balance Sheet- Historic'!D46:D47)/SUM('Working '!I25,'Working '!I27)*'Working '!I62 -> 80.213977 | J65: =SUM('Balance Sheet- Historic'!E46:E47)/SUM('Working '!J25,'Working '!J27)*'Working '!J62 -> 60.617039 | K65: =SUM('Balance Sheet- Historic'!F46:F47)/SUM('Working '!K25,'Working '!K27)*'Working '!K62 -> 74.081843 | L65: =SUM('Balance Sheet- Historic'!G46:G47)/SUM('Working '!L25,'Working '!L27)*'Working '!L62 -> 81.974838 | M65: =AVERAGE(H65:L65) -> 81.507366 | N65: =M65 -> 81.507366 | O65: =N65 -> 81.507366 | P65: =O65 -> 81.507366 | Q65: =P65 -> 81.507366 | R65: =Q65 -> 81.507366 | S65: =R65 -> 81.507366 | T65: =S65 -> 81.507366 | U65: =T65 -> 81.507366 | V65: =U65 -> 81.507366
A66: Accounts Receivable
A67: Beginning Balance | B67: ₹ Lakhs | H67: 0 | I67: =H70 -> 139499 | J67: =I70 -> 125486 | K67: =J70 -> 140732 | L67: =K70 -> 231384 | M67: =L70 -> 286063 | N67: =M70 -> 245349.93 | O67: =N70 -> 262524.43 | P67: =O70 -> 278824.61 | ... V67: =U70 -> 390998.32
A68: Addition – Revenue from Contracts with Customers | B68: ₹ Lakhs | H68: =H17 -> 1018576 | I68: =I17 -> 1312392 | J68: =J17 -> 1665109 | K68: =K17 -> 1837953 | L68: =L17 -> 1940854 | M68: =M17 -> 2076713.8 | N68: =N17 -> 2222083.7 | O68: =O17 -> 2366519.2 | ... V68: =V17 -> 3475000.6
A69: Reduction – Cash from Customers | B69: ₹ Lakhs | H69: =-(H67+H68-H70) -> -879077 | I69: =-(I67+I68-I70) -> -1326405 | J69: =-(J67+J68-J70) -> -1649863 | K69: =-(K67+K68-K70) -> -1747301 | L69: =-(L67+L68-L70) -> -1886175 | M69: =-(M67+M68-M70) -> -2117426.8 | N69: =-(N67+N68-N70) -> -2204909.2 | O69: =-(O67+O68-O70) -> -2350219 | ... V69: =-(V67+V68-V70) -> -3455450.7
A70: Ending Balance | B70: ₹ Lakhs | H70: ='Balance Sheet- Historic'!C21 -> 139499 | I70: ='Balance Sheet- Historic'!D21 -> 125486 | J70: ='Balance Sheet- Historic'!E21 -> 140732 | K70: ='Balance Sheet- Historic'!F21 -> 231384 | L70: ='Balance Sheet- Historic'!G21 -> 286063 | M70: =M68*M63/M62 -> 245349.93 | N70: =N68*N63/N62 -> 262524.43 | O70: =O68*O63/O62 -> 278824.61 | P70: =P68*P63/P62 -> 297761.77 | Q70: =Q68*Q63/Q62 -> 315627.48 | R70: =R68*R63/R62 -> 334565.13 | S70: =S68*S63/S62 -> 352001.82 | T70: =T68*T63/T62 -> 372379.35 | ... V70: =V68*V63/V62 -> 410548.23
A72: Inventory
A73: Beginning Balance | B73: ₹ Lakhs | H73: 0 | I73: =H76 -> 113668 | J73: =I76 -> 93581 | K73: =J76 -> 142781 | L73: =K76 -> 136874 | M73: =L76 -> 161643 | N73: =M76 -> 180220.8 | O73: =N76 -> 189079.12 | P73: =O76 -> 191042.56 | ... V73: =U76 -> 237876.29
A74: Addition – Purchases | B74: ₹ Lakhs | H74: =H76-H73-H75 -> 316605 | I74: =I76-I73-I75 -> 272525 | J74: =J76-J73-J75 -> 475736 | K74: =K76-K73-K75 -> 459328 | L74: =L76-L73-L75 -> 531620 | M74: =M76-M73-M75 -> 511361.6 | N74: =N76-N73-N75 -> 525863.74 | O74: =O76-O73-O75 -> 525768.72 | ... V74: =V76-V73-V75 -> 694848.64
A75: Reduction – Cost of Goods Sold | B75: ₹ Lakhs | H75: =-H33 -> -202937 | I75: =-I33 -> -292612 | J75: =-J33 -> -426536 | K75: =-K33 -> -465235 | L75: =-L33 -> -506851 | M75: =-M33 -> -492783.8 | N75: =-N33 -> -517005.42 | O75: =-O33 -> -523805.28 | ... V75: =-V33 -> -682954.82
A76: Ending Balance | B76: ₹ Lakhs | H76: ='Balance Sheet- Historic'!C20 -> 113668 | I76: ='Balance Sheet- Historic'!D20 -> 93581 | J76: ='Balance Sheet- Historic'!E20 -> 142781 | K76: ='Balance Sheet- Historic'!F20 -> 136874 | L76: ='Balance Sheet- Historic'!G20 -> 161643 | M76: =M64/M62*M33 -> 180220.8 | N76: =N64/N62*N33 -> 189079.12 | O76: =O64/O62*O33 -> 191042.56 | P76: =P64/P62*P33 -> 196082.97 | Q76: =Q64/Q62*Q33 -> 199773.5 | R76: =R64/R62*R33 -> 203543.36 | S76: =S64/S62*S33 -> 214151.53 | T76: =T64/T62*T33 -> 226548.85 | ... V76: =V64/V62*V33 -> 249770.11
A78: Accounts Payable
A79: Beginning Balance | B79: ₹ Lakhs | H79: 0 | I79: =H82 -> 61808 | J79: =I82 -> 63800 | K79: =J82 -> 71698 | L79: =K82 -> 94845 | M79: =L82 -> 114955 | N79: =M82 -> 110042.49 | O79: =N82 -> 115451.37 | P79: =O82 -> 116650.24 | ... V79: =U82 -> 145246.83
A80: Addition - COGS | B80: ₹ Lakhs | H80: =H33 -> 202937 | I80: =I33 -> 292612 | J80: =J33 -> 426536 | K80: =K33 -> 465235 | L80: =L33 -> 506851 | M80: =M33 -> 492783.8 | N80: =N33 -> 517005.42 | O80: =O33 -> 523805.28 | ... V80: =V33 -> 682954.82
A81: Reduction – Cash Paid to Suppliers | B81: ₹ Lakhs | H81: =-(H79+H80-H82) -> -141129 | I81: =-(I79+I80-I82) -> -290620 | J81: =-(J79+J80-J82) -> -418638 | K81: =-(K79+K80-K82) -> -442088 | L81: =-(L79+L80-L82) -> -486741 | M81: =-(M79+M80-M82) -> -497696.31 | N81: =-(N79+N80-N82) -> -511596.54 | O81: =-(O79+O80-O82) -> -522606.41 | ... V81: =-(V79+V80-V82) -> -675692.48
A82: Ending Balance | B82: ₹ Lakhs | H82: =SUM('Balance Sheet- Historic'!C46:C47) -> 61808 | I82: =SUM('Balance Sheet- Historic'!D46:D47) -> 63800 | J82: =SUM('Balance Sheet- Historic'!E46:E47) -> 71698 | K82: =SUM('Balance Sheet- Historic'!F46:F47) -> 94845 | L82: =SUM('Balance Sheet- Historic'!G46:G47) -> 114955 | M82: =M33/M62*M65 -> 110042.49 | N82: =N33/N62*N65 -> 115451.37 | O82: =O33/O62*O65 -> 116650.24 | P82: =P33/P62*P65 -> 119727.9 | Q82: =Q33/Q62*Q65 -> 121981.34 | R82: =R33/R62*R65 -> 124283.21 | S82: =S33/S62*S65 -> 130760.54 | T82: =T33/T62*T65 -> 138330.32 | ... V82: =V33/V62*V65 -> 152509.17
A84: Net Working Capital
A85: Trade Receivables | B85: ₹ Lakhs | H85: =H70 -> 139499 | I85: =I70 -> 125486 | J85: =J70 -> 140732 | K85: =K70 -> 231384 | L85: =L70 -> 286063 | M85: =M70 -> 245349.93 | N85: =N70 -> 262524.43 | O85: =O70 -> 278824.61 | ... V85: =V70 -> 410548.23
A86: Inventory | B86: ₹ Lakhs | H86: =H76 -> 113668 | I86: =I76 -> 93581 | J86: =J76 -> 142781 | K86: =K76 -> 136874 | L86: =L76 -> 161643 | M86: =M76 -> 180220.8 | N86: =N76 -> 189079.12 | O86: =O76 -> 191042.56 | ... V86: =V76 -> 249770.11
A87: Less: Trade Payables | B87: ₹ Lakhs | H87: =-H82 -> -61808 | I87: =-I82 -> -63800 | J87: =-J82 -> -71698 | K87: =-K82 -> -94845 | L87: =-L82 -> -114955 | M87: =-M82 -> -110042.49 | N87: =-N82 -> -115451.37 | O87: =-O82 -> -116650.24 | ... V87: =-V82 -> -152509.17
A88: Net Working Capital | B88: ₹ Lakhs | H88: =SUM(H85:H87) -> 191359 | I88: =SUM(I85:I87) -> 155267 | J88: =SUM(J85:J87) -> 211815 | K88: =SUM(K85:K87) -> 273413 | L88: =SUM(L85:L87) -> 332751 | M88: =SUM(M85:M87) -> 315528.24 | N88: =SUM(N85:N87) -> 336152.18 | O88: =SUM(O85:O87) -> 353216.93 | ... V88: =SUM(V85:V87) -> 507809.16
A89: Change in Net Working Capital | B89: ₹ Lakhs | I89: =I88-H88 -> -36092 | J89: =J88-I88 -> 56548 | K89: =K88-J88 -> 61598 | L89: =L88-K88 -> 59338 | M89: =M88-L88 -> -17222.762 | N89: =N88-M88 -> 20623.943 | O89: =O88-N88 -> 17064.752 | P89: =P88-O88 -> 20899.899 | ... V89: =V88-U88 -> 24181.389
A91: Capital Expenditure
A92: CAPEX
A93: CAPEX | B93: ₹ Lakhs | H93: =H100 -> 20282 | I93: =-I100 -> -16174 | J93: =-J100 -> -11595 | K93: =-K100 -> -23200 | L93: =-L100 -> -28703 | M93: =M17*M94 -> -11125.806 | N93: =N17*N94 -> -11904.612 | O93: =O17*O94 -> -12678.412 | P93: =P17*P94 -> -13502.509 | Q93: =Q17*Q94 -> -14312.659 | R93: =R17*R94 -> -15171.419 | S93: =S17*S94 -> -16005.847 | T93: =T17*T94 -> -16886.168 | ... V93: =V17*V94 -> -18617.001
A94: CAPEX as % of Revenue | B94: % of Revenue | H94: =H93/H17 -> 0.019912113 | I94: =I93/I17 -> -0.012324062 | J94: =J93/J17 -> -0.0069635081 | K94: =K93/K17 -> -0.012622738 | L94: =L93/L17 -> -0.014788851 | M94: =AVERAGE(H94:L94) -> -0.0053574093 | N94: =M94 -> -0.0053574093 | O94: =N94 -> -0.0053574093 | P94: =O94 -> -0.0053574093 | Q94: =P94 -> -0.0053574093 | R94: =Q94 -> -0.0053574093 | S94: =R94 -> -0.0053574093 | T94: =S94 -> -0.0053574093 | U94: =T94 -> -0.0053574093 | V94: =U94 -> -0.0053574093
A96: Depreciation & Amortisation | B96: ₹ Lakhs | H96: =H48 -> 23201 | I96: =I48 -> 21719 | J96: =J48 -> 21059 | K96: =K48 -> 21190 | L96: =L48 -> 23298 | M96: =M17*M97 -> 31361.449 | N96: =N17*N97 -> 33556.751 | O96: =O17*O97 -> 35737.939 | P96: =P17*P97 -> 38060.905 | Q96: =Q17*Q97 -> 40344.56 | R96: =R17*R97 -> 42765.233 | S96: =S17*S97 -> 45117.321 | T96: =T17*T97 -> 47598.774 | ... V96: =V17*V97 -> 52477.648
A97: D&A as % of Revenue | B97: % of Revenue | H97: =H49 -> 0.022777878 | I97: =I49 -> 0.016549171 | J97: =J49 -> 0.01264722 | K97: =K49 -> 0.011529131 | L97: =L49 -> 0.012003994 | M97: =AVERAGE(H97:L97) -> 0.015101479 | N97: =M97 -> 0.015101479 | O97: =N97 -> 0.015101479 | P97: =O97 -> 0.015101479 | Q97: =P97 -> 0.015101479 | R97: =Q97 -> 0.015101479 | S97: =R97 -> 0.015101479 | T97: =S97 -> 0.015101479 | U97: =T97 -> 0.015101479 | V97: =U97 -> 0.015101479
A99: Beginning Net Fixed Assets | B99: ₹ Lakhs | H99: 210099 | I99: =H102 -> 207180 | J99: =I102 -> 201635 | K99: =J102 -> 192171 | L99: =K102 -> 194181 | M99: =L102 -> 199586 | N99: =M102 -> 179350.36 | O99: =N102 -> 157698.22 | P99: =O102 -> 134638.69 | ... V99: =U102 -> -35617.738 | Z99: ₹ lakh | AA99: FY2021 | AB99: FY2022 | AC99: FY2023 | AD99: FY2024 | AE99: FY2025
A100: Addition - CAPEX | B100: ₹ Lakhs | H100: =H102-H99-H101 -> 20282 | I100: =I102-I99-I101 -> 16174 | J100: =J102-J99-J101 -> 11595 | K100: =K102-K99-K101 -> 23200 | L100: =L102-L99-L101 -> 28703 | M100: =-M93 -> 11125.806 | N100: =-N93 -> 11904.612 | O100: =-O93 -> 12678.412 | P100: =-P93 -> 13502.509 | Q100: =-Q93 -> 14312.659 | R100: =-R93 -> 15171.419 | S100: =-S93 -> 16005.847 | T100: =-T93 -> 16886.168 | ... V100: =-V93 -> 18617.001 | Z100: Revenue | AA100: 1018576 | AB100: 1312392 | AC100: 1665109 | AD100: 1837953 | AE100: 1940854
A101: Reduction – D&A | B101: ₹ Lakhs | H101: =-H48 -> -23201 | I101: =-I48 -> -21719 | J101: =-J48 -> -21059 | K101: =-K48 -> -21190 | L101: =-L48 -> -23298 | M101: =-M96 -> -31361.449 | N101: =-N96 -> -33556.751 | O101: =-O96 -> -35737.939 | P101: =-P96 -> -38060.905 | Q101: =-Q96 -> -40344.56 | R101: =-R96 -> -42765.233 | S101: =-S96 -> -45117.321 | T101: =-T96 -> -47598.774 | ... V101: =-V96 -> -52477.648 | Z101: EBITDA* | AA101: 42409 | AB101: 72641 | AC101: 63254 | AD101: 76993 | AE101: 85095
A102: Ending Net Fixed Assets | B102: ₹ Lakhs | H102: =H107 -> 207180 | I102: =I107 -> 201635 | J102: =J107 -> 192171 | K102: =K107 -> 194181 | L102: =L107 -> 199586 | M102: =SUM(M99:M101) -> 179350.36 | N102: =SUM(N99:N101) -> 157698.22 | O102: =SUM(O99:O101) -> 134638.69 | P102: =SUM(P99:P101) -> 110080.29 | Q102: =SUM(Q99:Q101) -> 84048.393 | R102: =SUM(R99:R101) -> 56454.578 | S102: =SUM(S99:S101) -> 27343.104 | T102: =SUM(T99:T101) -> -3369.5021 | ... V102: =SUM(V99:V101) -> -69478.386 | Z102: EBIT | AA102: 19208 | AB102: 50922 | AC102: 42195 | AD102: 55803 | AE102: 61797
Z103: PAT | AA103: 11383 | AB103: 36608 | AC103: 30468 | AD103: 41086 | AE103: 44241
A104: PPE | B104: ₹ Lakhs | H104: ='Balance Sheet- Historic'!C10 -> 192203 | I104: ='Balance Sheet- Historic'!D10 -> 189008 | J104: ='Balance Sheet- Historic'!E10 -> 183235 | K104: ='Balance Sheet- Historic'!F10 -> 176009 | L104: ='Balance Sheet- Historic'!G10 -> 173512 | M104: =M102*AVERAGE($H$104/$H$107,$I$104/$I$107,$J$104/$J$107,$K$104/$K$107,$L$104/$L$107) -> 164800.15 | N104: =N102*AVERAGE($H$104/$H$107,$I$104/$I$107,$J$104/$J$107,$K$104/$K$107,$L$104/$L$107) -> 144904.59 | O104: =O102*AVERAGE($H$104/$H$107,$I$104/$I$107,$J$104/$J$107,$K$104/$K$107,$L$104/$L$107) -> 123715.82 | P104: =P102*AVERAGE($H$104/$H$107,$I$104/$I$107,$J$104/$J$107,$K$104/$K$107,$L$104/$L$107) -> 101149.78 | Q104: =Q102*AVERAGE($H$104/$H$107,$I$104/$I$107,$J$104/$J$107,$K$104/$K$107,$L$104/$L$107) -> 77229.777 | R104: =R102*AVERAGE($H$104/$H$107,$I$104/$I$107,$J$104/$J$107,$K$104/$K$107,$L$104/$L$107) -> 51874.573 | S104: =S102*AVERAGE($H$104/$H$107,$I$104/$I$107,$J$104/$J$107,$K$104/$K$107,$L$104/$L$107) -> 25124.832 | T104: =T102*AVERAGE($H$104/$H$107,$I$104/$I$107,$J$104/$J$107,$K$104/$K$107,$L$104/$L$107) -> -3096.1436 | ... V104: =V102*AVERAGE($H$104/$H$107,$I$104/$I$107,$J$104/$J$107,$K$104/$K$107,$L$104/$L$107) -> -63841.794
A105: CWIP | B105: ₹ Lakhs | H105: ='Balance Sheet- Historic'!C11 -> 12879 | I105: ='Balance Sheet- Historic'!D11 -> 10989 | J105: ='Balance Sheet- Historic'!E11 -> 7713 | K105: ='Balance Sheet- Historic'!F11 -> 17268 | L105: ='Balance Sheet- Historic'!G11 -> 25337 | M105: =M102*AVERAGE($H$105/$H$107,$I$105/$I$107,$J$105/$J$107,$K$105/$K$107,$L$105/$L$107) -> 13367.845 | N105: =N102*AVERAGE($H$105/$H$107,$I$105/$I$107,$J$105/$J$107,$K$105/$K$107,$L$105/$L$107) -> 11754.007 | O105: =O102*AVERAGE($H$105/$H$107,$I$105/$I$107,$J$105/$J$107,$K$105/$K$107,$L$105/$L$107) -> 10035.269 | P105: =P102*AVERAGE($H$105/$H$107,$I$105/$I$107,$J$105/$J$107,$K$105/$K$107,$L$105/$L$107) -> 8204.8139 | Q105: =Q102*AVERAGE($H$105/$H$107,$I$105/$I$107,$J$105/$J$107,$K$105/$K$107,$L$105/$L$107) -> 6264.5311 | R105: =R102*AVERAGE($H$105/$H$107,$I$105/$I$107,$J$105/$J$107,$K$105/$K$107,$L$105/$L$107) -> 4207.8313 | S105: =S102*AVERAGE($H$105/$H$107,$I$105/$I$107,$J$105/$J$107,$K$105/$K$107,$L$105/$L$107) -> 2038.0131 | T105: =T102*AVERAGE($H$105/$H$107,$I$105/$I$107,$J$105/$J$107,$K$105/$K$107,$L$105/$L$107) -> -251.1452 | ... V105: =V102*AVERAGE($H$105/$H$107,$I$105/$I$107,$J$105/$J$107,$K$105/$K$107,$L$105/$L$107) -> -5178.5583
A106: Intangible Assets | B106: ₹ Lakhs | H106: ='Balance Sheet- Historic'!C12 -> 2098 | I106: ='Balance Sheet- Historic'!D12 -> 1638 | J106: ='Balance Sheet- Historic'!E12 -> 1223 | K106: ='Balance Sheet- Historic'!F12 -> 904 | L106: ='Balance Sheet- Historic'!G12 -> 737 | M106: =M102*AVERAGE($H$106/$H$107,$I$106/$I$107,$J$106/$J$107,$K$106/$K$107,$L$106/$L$107) -> 1182.3589 | N106: =N102*AVERAGE($H$106/$H$107,$I$106/$I$107,$J$106/$J$107,$K$106/$K$107,$L$106/$L$107) -> 1039.6182 | O106: =O102*AVERAGE($H$106/$H$107,$I$106/$I$107,$J$106/$J$107,$K$106/$K$107,$L$106/$L$107) -> 887.5993 | P106: =P102*AVERAGE($H$106/$H$107,$I$106/$I$107,$J$106/$J$107,$K$106/$K$107,$L$106/$L$107) -> 725.69921 | Q106: =Q102*AVERAGE($H$106/$H$107,$I$106/$I$107,$J$106/$J$107,$K$106/$K$107,$L$106/$L$107) -> 554.08512 | R106: =R102*AVERAGE($H$106/$H$107,$I$106/$I$107,$J$106/$J$107,$K$106/$K$107,$L$106/$L$107) -> 372.17418 | S106: =S102*AVERAGE($H$106/$H$107,$I$106/$I$107,$J$106/$J$107,$K$106/$K$107,$L$106/$L$107) -> 180.25814 | T106: =T102*AVERAGE($H$106/$H$107,$I$106/$I$107,$J$106/$J$107,$K$106/$K$107,$L$106/$L$107) -> -22.213286 | ... V106: =V102*AVERAGE($H$106/$H$107,$I$106/$I$107,$J$106/$J$107,$K$106/$K$107,$L$106/$L$107) -> -458.03303
A107: Total Net Fixed Assets | B107: ₹ Lakhs | H107: =SUM(H104:H106) -> 207180 | I107: =SUM(I104:I106) -> 201635 | J107: =SUM(J104:J106) -> 192171 | K107: =SUM(K104:K106) -> 194181 | L107: =SUM(L104:L106) -> 199586 | M107: =SUM(M104:M106) -> 179350.36 | N107: =SUM(N104:N106) -> 157698.22 | O107: =SUM(O104:O106) -> 134638.69 | ... V107: =SUM(V104:V106) -> -69478.386
A109: Debt
A110: Debt Assumptions
X111: =X112 -> 20282 | Y111: =-Y112 -> 16174 | Z111: =-Z112 -> 11595 | AA111: =-AA112 -> 23200 | AB111: =-AB112 -> 28703 | AC111: =-AC112 -> 11125.806 | AD111: =-AD112 -> 11904.612 | AE111: =-AE112 -> 12678.412 | AF111: =-AF112 -> 13502.509 | ... AL111: =-AL112 -> 18617.001
A112: Borrowings | X112: 20282 | Y112: -16174 | Z112: -11595 | AA112: -23200 | AB112: -28703 | AC112: -11125.806 | AD112: -11904.612 | AE112: -12678.412 | AF112: -13502.509 | AG112: -14312.659 | AH112: -15171.419 | AI112: -16005.847 | AJ112: -16886.168 | AK112: -17730.477 | AL112: -18617.001
A113: Beginning Borrowings | H113: 0 | I113: =H117 -> 11541 | J113: =I117 -> 0 | K113: =J117 -> 0 | L113: =K117 -> 7741 | M113: =L117 -> 57485 | N113: =M117 -> 57485 | O113: =N117 -> 57485 | P113: =O117 -> 57485 | ... V113: =U117 -> 57485
A114: Addition – New Borrowings | H114: ='Cash flow-Historic'!B52+MAX('Cash flow-Historic'!B55,0) -> 25000 | I114: ='Cash flow-Historic'!C52+MAX('Cash flow-Historic'!C55,0) -> 0 | J114: ='Cash flow-Historic'!D52+MAX('Cash flow-Historic'!D55,0) -> 0 | K114: ='Cash flow-Historic'!E52+MAX('Cash flow-Historic'!E55,0) -> 7741 | L114: ='Cash flow-Historic'!F52+MAX('Cash flow-Historic'!F55,0) -> 49744 | M114: 0 | N114: 0 | O114: 0 | P114: 0 | Q114: 0 | R114: 0 | S114: 0 | T114: 0 | U114: 0 | V114: 0
A115: Reduction – Repayment | H115: ='Cash flow-Historic'!B53+MIN('Cash flow-Historic'!B55,0) -> -23541 | I115: ='Cash flow-Historic'!C53+MIN('Cash flow-Historic'!C55,0) -> -25017 | J115: ='Cash flow-Historic'!D53+MIN('Cash flow-Historic'!D55,0) -> 0 | K115: ='Cash flow-Historic'!E53+MIN('Cash flow-Historic'!E55,0) -> 0 | L115: ='Cash flow-Historic'!F53+MIN('Cash flow-Historic'!F55,0) -> 0 | M115: 0 | N115: 0 | O115: 0 | P115: 0 | Q115: 0 | R115: 0 | S115: 0 | T115: 0 | U115: 0 | V115: 0
...

Sheet Balance Sheet- Historic
A1: United Breweries Limited
A2: Annual Report- Balance Sheet Consolidated
A9: Particulars | B9: Note | C9: FY2021 | D9: FY2022 | E9: FY2023 | F9: FY2024 | G9: FY2025
A10: Property, plant and equipment | C10: 192203 | D10: 189008 | E10: 183235 | F10: 176009 | G10: 173512
A11: Capital work-in-progress | C11: 12879 | D11: 10989 | E11: 7713 | F11: 17268 | G11: 25337
A12: Intangible assets | C12: 2098 | D12: 1638 | E12: 1223 | F12: 904 | G12: 737
A13: Goodwill on consolidation | C13: 645 | D13: 645 | E13: 645 | F13: 645 | G13: 645
A14: Investments | C14: 606 | D14: 835 | E14: 805 | F14: 797 | G14: 785
A15: Other financial assets | C15: 4711 | D15: 4816 | E15: 4676 | F15: 3937 | G15: 4498
A16: Income tax assets (net) | C16: 20395 | D16: 20199 | E16: 22138 | F16: 21135 | G16: 22596
A17: Deferred tax asset (net) | C17: 3497 | D17: 3844 | E17: 4501 | F17: 5293 | G17: 6674
A18: Other non-current assets | C18: 15826 | D18: 25044 | E18: 34458 | F18: 37802 | G18: 42203
A19: Total non-current assets | C19: =SUM(C10:C18) -> 252860 | D19: =SUM(D10:D18) -> 257018 | E19: =SUM(E10:E18) -> 259394 | F19: =SUM(F10:F18) -> 263790 | G19: =SUM(G10:G18) -> 276987
A20: Inventories | C20: 113668 | D20: 93581 | E20: 142781 | F20: 136874 | G20: 161643
A21: Trade receivables | C21: 139499 | D21: 125486 | E21: 140732 | F21: 231384 | G21: 286063
A22: Cash and cash equivalents | C22: 40970 | D22: 86260 | E22: 32986 | F22: 12915 | G22: 34192
A23: Bank balances | C23: 5958 | D23: 4708 | E23: 6543 | F23: 8505 | G23: 10096
A24: Other financial assets | C24: 84 | D24: 115 | E24: 104 | F24: 254 | G24: 389
A25: Other current assets | C25: 31689 | D25: 27275 | E25: 45013 | F25: 51122 | G25: 52423
A26: Total current assets | C26: =SUM(C20:C25) -> 331868 | D26: =SUM(D20:D25) -> 337425 | E26: =SUM(E20:E25) -> 368159 | F26: =SUM(F20:F25) -> 441054 | G26: =SUM(G20:G25) -> 544806
A27: Assets held for sale | C27: 488 | D27: 488 | E27: 486 | F27: 493 | G27: 486
A28: Total assets | C28: =SUM(C19,C26,C27) -> 585216 | D28: =SUM(D19,D26,D27) -> 594931 | E28: =SUM(E19,E26,E27) -> 628039 | F28: =SUM(F19,F26,F27) -> 705337 | G28: =SUM(G19,G26,G27) -> 822279
A30: Equity Share Capital | C30: 2644 | D30: 2644 | E30: 2644 | F30: 2644 | G30: 2644
A31: Other Equity | C31: 355584 | D31: 390868 | E31: 393845 | F31: 415190 | G31: 433748
A32: Equity attributable to owners of the parent | C32: =SUM(C30:C31) -> 358228 | D32: =SUM(D30:D31) -> 393512 | E32: =SUM(E30:E31) -> 396489 | F32: =SUM(F30:F31) -> 417834 | G32: =SUM(G30:G31) -> 436392
A33: Non-controlling interests (NCI) | C33: 375 | D33: 414 | E33: 461 | F33: 522 | G33: 572
A34: Total Equity | C34: =SUM(C32:C33) -> 358603 | D34: =SUM(D32:D33) -> 393926 | E34: =SUM(E32:E33) -> 396950 | F34: =SUM(F32:F33) -> 418356 | G34: =SUM(G32:G33) -> 436964
A36: Non-current Liabilities
A37: Borrowings | C37: 11524 | D37: 0 | E37: 0 | F37: 0 | G37: 0
A38: Lease Liabilities | C38: — | D38: 606 | E38: 1074 | F38: 1690 | G38: 3569
A39: Other Financial Liabilities | C39: 1109 | D39: 2497 | E39: 1845 | F39: 1461 | G39: 2040
A40: Provisions | C40: 160 | D40: 441 | E40: 424 | F40: 917 | G40: 1405
A41: Total Non-current Liabilities | C41: 12793 | D41: 3544 | E41: 3343 | F41: 4068 | G41: 7014
A43: Current Liabilities
A44: Borrowings | C44: 17 | D44: 0 | E44: 0 | F44: 7741 | G44: 57485
A45: Lease Liabilities | C45: — | D45: 368 | E45: 488 | F45: 772 | G45: 944
A46: Trade Payables — MSME | C46: 5205 | D46: 9158 | E46: 9530 | F46: 12566 | G46: 12693
A47: Trade Payables — Others | C47: 56603 | D47: 54642 | E47: 62168 | F47: 82279 | G47: 102262
A48: Other Financial Liabilities | C48: 68177 | D48: 55810 | E48: 77835 | F48: 86664 | G48: 100578
A49: Other Current Liabilities | C49: 74710 | D49: 67261 | E49: 67518 | F49: 83327 | G49: 94769
A50: Provisions | C50: 9108 | D50: 10222 | E50: 10207 | F50: 9564 | G50: 9570
A51: Total Current Liabilities | C51: 213820 | D51: 197461 | E51: 227746 | F51: 282913 | G51: 378301
A52: Total Liabilities | C52: 226613 | D52: 201005 | E52: 231089 | F52: 286981 | G52: 385315
A53: Total Equity & Liabilities | C53: =C34+C52 -> 585216 | D53: =D34+D52 -> 594931 | E53: =E34+E52 -> 628039 | F53: =F34+F52 -> 705337 | G53: =G34+G52 -> 822279

Sheet Income Statement-Historic
A1: United Breweries Limited
A2: Annual Report- Income Statement Consolidated
A10: Particulars | B10: Note | C10: FY2021 | D10: FY2022 | E10: FY2023 | F10: FY2024 | G10: FY2025
A11: INCOME
A12: Revenue from contracts with customers (including excise duty) | B12: 21/19/20 | C12: 1018576 | D12: 1312392 | E12: 1665109 | F12: 1837953 | G12: 1940854
A13: Other income | B13: 22/20/21 | C13: 5025 | D13: 2979 | E13: 4943 | F13: 7374 | G13: 3590
A14: Total Income | C14: =SUM(C12:C13) -> 1023601 | D14: =SUM(D12:D13) -> 1315371 | E14: =SUM(E12:E13) -> 1670052 | F14: =SUM(F12:F13) -> 1845327 | G14: =SUM(G12:G13) -> 1944444
A16: EXPENSES
A17: Cost of materials consumed | B17: 23/21/22 | C17: 196516 | D17: 270729 | E17: 422476 | F17: 456755 | G17: 493673
A18: Purchase of stock-in-trade / traded goods | B18: 24/22/23 | C18: 7371 | D18: 19582 | E18: 9247 | F18: 11825 | G18: 18174
A19: Changes in inventories of finished goods, WIP and stock-in-trade | B19: 25/23/24 | C19: -950 | D19: 2301 | E19: -5187 | F19: -3345 | G19: -4996
A20: Excise duty on sale of goods/products | B20: — | C20: 594267 | D20: 728548 | E20: 915117 | F20: 1025685 | G20: 1049345
A21: Employee benefits expense | B21: 26/24/25 | C21: 48549 | D21: 52312 | E21: 41183 | F21: 45210 | G21: 52180
A22: Contract employee expense | B22: — | C22: — | D22: — | E22: 18368 | F22: 19525 | G22: 19666
A23: Finance costs | B23: 27/25/26 | C23: 2267 | D23: 1478 | E23: 464 | F23: 689 | G23: 1286
A24: Depreciation and amortisation expense | B24: 28/26/27 | C24: 23201 | D24: 21719 | E24: 21059 | F24: 21190 | G24: 23298
A25: Other expenses | B25: 29/27/28 | C25: 134717 | D25: 169258 | E25: 202282 | F25: 212679 | G25: 228731
A26: Total Expenses | C26: =-SUM(C17:C25) -> -1005938 | D26: =-SUM(D17:D25) -> -1265927 | E26: =-SUM(E17:E25) -> -1625009 | F26: =-SUM(F17:F25) -> -1790213 | G26: =-SUM(G17:G25) -> -1881357
A28: Profit before exceptional items and tax | C28: =SUM(C14,C26) -> 17663 | D28: =SUM(D14,D26) -> 49444 | E28: =SUM(E14,E26) -> 45043 | F28: =SUM(F14,F26) -> 55114 | G28: =SUM(G14,G26) -> 63087
A29: Exceptional items | B29: 30/28/29 | C29: -722 | D29: — | E29: -3312 | F29: — | G29: -2576
A30: Profit before tax | C30: =SUM(C28:C29) -> 16941 | D30: =SUM(D28:D29) -> 49444 | E30: =SUM(E28:E29) -> 41731 | F30: =SUM(F28:F29) -> 55114 | G30: =SUM(G28:G29) -> 60511
A32: Tax Expense
A33: Current tax | B33: 31/29/30 | C33: -6779 | D33: -13203 | E33: -12035 | F33: -14879 | G33: -17731
A34: Deferred tax (credit) | B34: 31/29/30 | C34: 1221 | D34: 367 | E34: 772 | F34: 851 | G34: 1461
A35: Total Tax Expense | C35: =SUM(C33:C34) -> -5558 | D35: =SUM(D33:D34) -> -12836 | E35: =SUM(E33:E34) -> -11263 | F35: =SUM(F33:F34) -> -14028 | G35: =SUM(G33:G34) -> -16270
A36: Profit for the year | C36: =SUM(C35,C30) -> 11383 | D36: =SUM(D35,D30) -> 36608 | E36: =SUM(E35,E30) -> 30468 | F36: =SUM(F35,F30) -> 41086 | G36: =SUM(G35,G30) -> 44241
A38: Other Comprehensive Income (OCI)
A39: Re-measurement gains/(losses) on defined benefit plans | C39: 1991 | D39: 80 | E39: 457 | F39: 232 | G39: 318
A40: Income tax effect on above | C40: -501 | D40: -20 | E40: -115 | F40: -59 | G40: -80
A41: Total OCI | C41: 1490 | D41: 60 | E41: 342 | F41: 173 | G41: 238
A42: Total Comprehensive Income | C42: 12873 | D42: 36668 | E42: 30810 | F42: 41259 | G42: 44479
A44: Profit attributable to:
A45: Equity shareholders of the Holding Company | C45: 11322 | D45: 36546 | E45: 30398 | F45: 41003 | G45: 44169
A46: Non-controlling interest | C46: 61 | D46: 62 | E46: 70 | F46: 83 | G46: 72
A47: Total Profit | C47: 11383 | D47: 36608 | E47: 30468 | F47: 41086 | G47: 44241
A49: OCI attributable to:
A50: Equity shareholders of the Holding Company | C50: 1490 | D50: 60 | E50: 342 | F50: 173 | G50: 238
A51: Non-controlling interest | C51: — | D51: — | E51: — | F51: — | G51: —
A52: Total OCI | C52: 1490 | D52: 60 | E52: 342 | F52: 173 | G52: 238
A54: Total Comprehensive Income attributable to:
A55: Equity shareholders of the Holding Company | C55: 12812 | D55: 36606 | E55: 30740 | F55: 41176 | G55: 44407
A56: Non-controlling interest | C56: 61 | D56: 62 | E56: 70 | F56: 83 | G56: 72
A57: Total Comprehensive Income | C57: 12873 | D57: 36668 | E57: 30810 | F57: 41259 | G57: 44479
A59: Earnings Per Share (₹)
A60: Basic EPS | B60: 32/30/31 | C60: 4.28 | D60: 13.82 | E60: 11.5 | F60: 15.51 | G60: 16.71
A61: Diluted EPS | B61: 32/30/31 | C61: 4.28 | D61: 13.82 | E61: 11.5 | F61: 15.51 | G61: 16.71

Sheet Cash flow-Historic
A1: United Breweries Limited
A2: Annual Report- Cash Flow Consolidated
A12: Particulars | B12: FY2021 | C12: FY2022 | D12: FY2023 | E12: FY2024 | F12: FY2025
A13: CASH FLOW FROM OPERATING ACTIVITIES
A14: Profit before tax | B14: 16941 | C14: 49444 | D14: 41731 | E14: 55114 | F14: 60511
A15: Depreciation and amortisation expense | B15: 23201 | C15: 21719 | D15: 21059 | E15: 21190 | F15: 23298
A16: Bad debts/advances written off | B16: 28 | C16: 301 | D16: 0 | E16: 6 | F16: 0
A17: Loss allowance for trade receivables | B17: 479 | C17: 1720 | D17: 818 | E17: 1274 | F17: 1099
A18: Provision for doubtful advances/deposits | B18: 966 | C18: 620 | D18: 181 | E18: 358 | F18: 11
A19: Unrealised exchange differences (net) | B19: -33 | C19: 48 | D19: -148 | E19: 11 | F19: 61
A20: Net gain on disposal of PPE | B20: -4 | C20: -8 | D20: -135 | E20: -37 | F20: -4
A21: Profit on sale of investments | B21: 0 | C21: -54 | D21: 0 | E21: 0 | F21: 0
A22: Liabilities no longer required written back | B22: -205 | C22: -479 | D22: -297 | E22: -730 | F22: 0
A23: Loss allowance no longer required written back | B23: -3380 | C23: -217 | D23: -4 | E23: -50 | F23: 0
A24: Impairment loss on PPE | B24: 4446 | C24: 0 | D24: 3312 | E24: 0 | F24: 0
A25: Impairment loss on goodwill | B25: 1776 | C25: 0 | D25: 0 | E25: 0 | F25: 0
... A39: Net cash from/(used in) operating activities | B39: 62028 | C39: 89962 | D39: -11957 | E39: 6950 | F39: 23505
A41: CASH FLOW FROM INVESTING ACTIVITIES
A42: Purchase of PPE including CWIP, intangible assets and capital advances | B42: -20066 | C42: -17355 | D42: -15628 | E42: -19150 | F42: -25830
A43: Proceeds from sale of PPE | B43: 5091 | C43: 77 | D43: 198 | E43: 82 | F43: 14
A44: Investments in equity and debt securities | B44: -579 | C44: -300 | D44: 0 | E44: -1 | F44: 0
A45: Proceeds from sale of equity and debt securities | B45: 0 | C45: 125 | D45: 30 | E45: 9 | F45: 12
A46: Investments in bank deposits >3 months | B46: -394 | C46: -173 | D46: -616 | E46: -167 | F46: -511
A47: Redemption/maturity of bank deposits >3 months | B47: 335 | C47: 122 | D47: 581 | E47: 61 | F47: 633
A48: Interest received | B48: 458 | C48: 1497 | D48: 3352 | E48: 4385 | F48: 1740
A49: Net cash used in investing activities | B49: -15155 | C49: -16007 | D49: -12083 | E49: -14781 | F49: -23942
A51: CASH FLOW FROM FINANCING ACTIVITIES
A52: Proceeds from long-term borrowings | B52: 25000 | C52: 0 | D52: 0 | E52: 0 | F52: 0
A53: Repayment of long-term borrowings | B53: -7543 | C53: -25000 | D53: 0 | E53: 0 | F53: 0
A54: Repayment of principal portion of lease liabilities | B54: -853 | C54: -492 | D54: -998 | E54: -727 | F54: -953
A55: (Repayment of)/proceeds from short-term borrowings | B55: -15998 | C55: -17 | D55: 0 | E55: 7741 | F55: 49744
A56: Interest paid | B56: -2813 | C56: -1812 | D56: -451 | E56: 598 | F56: -614
A57: Dividend paid | B57: -6610 | C57: -1344 | D57: -27785 | E57: -19852 | F57: -26463
A58: Dividend distribution tax paid | B58: 0 | C58: 0 | D58: 0 | E58: 0 | F58: 0
A59: Net cash from/(used in) financing activities | B59: -8817 | C59: -28665 | D59: -29234 | E59: -12240 | F59: 21714
A61: Net increase/(decrease) in cash and cash equivalents | B61: 38041 | C61: 45290 | D61: -53274 | E61: -20071 | F61: 21277
A62: Cash and cash equivalents at beginning of year | B62: 2899 | C62: 40970 | D62: 86260 | E62: 32986 | F62: 12915
A63: Cash and cash equivalents at end of year | B63: 40940 | C63: 86260 | D63: 32986 | E63: 12915 | F63: 34192

Sheet Assumptions
A1: United Breweries Limited
A2: Assumptions and Forecasts
C3: Period Start | H3: 43922 | I3: 44287 | J3: 44652 | K3: 45017 | L3: 45383 | M3: 45748 | N3: 46113 | O3: 46478 | P3: 46844 | Q3: 47209 | R3: 47574 | S3: 47939 | T3: 48305 | U3: 48670 | V3: 49035
C4: Period End | H4: 44286 | I4: 44651 | J4: 45016 | K4: 45382 | L4: 45747 | M4: 46112 | N4: 46477 | O4: 46843 | P4: 47208 | Q4: 47573 | R4: 47938 | S4: 48304 | T4: 48669 | U4: 49034 | V4: 49399
C5: Period Type | H5: Historical | I5: Historical | J5: Historical | K5: Historical | L5: Historical | M5: Forecast | N5: Forecast | O5: Forecast | P5: Forecast | Q5: Forecast | R5: Forecast | S5: Forecast | T5: Forecast | U5: Forecast | V5: Forecast
C6: Days | H6: =H4-H3+1 -> 365 | I6: =I4-I3+1 -> 365 | J6: =J4-J3+1 -> 365 | K6: =K4-K3+1 -> 366 | L6: =L4-L3+1 -> 365 | M6: =M4-M3+1 -> 365 | N6: =N4-N3+1 -> 365 | O6: =O4-O3+1 -> 366 | ... V6: =V4-V3+1 -> 365
A8: Timing
A10: Model Start Date | B10: Date | C10: 01-Apr-20
A11: Months in a period | B11: # | C11: 12
A12: Start of Forecast Period | B12: Date | C12: 01-Apr-25
A13: Number of Forecast Period | B13: # | C13: 10
A16: Revenue
A17: Revenue from Contracts with Customers
A18: Revenue from Contracts with Customers | B18: ₹ Lakhs | C18: Forecast based on recent historical growth trend, with gradual normalization toward a steady-state growth rate. | H18: ='Income Statement-Historic'!C12 -> 1018576 | I18: ='Income Statement-Historic'!D12 -> 1312392 | J18: ='Income Statement-Historic'!E12 -> 1665109 | K18: ='Income Statement-Historic'!F12 -> 1837953 | L18: ='Income Statement-Historic'!G12 -> 1940854
A19: Revenue Growth Rate | B19: % | I19: =IFERROR(I18/H18-1,"") -> 0.28845761 | J19: =IFERROR(J18/I18-1,"") -> 0.26875888 | K19: =IFERROR(K18/J18-1,"") -> 0.10380341 | L19: =IFERROR(L18/K18-1,"") -> 0.055986742 | M19: 0.07 | N19: 0.07 | O19: 0.065 | P19: 0.065 | Q19: 0.06 | R19: 0.06 | S19: 0.055 | T19: 0.055 | U19: 0.05 | V19: 0.05
A21: Other Income | B21: ₹ Lakhs | H21: ='Income Statement-Historic'!C13 -> 5025 | I21: ='Income Statement-Historic'!D13 -> 2979 | J21: ='Income Statement-Historic'!E13 -> 4943 | K21: ='Income Statement-Historic'!F13 -> 7374 | L21: ='Income Statement-Historic'!G13 -> 3590
A22: Other Income % of Revenue | B22: % | H22: =H21/H18 -> 0.0049333579 | I22: =I21/I18 -> 0.0022699011 | J22: =J21/J18 -> 0.0029685744 | K22: =K21/K18 -> 0.0040120721 | L22: =L21/L18 -> 0.0018497012 | M22: =AVERAGE(H22:L22) -> 0.0032067214 | N22: =M22 -> 0.0032067214 | O22: =N22 -> 0.0032067214 | P22: =O22 -> 0.0032067214 | Q22: =P22 -> 0.0032067214 | R22: =Q22 -> 0.0032067214 | S22: =R22 -> 0.0032067214 | T22: =S22 -> 0.0032067214 | U22: =T22 -> 0.0032067214 | V22: =U22 -> 0.0032067214
A25: Cost
A26: Cost of Sales
A27: Cost of Materials Consumed | B27: ₹ Lakhs | H27: ='Income Statement-Historic'!C17 -> 196516 | I27: ='Income Statement-Historic'!D17 -> 270729 | J27: ='Income Statement-Historic'!E17 -> 422476 | K27: ='Income Statement-Historic'!F17 -> 456755 | L27: ='Income Statement-Historic'!G17 -> 493673
A28: Cost of Materials % of Revenue | B28: % | H28: =H27/H18 -> 0.19293209 | I28: =I27/I18 -> 0.20628669 | J28: =J27/J18 -> 0.25372273 | K28: =K27/K18 -> 0.24851288 | L28: =L27/L18 -> 0.25435865 | M28: ='Working '!M26 -> 0.23116261 | N28: ='Working '!N26 -> 0.22653936 | O28: ='Working '!O26 -> 0.21521239 | P28: ='Working '!P26 -> 0.20660389 | Q28: ='Working '!Q26 -> 0.19833974 | R28: ='Working '!R26 -> 0.19040615 | S28: ='Working '!S26 -> 0.19040615 | T28: ='Working '!T26 -> 0.19040615 | ... V28: ='Working '!V26 -> 0.19040615
A30: Purchase of Stock-in-Trade / Traded Goods | B30: ₹ Lakhs | H30: ='Income Statement-Historic'!C18 -> 7371 | I30: ='Income Statement-Historic'!D18 -> 19582 | J30: ='Income Statement-Historic'!E18 -> 9247 | K30: ='Income Statement-Historic'!F18 -> 11825 | L30: ='Income Statement-Historic'!G18 -> 18174
A31: Purchases % of Revenue | B31: % | H31: =H30/H18 -> 0.0072365734 | I31: =I30/I18 -> 0.014920847 | J31: =J30/J18 -> 0.0055533902 | K31: =K30/K18 -> 0.006433788 | L31: =L30/L18 -> 0.0093639192 | M31: =AVERAGE(H31:L31) -> 0.0087017035 | N31: =M31 -> 0.0087017035 | O31: =N31 -> 0.0087017035 | P31: =O31 -> 0.0087017035 | Q31: =P31 -> 0.0087017035 | R31: =Q31 -> 0.0087017035 | S31: =R31 -> 0.0087017035 | T31: =S31 -> 0.0087017035 | U31: =T31 -> 0.0087017035 | V31: =U31 -> 0.0087017035
A33: Changes in Inventories | B33: ₹ Lakhs | H33: ='Income Statement-Historic'!C19 -> -950 | I33: ='Income Statement-Historic'!D19 -> 2301 | J33: ='Income Statement-Historic'!E19 -> -5187 | K33: ='Income Statement-Historic'!F19 -> -3345 | L33: ='Income Statement-Historic'!G19 -> -4996
A34: Changes in Inventories % of Revenue | B34: % | H34: =H33/H18 -> -0.00093267464 | I34: =I33/I18 -> 0.0017532871 | J34: =J33/J18 -> -0.0031151114 | K34: =K33/K18 -> -0.0018199595 | L34: =L33/L18 -> -0.0025741246 | M34: =AVERAGE(H34:L34) -> -0.0013377166 | N34: =M34 -> -0.0013377166 | O34: =N34 -> -0.0013377166 | P34: =O34 -> -0.0013377166 | Q34: =P34 -> -0.0013377166 | R34: =Q34 -> -0.0013377166 | S34: =R34 -> -0.0013377166 | T34: =S34 -> -0.0013377166 | U34: =T34 -> -0.0013377166 | V34: =U34 -> -0.0013377166
A36: Excise Duty on Sale of Goods/Products | B36: ₹ Lakhs | H36: ='Income Statement-Historic'!C20 -> 594267 | I36: ='Income Statement-Historic'!D20 -> 728548 | J36: ='Income Statement-Historic'!E20 -> 915117 | K36: ='Income Statement-Historic'!F20 -> 1025685 | L36: ='Income Statement-Historic'!G20 -> 1049345
A37: Excise Duty % of Revenue | B37: % | H37: =H36/H18 -> 0.58342922 | I37: =I36/I18 -> 0.55512987 | J37: =J36/J18 -> 0.54958384 | K37: =K36/K18 -> 0.55805834 | L37: =L36/L18 -> 0.54066148 | M37: ='Working '!M32 -> 0.55737255 | N37: ='Working '!N32 -> 0.55737255 | O37: ='Working '!O32 -> 0.55179882 | P37: ='Working '!P32 -> 0.54628084 | Q37: ='Working '!Q32 -> 0.54081803 | R37: ='Working '!R32 -> 0.53540985 | S37: ='Working '!S32 -> 0.53005575 | T37: ='Working '!T32 -> 0.52475519 | ... V37: ='Working '!V32 -> 0.51431256
A39: COGS | B39: ₹ Lakhs | C39: Excise duty is an indirect tax/levy on sales rather than a core operating cost incurred to produce the product; therefore, it is presented separately and excluded from COGS. | H39: =SUM(H33,H30,H27) -> 202937 | I39: =SUM(I33,I30,I27) -> 292612 | J39: =SUM(J33,J30,J27) -> 426536 | K39: =SUM(K33,K30,K27) -> 465235 | L39: =SUM(L33,L30,L27) -> 506851 | M39: ='Working '!M33 -> 492783.8 | N39: ='Working '!N33 -> 517005.42 | O39: ='Working '!O33 -> 523805.28 | P39: ='Working '!P33 -> 536156.26 | Q39: ='Working '!Q33 -> 546247.42 | R39: ='Working '!R33 -> 556555.47 | S39: ='Working '!S33 -> 587166.02 | T39: ='Working '!T33 -> 619460.16 | ... V39: ='Working '!V33 -> 682954.82
A40: COGS % of Revenue | B40: % | H40: =H39/H18 -> 0.19923599 | I40: =I39/I18 -> 0.22296082 | J40: =J39/J18 -> 0.25616101 | K40: =K39/K18 -> 0.25312671 | L40: =L39/L18 -> 0.26114844
A42: Employee Costs
A43: Employee Benefits Expense | B43: ₹ Lakhs | H43: ='Income Statement-Historic'!C21 -> 48549 | I43: ='Income Statement-Historic'!D21 -> 52312 | J43: ='Income Statement-Historic'!E21 -> 41183 | K43: ='Income Statement-Historic'!F21 -> 45210 | L43: ='Income Statement-Historic'!G21 -> 52180
A44: Employee Benefits % of Revenue | B44: % | H44: =H43/H18 -> 0.047663601 | I44: =I43/I18 -> 0.039860042 | J44: =J43/J18 -> 0.024732915 | K44: =K43/K18 -> 0.024598017 | L44: =L43/L18 -> 0.026885072 | M44: =AVERAGE(H44:L44) -> 0.03274793 | N44: =M44 -> 0.03274793 | O44: =N44 -> 0.03274793 | P44: =O44 -> 0.03274793 | Q44: =P44 -> 0.03274793 | R44: =Q44 -> 0.03274793 | S44: =R44 -> 0.03274793 | T44: =S44 -> 0.03274793 | U44: =T44 -> 0.03274793 | V44: =U44 -> 0.03274793
A46: Contract Employee Expense | B46: ₹ Lakhs | H46: ='Income Statement-Historic'!C22 -> — | I46: ='Income Statement-Historic'!D22 -> — | J46: ='Income Statement-Historic'!E22 -> 18368 | K46: ='Income Statement-Historic'!F22 -> 19525 | L46: ='Income Statement-Historic'!G22 -> 19666
A47: Contract Employee % of Revenue | B47: % | H47: =IFERROR([2]Working!H38/[2]Working!H17,"") | I47: =IFERROR([2]Working!I38/[2]Working!I17,"") | J47: =J46/J18 -> 0.01103111 | K47: =K46/K18 -> 0.010623231 | L47: =L46/L18 -> 0.010132653 | M47: =AVERAGE(J47:L47) -> 0.010595665 | N47: =M47 -> 0.010595665 | O47: =N47 -> 0.010595665 | P47: =O47 -> 0.010595665 | Q47: =P47 -> 0.010595665 | R47: =Q47 -> 0.010595665 | S47: =R47 -> 0.010595665 | T47: =S47 -> 0.010595665 | U47: =T47 -> 0.010595665 | V47: =U47 -> 0.010595665
A49: Other Operating Expenses
A50: Other Expenses | B50: ₹ Lakhs | H50: ='Income Statement-Historic'!C25 -> 134717 | I50: ='Income Statement-Historic'!D25 -> 169258 | J50: ='Income Statement-Historic'!E25 -> 202282 | K50: ='Income Statement-Historic'!F25 -> 212679 | L50: ='Income Statement-Historic'!G25 -> 228731
A51: Other Expenses % of Revenue | B51: % | H51: =H50/H18 -> 0.13226014 | I51: =I50/I18 -> 0.12896909 | J51: =J50/J18 -> 0.12148274 | K51: =K50/K18 -> 0.11571515 | L51: =L50/L18 -> 0.1178507 | M51: ='Working '!M43 -> 0.12325556 | N51: ='Working '!N43 -> 0.12325556 | O51: ='Working '!O43 -> 0.12202301 | P51: ='Working '!P43 -> 0.12080278 | Q51: ='Working '!Q43 -> 0.11959475 | R51: ='Working '!R43 -> 0.1183988 | S51: ='Working '!S43 -> 0.11484684 | T51: ='Working '!T43 -> 0.11140143 | ... V51: ='Working '!V43 -> 0.10481761
A53: Finance Cost
A54: Finance Cost | B54: ₹ Lakhs | H54: ='Income Statement-Historic'!C23 -> 2267 | I54: ='Income Statement-Historic'!D23 -> 1478 | J54: ='Income Statement-Historic'!E23 -> 464 | K54: ='Income Statement-Historic'!F23 -> 689 | L54: ='Income Statement-Historic'!G23 -> 1286
A55: Finance Cost % of Revenue | B55: % | H55: =H54/H18 -> 0.0022256562 | I55: =I54/I18 -> 0.0011261879 | J55: =J54/J18 -> 0.00027866044 | K55: =K54/K18 -> 0.00037487357 | L55: =L54/L18 -> 0.00066259492 | M55: =AVERAGE(H55:L55) -> 0.00093359461 | N55: =AVERAGE(I55:M55) -> 0.00067518229 | O55: =AVERAGE(J55:N55) -> 0.00058498116 | P55: =AVERAGE(K55:O55) -> 0.00064624531 | Q55: =AVERAGE(L55:P55) -> 0.00070051966 | R55: =AVERAGE(M55:Q55) -> 0.00070810461 | S55: =AVERAGE(N55:R55) -> 0.00066300661 | T55: =AVERAGE(O55:S55) -> 0.00066057147 | ... V55: =AVERAGE(Q55:U55) -> 0.00068157837
A57: Depreciation & Amortisation
A58: Depreciation & Amortisation | B58: ₹ Lakhs | H58: ='Income Statement-Historic'!C24 -> 23201 | I58: ='Income Statement-Historic'!D24 -> 21719 | J58: ='Income Statement-Historic'!E24 -> 21059 | K58: ='Income Statement-Historic'!F24 -> 21190 | L58: ='Income Statement-Historic'!G24 -> 23298
A59: D&A % of Revenue | B59: % | H59: =H58/H18 -> 0.022777878 | I59: =I58/I18 -> 0.016549171 | J59: =J58/J18 -> 0.01264722 | K59: =K58/K18 -> 0.011529131 | L59: =L58/L18 -> 0.012003994 | M59: =AVERAGE(H59:L59) -> 0.015101479 | N59: =M59 -> 0.015101479 | O59: =N59 -> 0.015101479 | P59: =O59 -> 0.015101479 | Q59: =P59 -> 0.015101479 | R59: =Q59 -> 0.015101479 | S59: =R59 -> 0.015101479 | T59: =S59 -> 0.015101479 | U59: =T59 -> 0.015101479 | V59: =U59 -> 0.015101479
A62: Working Capital
A63: Working Capital Assumptions
A65: Trade Receivable Days | B65: Days | H65: ='Balance Sheet- Historic'!C21/'Working '!H17*'Working '!H62 -> 49.988548 | I65: ='Balance Sheet- Historic'!D21/'Working '!I17*'Working '!I62 -> 34.899931 | J65: ='Balance Sheet- Historic'!E21/'Working '!J17*'Working '!J62 -> 30.84914 | K65: ='Balance Sheet- Historic'!F21/'Working '!K17*'Working '!K62 -> 46.076556 | L65: ='Balance Sheet- Historic'!G21/'Working '!L17*'Working '!L62 -> 53.797449 | M65: =AVERAGE(H65:L65) -> 43.122325 | N65: =M65 -> 43.122325 | O65: =N65 -> 43.122325 | P65: =O65 -> 43.122325 | Q65: =P65 -> 43.122325 | R65: =Q65 -> 43.122325 | S65: =R65 -> 43.122325 | T65: =S65 -> 43.122325 | U65: =T65 -> 43.122325 | V65: =U65 -> 43.122325
A67: Inventory Days | B67: Days | H67: ='Balance Sheet- Historic'!C20*Assumptions!H6/Assumptions!H39 -> 204.44187 | I67: ='Balance Sheet- Historic'!D20*Assumptions!I6/Assumptions!I39 -> 116.73159 | J67: ='Balance Sheet- Historic'!E20*Assumptions!J6/Assumptions!J39 -> 122.1821 | K67: ='Balance Sheet- Historic'!F20*Assumptions!K6/Assumptions!K39 -> 107.67867 | L67: ='Balance Sheet- Historic'!G20*Assumptions!L6/Assumptions!L39 -> 116.40442 | M67: =AVERAGE(H67:L67) -> 133.48773 | N67: =M67 -> 133.48773 | O67: =N67 -> 133.48773 | P67: =O67 -> 133.48773 | Q67: =P67 -> 133.48773 | R67: =Q67 -> 133.48773 | S67: =R67 -> 133.48773 | T67: =S67 -> 133.48773 | U67: =T67 -> 133.48773 | V67: =U67 -> 133.48773
A69: Trade Payable Days | B69: Days | H69: =SUM('Balance Sheet- Historic'!C46:C47)/SUM(Assumptions!H27,Assumptions!H30)*Assumptions!H6 -> 110.64913 | I69: =SUM('Balance Sheet- Historic'!D46:D47)/SUM(Assumptions!I27,Assumptions!I30)*Assumptions!I6 -> 80.213977 | J69: =SUM('Balance Sheet- Historic'!E46:E47)/SUM(Assumptions!J27,Assumptions!J30)*Assumptions!J6 -> 60.617039 | K69: =SUM('Balance Sheet- Historic'!F46:F47)/SUM(Assumptions!K27,Assumptions!K30)*Assumptions!K6 -> 74.081843 | L69: =SUM('Balance Sheet- Historic'!G46:G47)/SUM(Assumptions!L27,Assumptions!L30)*Assumptions!L6 -> 81.974838 | M69: =AVERAGE(H69:L69) -> 81.507366 | N69: =M69 -> 81.507366 | O69: =N69 -> 81.507366 | P69: =O69 -> 81.507366 | Q69: =P69 -> 81.507366 | R69: =Q69 -> 81.507366 | S69: =R69 -> 81.507366 | T69: =S69 -> 81.507366 | U69: =T69 -> 81.507366 | V69: =U69 -> 81.507366
A72: Capital Expenditure
A74: CAPEX | B74: ₹ Lakhs | H74: ='Working '!H93 -> -20282 | I74: ='Working '!I93 -> -16174 | J74: ='Working '!J93 -> -11595 | K74: ='Working '!K93 -> -23200 | L74: ='Working '!L93 -> -28703
A75: CAPEX % of Revenue | B75: % | H75: =H74/H18 -> -0.019912113 | I75: =I74/I18 -> -0.012324062 | J75: =J74/J18 -> -0.0069635081 | K75: =K74/K18 -> -0.012622738 | L75: =L74/L18 -> -0.014788851 | M75: =AVERAGE(H75:L75) -> -0.013322254 | N75: =M75 -> -0.013322254 | O75: =N75 -> -0.013322254 | P75: =O75 -> -0.013322254 | Q75: =P75 -> -0.013322254 | R75: =Q75 -> -0.013322254 | S75: =R75 -> -0.013322254 | T75: =S75 -> -0.013322254 | U75: =T75 -> -0.013322254 | V75: =U75 -> -0.013322254
A77: Depreciation & Amortisation | B77: ₹ Lakhs | H77: =H58 -> 23201 | I77: =I58 -> 21719 | J77: =J58 -> 21059 | K77: =K58 -> 21190 | L77: =L58 -> 23298
A78: D&A % of Revenue | B78: % | H78: =H59 -> 0.022777878 | I78: =I59 -> 0.016549171 | J78: =J59 -> 0.01264722 | K78: =K59 -> 0.011529131 | L78: =L59 -> 0.012003994 | M78: =M59 -> 0.015101479 | N78: =N59 -> 0.015101479 | O78: =O59 -> 0.015101479 | ... V78: =V59 -> 0.015101479
A80: Debt
A82: Debt Drawdown | B82: ₹ Lakhs | H82: ='Cash flow-Historic'!B52 -> 25000 | I82: ='Cash flow-Historic'!C52 -> 0 | J82: ='Cash flow-Historic'!D52 -> 0 | K82: ='Cash flow-Historic'!E52 -> 0 | L82: ='Cash flow-Historic'!F52 -> 0 | M82: 0 | N82: 0 | O82: 0 | P82: 0 | Q82: 0 | R82: 0 | S82: 0 | T82: 0 | U82: 0 | V82: 0
A83: Scheduled Repayment | H83: ='Cash flow-Historic'!B53 -> -7543 | I83: ='Cash flow-Historic'!C53 -> -25000 | J83: ='Cash flow-Historic'!D53 -> 0 | K83: ='Cash flow-Historic'!E53 -> 0 | L83: ='Cash flow-Historic'!F53 -> 0 | M83: 0 | N83: 0 | O83: 0 | P83: 0 | Q83: 0 | R83: 0 | S83: 0 | T83: 0 | U83: 0 | V83: 0
A84: Interest Rate | B84: % | C84: 0.085
B85: For the forecast period, I have assumed no incremental debt drawdown or scheduled repayment because UBL's available disclosures do not provide a fixed 10-year borrowing or repayment schedule. Rather than arbitrarily forecasting new debt or repayments, I have kept these at zero and carried forward the existing debt balance. This keeps the DCF assumption conservative and avoids introducing an unsupported financing assumption.
A88: NOTE
A100: Valuation Assumptions
A102: Risk-Free Rate | B102: % | C102: 0.071
A103: Equity Risk Premium | B103: % | C103: 0.065
A104: Beta | B104: x | C104: 0.92
A105: Cost of Equity | B105: % | C105: =C102+(C103*C104) -> 0.1308
A107: Effective Tax Rate | B107: % | C107: 0.3
B108: %
A109: Terminal Growth Rate | B109: % | C109: 0.04
A112: Colour Key
A113: Blue font | B113: Linked / historical values
A114: Blue font + yellow cell | B114: Forecast assumption / editable input
A115: Black font | B115: Formula / calculated value

Sheet Working 
A1: United Breweries Limited
A2: Working
C3: Period Start | H3: 43922 | I3: 44287 | J3: 44652 | K3: 45017 | L3: 45383 | M3: 45748 | N3: 46113 | O3: 46478 | P3: 46844 | Q3: 47209 | R3: 47574 | S3: 47939 | T3: 48305 | U3: 48670 | V3: 49035
C4: Period End | H4: 44286 | I4: 44651 | J4: 45016 | K4: 45382 | L4: 45747 | M4: 46112 | N4: 46477 | O4: 46843 | P4: 47208 | Q4: 47573 | R4: 47938 | S4: 48304 | T4: 48669 | U4: 49034 | V4: 49399
C5: Period Type | H5: Historical | I5: Historical | J5: Historical | K5: Historical | L5: Historical | M5: Forecast | N5: Forecast | O5: Forecast | P5: Forecast | Q5: Forecast | R5: Forecast | S5: Forecast | T5: Forecast | U5: Forecast | V5: Forecast
C6: Days | H6: =H4-H3+1 -> 365 | I6: =I4-I3+1 -> 365 | J6: =J4-J3+1 -> 365 | K6: =K4-K3+1 -> 366 | L6: =L4-L3+1 -> 365 | M6: =M4-M3+1 -> 365 | N6: =N4-N3+1 -> 365 | O6: =O4-O3+1 -> 366 | ... V6: =V4-V3+1 -> 365
A7: Timing
A9: Model Start Date | B9: Date | C9: 43922
A10: Months in a period | B10: # | C10: 12
A11: Start of Forecast Period | B11: Date | C11: 45748
A12: Number of Forecast Period | B12: # | C12: 10
A15: Revenue
A16: Revenue from Contracts with Customers
A17: Revenue from contracts with customers (including excise duty) | B17: ₹ Lakhs | H17: ='Income Statement-Historic'!C12 -> 1018576 | I17: ='Income Statement-Historic'!D12 -> 1312392 | J17: ='Income Statement-Historic'!E12 -> 1665109 | K17: ='Income Statement-Historic'!F12 -> 1837953 | L17: ='Income Statement-Historic'!G12 -> 1940854 | M17: =L17*(1+M18) -> 2076713.8 | N17: =M17*(1+N18) -> 2222083.7 | O17: =N17*(1+O18) -> 2366519.2 | P17: =O17*(1+P18) -> 2520342.9 | Q17: =P17*(1+Q18) -> 2671563.5 | R17: =Q17*(1+R18) -> 2831857.3 | S17: =R17*(1+S18) -> 2987609.5 | T17: =S17*(1+T18) -> 3151928 | ... V17: =U17*(1+V18) -> 3475000.6
A18: Revenue Growth Rate | B18: % | I18: =I17/H17-1 -> 0.28845761 | J18: =J17/I17-1 -> 0.26875888 | K18: =K17/J17-1 -> 0.10380341 | L18: =L17/K17-1 -> 0.055986742 | M18: 0.07 | N18: 0.07 | O18: 0.065 | P18: 0.065 | Q18: 0.06 | R18: 0.06 | S18: 0.055 | T18: 0.055 | U18: 0.05 | V18: 0.05
A19: Other income | B19: ₹ Lakhs | H19: ='Income Statement-Historic'!C13 -> 5025 | I19: ='Income Statement-Historic'!D13 -> 2979 | J19: ='Income Statement-Historic'!E13 -> 4943 | K19: ='Income Statement-Historic'!F13 -> 7374 | L19: ='Income Statement-Historic'!G13 -> 3590 | M19: =M17*M20 -> 6659.4424 | N19: =N17*N20 -> 7125.6034 | O19: =O17*O20 -> 7588.7676 | P19: =P17*P20 -> 8082.0375 | Q19: =Q17*Q20 -> 8566.9598 | R19: =R17*R20 -> 9080.9774 | S19: =S17*S20 -> 9580.4311 | T19: =T17*T20 -> 10107.355 | ... V19: =V17*V20 -> 11143.359
A20: Other Income % of Revenue | B20: % | H20: =H19/H17 -> 0.0049333579 | I20: =I19/I17 -> 0.0022699011 | J20: =J19/J17 -> 0.0029685744 | K20: =K19/K17 -> 0.0040120721 | L20: =L19/L17 -> 0.0018497012 | M20: =AVERAGE(H20:L20) -> 0.0032067214 | N20: =$M$20 -> 0.0032067214 | O20: =$M$20 -> 0.0032067214 | P20: =$M$20 -> 0.0032067214 | Q20: =$M$20 -> 0.0032067214 | R20: =$M$20 -> 0.0032067214 | S20: =$M$20 -> 0.0032067214 | T20: =$M$20 -> 0.0032067214 | U20: =$M$20 -> 0.0032067214 | V20: =$M$20 -> 0.0032067214
A21: Total Revenue | H21: =SUM(H19,H17) -> 1023601 | I21: =SUM(I19,I17) -> 1315371 | J21: =SUM(J19,J17) -> 1670052 | K21: =SUM(K19,K17) -> 1845327 | L21: =SUM(L19,L17) -> 1944444 | M21: =SUM(M19,M17) -> 2083373.2 | N21: =SUM(N19,N17) -> 2229209.3 | O21: =SUM(O19,O17) -> 2374108 | ... V21: =SUM(V19,V17) -> 3486144
A23: Cost
A24: Cost of Sales
A25: Cost of materials consumed | B25: ₹ Lakhs | H25: ='Income Statement-Historic'!C17 -> 196516 | I25: ='Income Statement-Historic'!D17 -> 270729 | J25: ='Income Statement-Historic'!E17 -> 422476 | K25: ='Income Statement-Historic'!F17 -> 456755 | L25: ='Income Statement-Historic'!G17 -> 493673 | M25: =M17*M26 -> 480058.57 | N25: =N17*N26 -> 503389.42 | O25: =O17*O26 -> 509304.25 | P25: =P17*P26 -> 520712.66 | Q25: =Q17*Q26 -> 529877.21 | R25: =R17*R26 -> 539203.04 | S25: =S17*S26 -> 568859.21 | T25: =T17*T26 -> 600146.47 | ... V25: =V17*V26 -> 661661.48
A26: Cost as % of Revenue | B26: % of Revenue | H26: =H25/H17 -> 0.19293209 | I26: =I25/I17 -> 0.20628669 | J26: =J25/J17 -> 0.25372273 | K26: =K25/K17 -> 0.24851288 | L26: =L25/L17 -> 0.25435865 | M26: =AVERAGE(H26:L26) -> 0.23116261 | N26: =M26-(M26*2%) -> 0.22653936 | O26: =N26-(N26*5%) -> 0.21521239 | P26: =O26-(O26*4%) -> 0.20660389 | Q26: =P26-(P26*4%) -> 0.19833974 | R26: =Q26-(Q26*4%) -> 0.19040615 | S26: =R26 -> 0.19040615 | T26: =S26 -> 0.19040615 | U26: =T26 -> 0.19040615 | V26: =U26 -> 0.19040615
A27: Purchase of stock-in-trade / traded goods | B27: ₹ Lakhs | H27: ='Income Statement-Historic'!C18 -> 7371 | I27: ='Income Statement-Historic'!D18 -> 19582 | J27: ='Income Statement-Historic'!E18 -> 9247 | K27: ='Income Statement-Historic'!F18 -> 11825 | L27: ='Income Statement-Historic'!G18 -> 18174 | M27: =M17*M28 -> 18070.948 | N27: =N17*N28 -> 19335.914 | O27: =O17*O28 -> 20592.748 | P27: =P17*P28 -> 21931.277 | Q27: =Q17*Q28 -> 23247.154 | R27: =R17*R28 -> 24641.983 | S27: =S17*S28 -> 25997.292 | T27: =T17*T28 -> 27427.143 | ... V27: =V17*V28 -> 30238.425
A28: Cost as % of Revenue | B28: % of Revenue | H28: =H27/H17 -> 0.0072365734 | I28: =I27/I17 -> 0.014920847 | J28: =J27/J17 -> 0.0055533902 | K28: =K27/K17 -> 0.006433788 | L28: =L27/L17 -> 0.0093639192 | M28: =AVERAGE(H28:L28) -> 0.0087017035 | N28: =$M$28 -> 0.0087017035 | O28: =$M$28 -> 0.0087017035 | P28: =$M$28 -> 0.0087017035 | Q28: =$M$28 -> 0.0087017035 | R28: =$M$28 -> 0.0087017035 | S28: =$M$28 -> 0.0087017035 | T28: =$M$28 -> 0.0087017035 | U28: =$M$28 -> 0.0087017035 | V28: =$M$28 -> 0.0087017035
A29: Changes in inventories of finished goods, work-in-progress and stock-in-trade | B29: ₹ Lakhs | H29: ='Income Statement-Historic'!C19 -> -950 | I29: ='Income Statement-Historic'!D19 -> 2301 | J29: ='Income Statement-Historic'!E19 -> -5187 | K29: ='Income Statement-Historic'!F19 -> -3345 | L29: ='Income Statement-Historic'!G19 -> -4996 | M29: =M17*M30 -> -5345.72 | N29: =N17*N30 -> -5719.9204 | O29: =O17*O30 -> -6091.7152 | P29: =P17*P30 -> -6487.6767 | Q29: =Q17*Q30 -> -6876.9373 | R29: =R17*R30 -> -7289.5536 | S29: =S17*S30 -> -7690.479 | T29: =T17*T30 -> -8113.4553 | ... V29: =V17*V30 -> -8945.0845
A30: Changes in Inventories as % of Revenue | B30: % of Revenue | H30: =H29/H17 -> -0.00093267464 | I30: =I29/I17 -> 0.0017532871 | J30: =J29/J17 -> -0.0031151114 | K30: =K29/K17 -> -0.0018199595 | L30: =L29/L17 -> -0.0025741246 | M30: =L30 -> -0.0025741246 | N30: =M30 -> -0.0025741246 | O30: =N30 -> -0.0025741246 | P30: =O30 -> -0.0025741246 | Q30: =P30 -> -0.0025741246 | R30: =Q30 -> -0.0025741246 | S30: =R30 -> -0.0025741246 | T30: =S30 -> -0.0025741246 | ... V30: =U30 -> -0.0025741246
A31: Excise duty on sale of goods/products | B31: ₹ Lakhs | H31: ='Income Statement-Historic'!C20 -> 594267 | I31: ='Income Statement-Historic'!D20 -> 728548 | J31: ='Income Statement-Historic'!E20 -> 915117 | K31: ='Income Statement-Historic'!F20 -> 1025685 | L31: ='Income Statement-Historic'!G20 -> 1049345 | M31: =M17*M32 -> 1157503.3 | N31: =N17*N32 -> 1238528.5 | O31: =O17*O32 -> 1305842.5 | P31: =P17*P32 -> 1376815 | Q31: =Q17*Q32 -> 1444829.7 | R31: =R17*R32 -> 1516204.3 | S31: =S17*S32 -> 1583599.6 | T31: =T17*T32 -> 1653990.6 | ... V31: =V17*V32 -> 1787236.5
A32: Excise Duty as % of Revenue | B32: % of Revenue | H32: =H31/H17 -> 0.58342922 | I32: =I31/I17 -> 0.55512987 | J32: =J31/J17 -> 0.54958384 | K32: =K31/K17 -> 0.55805834 | L32: =L31/L17 -> 0.54066148 | M32: =AVERAGE(H32:L32) -> 0.55737255 | N32: =M32 -> 0.55737255 | O32: =N32-(N32*1%) -> 0.55179882 | P32: =O32-(O32*1%) -> 0.54628084 | Q32: =P32-(P32*1%) -> 0.54081803 | R32: =Q32-(Q32*1%) -> 0.53540985 | S32: =R32-(R32*1%) -> 0.53005575 | T32: =S32-(S32*1%) -> 0.52475519 | U32: =T32-(T32*1%) -> 0.51950764 | V32: =U32-(U32*1%) -> 0.51431256
A33: COGS | H33: =SUM(H25+H27+H29) -> 202937 | I33: =SUM(I25+I27+I29) -> 292612 | J33: =SUM(J25+J27+J29) -> 426536 | K33: =SUM(K25+K27+K29) -> 465235 | L33: =SUM(L25+L27+L29) -> 506851 | M33: =SUM(M25+M27+M29) -> 492783.8 | N33: =SUM(N25+N27+N29) -> 517005.42 | O33: =SUM(O25+O27+O29) -> 523805.28 | ... V33: =SUM(V25+V27+V29) -> 682954.82
A35: Employee Costs
A36: Employee benefits expense | B36: ₹ Lakhs | H36: ='Income Statement-Historic'!C21 -> 48549 | I36: ='Income Statement-Historic'!D21 -> 52312 | J36: ='Income Statement-Historic'!E21 -> 41183 | K36: ='Income Statement-Historic'!F21 -> 45210 | L36: ='Income Statement-Historic'!G21 -> 52180 | M36: =M17*M37 -> 68008.077 | N36: =N17*N37 -> 72768.642 | O36: =O17*O37 -> 77498.604 | P36: =P17*P37 -> 82536.013 | Q36: =Q17*Q37 -> 87488.174 | R36: =R17*R37 -> 92737.464 | S36: =S17*S37 -> 97838.025 | T36: =T17*T37 -> 103219.12 | ... V36: =V17*V37 -> 113799.08
A37: Employee Benefits Expense as % of Revenue | B37: % of Revenue | H37: =H36/H17 -> 0.047663601 | I37: =I36/I17 -> 0.039860042 | J37: =J36/J17 -> 0.024732915 | K37: =K36/K17 -> 0.024598017 | L37: =L36/L17 -> 0.026885072 | M37: =AVERAGE(H37:L37) -> 0.03274793 | N37: =M37 -> 0.03274793 | O37: =N37 -> 0.03274793 | P37: =O37 -> 0.03274793 | Q37: =P37 -> 0.03274793 | R37: =Q37 -> 0.03274793 | S37: =R37 -> 0.03274793 | T37: =S37 -> 0.03274793 | U37: =T37 -> 0.03274793 | V37: =U37 -> 0.03274793
A38: Contract employee expense | B38: ₹ Lakhs | H38: ='Income Statement-Historic'!C22 -> — | I38: ='Income Statement-Historic'!D22 -> — | J38: ='Income Statement-Historic'!E22 -> 18368 | K38: ='Income Statement-Historic'!F22 -> 19525 | L38: ='Income Statement-Historic'!G22 -> 19666 | M38: =M17*M39 -> 22004.163 | N38: =N17*N39 -> 23544.454 | O38: =O17*O39 -> 25074.844 | P38: =P17*P39 -> 26704.709 | Q38: =Q17*Q39 -> 28306.991 | R38: =R17*R39 -> 30005.411 | S38: =S17*S39 -> 31655.708 | T38: =T17*T39 -> 33396.772 | ... V38: =V17*V39 -> 36819.941
A39: Contract Employee Expense as % of Revenue | B39: % of Revenue | J39: =J38/J17 -> 0.01103111 | K39: =K38/K17 -> 0.010623231 | L39: =L38/L17 -> 0.010132653 | M39: =AVERAGE(J39:L39) -> 0.010595665 | N39: =M39 -> 0.010595665 | O39: =N39 -> 0.010595665 | P39: =O39 -> 0.010595665 | Q39: =P39 -> 0.010595665 | R39: =Q39 -> 0.010595665 | S39: =R39 -> 0.010595665 | T39: =S39 -> 0.010595665 | U39: =T39 -> 0.010595665 | V39: =U39 -> 0.010595665
A41: Other Operating Expenses
A42: Other expenses | B42: ₹ Lakhs | H42: ='Income Statement-Historic'!C25 -> 134717 | I42: ='Income Statement-Historic'!D25 -> 169258 | J42: ='Income Statement-Historic'!E25 -> 202282 | K42: ='Income Statement-Historic'!F25 -> 212679 | L42: ='Income Statement-Historic'!G25 -> 228731 | M42: =M17*M43 -> 255966.52 | N42: =N17*N43 -> 273884.18 | O42: =O17*O43 -> 288769.78 | P42: =P17*P43 -> 304464.42 | Q42: =Q17*Q43 -> 319504.96 | R42: =R17*R43 -> 335288.51 | S42: =S17*S43 -> 343117.5 | T42: =T17*T43 -> 351129.29 | ... V42: =V17*V43 -> 364241.25
A43: Other Expenses as % of Revenue | B43: % of Revenue | H43: =H42/H17 -> 0.13226014 | I43: =I42/I17 -> 0.12896909 | J43: =J42/J17 -> 0.12148274 | K43: =K42/K17 -> 0.11571515 | L43: =L42/L17 -> 0.1178507 | M43: =AVERAGE(H43:L43) -> 0.12325556 | N43: =M43 -> 0.12325556 | O43: =N43-(N43*1%) -> 0.12202301 | P43: =O43-(O43*1%) -> 0.12080278 | Q43: =P43-(P43*1%) -> 0.11959475 | R43: =Q43-(Q43*1%) -> 0.1183988 | S43: =R43-(R43*3%) -> 0.11484684 | T43: =S43-(S43*3%) -> 0.11140143 | U43: =T43-(T43*3%) -> 0.10805939 | V43: =U43-(U43*3%) -> 0.10481761
A44: Finance Cost
A45: Finance Cost | B45: ₹ Lakhs | H45: ='Income Statement-Historic'!C23 -> 2267 | I45: ='Income Statement-Historic'!D23 -> 1478 | J45: ='Income Statement-Historic'!E23 -> 464 | K45: ='Income Statement-Historic'!F23 -> 689 | L45: ='Income Statement-Historic'!G23 -> 1286 | M45: =M46*M17 -> 1938.8088 | N45: =N46*N17 -> 2074.5254 | O45: =O46*O17 -> 2209.3696 | P45: =P46*P17 -> 2352.9786 | Q45: =Q46*Q17 -> 2494.1573 | R45: =R46*R17 -> 2643.8067 | S45: =S46*S17 -> 2789.2161 | T45: =T46*T17 -> 2942.623 | ... V45: =V46*V17 -> 3244.2418
A46: Finacne cost as % of Revenue | B46: % of Revenue | H46: =H45/H17 -> 0.0022256562 | I46: =I45/I17 -> 0.0011261879 | J46: =J45/J17 -> 0.00027866044 | K46: =K45/K17 -> 0.00037487357 | L46: =L45/L17 -> 0.00066259492 | M46: =AVERAGE(H46:L46) -> 0.00093359461 | N46: =M46 -> 0.00093359461 | O46: =N46 -> 0.00093359461 | P46: =O46 -> 0.00093359461 | Q46: =P46 -> 0.00093359461 | R46: =Q46 -> 0.00093359461 | S46: =R46 -> 0.00093359461 | T46: =S46 -> 0.00093359461 | U46: =T46 -> 0.00093359461 | V46: =U46 -> 0.00093359461
A47: Depreciation & Amortisation
A48: Depreciation and amortisation expense | B48: ₹ Lakhs | H48: ='Income Statement-Historic'!C24 -> 23201 | I48: ='Income Statement-Historic'!D24 -> 21719 | J48: ='Income Statement-Historic'!E24 -> 21059 | K48: ='Income Statement-Historic'!F24 -> 21190 | L48: ='Income Statement-Historic'!G24 -> 23298 | M48: =M49*M17 -> 31361.449 | N48: =N49*N17 -> 33556.751 | O48: =O49*O17 -> 35737.939 | P48: =P49*P17 -> 38060.905 | Q48: =Q49*Q17 -> 40344.56 | R48: =R49*R17 -> 42765.233 | S48: =S49*S17 -> 45117.321 | T48: =T49*T17 -> 47598.774 | ... V48: =V49*V17 -> 52477.648
A49: D&A as % of Revenue | B49: % of Revenue | H49: =H48/H17 -> 0.022777878 | I49: =I48/I17 -> 0.016549171 | J49: =J48/J17 -> 0.01264722 | K49: =K48/K17 -> 0.011529131 | L49: =L48/L17 -> 0.012003994 | M49: =AVERAGE(H49:L49) -> 0.015101479 | N49: =M49 -> 0.015101479 | O49: =N49 -> 0.015101479 | P49: =O49 -> 0.015101479 | Q49: =P49 -> 0.015101479 | R49: =Q49 -> 0.015101479 | S49: =R49 -> 0.015101479 | T49: =S49 -> 0.015101479 | U49: =T49 -> 0.015101479 | V49: =U49 -> 0.015101479
A50: Total Expenses | H50: =-SUM(H48,H45,H42,H36,H38,H31,H29,H27,H25) -> -1005938 | I50: =-SUM(I48,I45,I42,I36,I38,I31,I29,I27,I25) -> -1265927 | J50: =-SUM(J48,J45,J42,J36,J38,J31,J29,J27,J25) -> -1625009 | K50: =-SUM(K48,K45,K42,K36,K38,K31,K29,K27,K25) -> -1790213 | L50: =-SUM(L48,L45,L42,L36,L38,L31,L29,L27,L25) -> -1881357 | M50: =-SUM(M48,M45,M42,M36,M38,M31,M29,M27,M25) -> -2029566.1 | N50: =-SUM(N48,N45,N42,N36,N38,N31,N29,N27,N25) -> -2161362.5 | O50: =-SUM(O48,O45,O42,O36,O38,O31,O29,O27,O25) -> -2258938.3 | ... V50: =-SUM(V48,V45,V42,V36,V38,V31,V29,V27,V25) -> -3040773.5
A52: PAT | H52: =FS!D25 -> 11383 | I52: =FS!E25 -> 36608 | J52: =FS!F25 -> 30468 | K52: =FS!G25 -> 41086 | L52: =FS!H25 -> 44241 | M52: =FS!I25 -> 37665.001 | N52: =FS!J25 -> 47492.828 | O52: =FS!K25 -> 80618.739 | ... V52: =FS!R25 -> 311759.37
I53: =(I52/H52)-1 -> 2.2160239 | J53: =(J52/I52)-1 -> -0.1677229 | K53: =(K52/J52)-1 -> 0.34849678 | L53: =(L52/K52)-1 -> 0.076790147 | M53: =(M52/L52)-1 -> -0.14864038 | N53: =(N52/M52)-1 -> 0.26092731 | O53: =(O52/N52)-1 -> 0.69749291 | P53: =(P52/O52)-1 -> 0.4008436 | ... V53: =(V52/U52)-1 -> 0.12399065
A54: EBIT | H54: =FS!D26 -> 19208 | I54: =FS!E26 -> 50922 | J54: =FS!F26 -> 42195 | K54: =FS!G26 -> 55803 | L54: =FS!H26 -> 61797 | M54: =FS!I26 -> 55745.953 | N54: =FS!J26 -> 69921.423 | O54: =FS!K26 -> 117379 | ... V54: =FS!R26 -> 448614.76
I55: =(I54/H54)-1 -> 1.6510829 | J55: =(J54/I54)-1 -> -0.17137976 | K55: =(K54/J54)-1 -> 0.32250267 | L55: =(L54/K54)-1 -> 0.10741358 | M55: =(M54/L54)-1 -> -0.097918139 | N55: =(N54/M54)-1 -> 0.25428698 | O55: =(O54/N54)-1 -> 0.67872723 | P55: =(P54/O54)-1 -> 0.39452217 | ... V55: =(V54/U54)-1 -> 0.12341816
A56: EBITDA | H56: =H54+H48 -> 42409 | I56: =I54+I48 -> 72641 | J56: =J54+J48 -> 63254 | K56: =K54+K48 -> 76993 | L56: =L54+L48 -> 85095 | M56: =M54+M48 -> 87107.402 | N56: =N54+N48 -> 103478.17 | O56: =O54+O48 -> 153116.94 | ... V56: =V54+V48 -> 501092.41
I57: =(I56/H56)-1 -> 0.71286755 | J57: =(J56/I56)-1 -> -0.12922454 | K57: =(K56/J56)-1 -> 0.21720366 | L57: =(L56/K56)-1 -> 0.10523035 | M57: =(M56/L56)-1 -> 0.023648886 | N57: =(N56/M56)-1 -> 0.18793778 | O57: =(O56/N56)-1 -> 0.47970273 | P57: =(P56/O56)-1 -> 0.31761073 | ... V57: =(V56/U56)-1 -> 0.11525152
A60: Working Capital
A61: Working Capital Assumptions
A62: Days in Period | B62: Days | H62: =H6 -> 365 | I62: =I6 -> 365 | J62: =J6 -> 365 | K62: =K6 -> 366 | L62: =L6 -> 365 | M62: =M6 -> 365 | N62: =N6 -> 365 | O62: =O6 -> 366 | ... V62: =V6 -> 365
A63: Trade Receivables Days | B63: Days | H63: ='Balance Sheet- Historic'!C21/'Working '!H17*'Working '!H62 -> 49.988548 | I63: ='Balance Sheet- Historic'!D21/'Working '!I17*'Working '!I62 -> 34.899931 | J63: ='Balance Sheet- Historic'!E21/'Working '!J17*'Working '!J62 -> 30.84914 | K63: ='Balance Sheet- Historic'!F21/'Working '!K17*'Working '!K62 -> 46.076556 | L63: ='Balance Sheet- Historic'!G21/'Working '!L17*'Working '!L62 -> 53.797449 | M63: =AVERAGE(H63:L63) -> 43.122325 | N63: =M63 -> 43.122325 | O63: =N63 -> 43.122325 | P63: =O63 -> 43.122325 | Q63: =P63 -> 43.122325 | R63: =Q63 -> 43.122325 | S63: =R63 -> 43.122325 | T63: =S63 -> 43.122325 | U63: =T63 -> 43.122325 | V63: =U63 -> 43.122325
A64: Inventory Days | B64: Days | H64: ='Balance Sheet- Historic'!C20/('Working '!H25+'Working '!H27+'Working '!H29)*'Working '!H62 -> 204.44187 | I64: ='Balance Sheet- Historic'!D20/('Working '!I25+'Working '!I27+'Working '!I29)*'Working '!I62 -> 116.73159 | J64: ='Balance Sheet- Historic'!E20/('Working '!J25+'Working '!J27+'Working '!J29)*'Working '!J62 -> 122.1821 | K64: ='Balance Sheet- Historic'!F20/('Working '!K25+'Working '!K27+'Working '!K29)*'Working '!K62 -> 107.67867 | L64: ='Balance Sheet- Historic'!G20/('Working '!L25+'Working '!L27+'Working '!L29)*'Working '!L62 -> 116.40442 | M64: =AVERAGE(H64:L64) -> 133.48773 | N64: =M64 -> 133.48773 | O64: =N64 -> 133.48773 | P64: =O64 -> 133.48773 | Q64: =P64 -> 133.48773 | R64: =Q64 -> 133.48773 | S64: =R64 -> 133.48773 | T64: =S64 -> 133.48773 | U64: =T64 -> 133.48773 | V64: =U64 -> 133.48773
A65: Trade Payables Days | B65: Days | H65: =SUM('Balance Sheet- Historic'!C46:C47)/SUM('Working '!H25,'Working '!H27)*'Working '!H62 -> 110.64913 | I65: =SUM('Balance Sheet- Historic'!D46:D47)/SUM('Working '!I25,'Working '!I27)*'Working '!I62 -> 80.213977 | J65: =SUM('Balance Sheet- Historic'!E46:E47)/SUM('Working '!J25,'Working '!J27)*'Working '!J62 -> 60.617039 | K65: =SUM('Balance Sheet- Historic'!F46:F47)/SUM('Working '!K25,'Working '!K27)*'Working '!K62 -> 74.081843 | L65: =SUM('Balance Sheet- Historic'!G46:G47)/SUM('Working '!L25,'Working '!L27)*'Working '!L62 -> 81.974838 | M65: =AVERAGE(H65:L65) -> 81.507366 | N65: =M65 -> 81.507366 | O65: =N65 -> 81.507366 | P65: =O65 -> 81.507366 | Q65: =P65 -> 81.507366 | R65: =Q65 -> 81.507366 | S65: =R65 -> 81.507366 | T65: =S65 -> 81.507366 | U65: =T65 -> 81.507366 | V65: =U65 -> 81.507366
A66: Accounts Receivable
A67: Beginning Balance | B67: ₹ Lakhs | H67: 0 | I67: =H70 -> 139499 | J67: =I70 -> 125486 | K67: =J70 -> 140732 | L67: =K70 -> 231384 | M67: =L70 -> 286063 | N67: =M70 -> 245349.93 | O67: =N70 -> 262524.43 | P67: =O70 -> 278824.61 | ... V67: =U70 -> 390998.32
A68: Addition – Revenue from Contracts with Customers | B68: ₹ Lakhs | H68: =H17 -> 1018576 | I68: =I17 -> 1312392 | J68: =J17 -> 1665109 | K68: =K17 -> 1837953 | L68: =L17 -> 1940854 | M68: =M17 -> 2076713.8 | N68: =N17 -> 2222083.7 | O68: =O17 -> 2366519.2 | ... V68: =V17 -> 3475000.6
A69: Reduction – Cash from Customers | B69: ₹ Lakhs | H69: =-(H67+H68-H70) -> -879077 | I69: =-(I67+I68-I70) -> -1326405 | J69: =-(J67+J68-J70) -> -1649863 | K69: =-(K67+K68-K70) -> -1747301 | L69: =-(L67+L68-L70) -> -1886175 | M69: =-(M67+M68-M70) -> -2117426.8 | N69: =-(N67+N68-N70) -> -2204909.2 | O69: =-(O67+O68-O70) -> -2350219 | ... V69: =-(V67+V68-V70) -> -3455450.7
A70: Ending Balance | B70: ₹ Lakhs | H70: ='Balance Sheet- Historic'!C21 -> 139499 | I70: ='Balance Sheet- Historic'!D21 -> 125486 | J70: ='Balance Sheet- Historic'!E21 -> 140732 | K70: ='Balance Sheet- Historic'!F21 -> 231384 | L70: ='Balance Sheet- Historic'!G21 -> 286063 | M70: =M68*M63/M62 -> 245349.93 | N70: =N68*N63/N62 -> 262524.43 | O70: =O68*O63/O62 -> 278824.61 | P70: =P68*P63/P62 -> 297761.77 | Q70: =Q68*Q63/Q62 -> 315627.48 | R70: =R68*R63/R62 -> 334565.13 | S70: =S68*S63/S62 -> 352001.82 | T70: =T68*T63/T62 -> 372379.35 | ... V70: =V68*V63/V62 -> 410548.23
A72: Inventory
A73: Beginning Balance | B73: ₹ Lakhs | H73: 0 | I73: =H76 -> 113668 | J73: =I76 -> 93581 | K73: =J76 -> 142781 | L73: =K76 -> 136874 | M73: =L76 -> 161643 | N73: =M76 -> 180220.8 | O73: =N76 -> 189079.12 | P73: =O76 -> 191042.56 | ... V73: =U76 -> 237876.29
A74: Addition – Purchases | B74: ₹ Lakhs | H74: =H76-H73-H75 -> 316605 | I74: =I76-I73-I75 -> 272525 | J74: =J76-J73-J75 -> 475736 | K74: =K76-K73-K75 -> 459328 | L74: =L76-L73-L75 -> 531620 | M74: =M76-M73-M75 -> 511361.6 | N74: =N76-N73-N75 -> 525863.74 | O74: =O76-O73-O75 -> 525768.72 | ... V74: =V76-V73-V75 -> 694848.64
A75: Reduction – Cost of Goods Sold | B75: ₹ Lakhs | H75: =-H33 -> -202937 | I75: =-I33 -> -292612 | J75: =-J33 -> -426536 | K75: =-K33 -> -465235 | L75: =-L33 -> -506851 | M75: =-M33 -> -492783.8 | N75: =-N33 -> -517005.42 | O75: =-O33 -> -523805.28 | ... V75: =-V33 -> -682954.82
A76: Ending Balance | B76: ₹ Lakhs | H76: ='Balance Sheet- Historic'!C20 -> 113668 | I76: ='Balance Sheet- Historic'!D20 -> 93581 | J76: ='Balance Sheet- Historic'!E20 -> 142781 | K76: ='Balance Sheet- Historic'!F20 -> 136874 | L76: ='Balance Sheet- Historic'!G20 -> 161643 | M76: =M64/M62*M33 -> 180220.8 | N76: =N64/N62*N33 -> 189079.12 | O76: =O64/O62*O33 -> 191042.56 | P76: =P64/P62*P33 -> 196082.97 | Q76: =Q64/Q62*Q33 -> 199773.5 | R76: =R64/R62*R33 -> 203543.36 | S76: =S64/S62*S33 -> 214151.53 | T76: =T64/T62*T33 -> 226548.85 | ... V76: =V64/V62*V33 -> 249770.11
A78: Accounts Payable
A79: Beginning Balance | B79: ₹ Lakhs | H79: 0 | I79: =H82 -> 61808 | J79: =I82 -> 63800 | K79: =J82 -> 71698 | L79: =K82 -> 94845 | M79: =L82 -> 114955 | N79: =M82 -> 110042.49 | O79: =N82 -> 115451.37 | P79: =O82 -> 116650.24 | ... V79: =U82 -> 145246.83
A80: Addition - COGS | B80: ₹ Lakhs | H80: =H33 -> 202937 | I80: =I33 -> 292612 | J80: =J33 -> 426536 | K80: =K33 -> 465235 | L80: =L33 -> 506851 | M80: =M33 -> 492783.8 | N80: =N33 -> 517005.42 | O80: =O33 -> 523805.28 | ... V80: =V33 -> 682954.82
A81: Reduction – Cash Paid to Suppliers | B81: ₹ Lakhs | H81: =-(H79+H80-H82) -> -141129 | I81: =-(I79+I80-I82) -> -290620 | J81: =-(J79+J80-J82) -> -418638 | K81: =-(K79+K80-K82) -> -442088 | L81: =-(L79+L80-L82) -> -486741 | M81: =-(M79+M80-M82) -> -497696.31 | N81: =-(N79+N80-N82) -> -511596.54 | O81: =-(O79+O80-O82) -> -522606.41 | ... V81: =-(V79+V80-V82) -> -675692.48
A82: Ending Balance | B82: ₹ Lakhs | H82: =SUM('Balance Sheet- Historic'!C46:C47) -> 61808 | I82: =SUM('Balance Sheet- Historic'!D46:D47) -> 63800 | J82: =SUM('Balance Sheet- Historic'!E46:E47) -> 71698 | K82: =SUM('Balance Sheet- Historic'!F46:F47) -> 94845 | L82: =SUM('Balance Sheet- Historic'!G46:G47) -> 114955 | M82: =M33/M62*M65 -> 110042.49 | N82: =N33/N62*N65 -> 115451.37 | O82: =O33/O62*O65 -> 116650.24 | P82: =P33/P62*P65 -> 119727.9 | Q82: =Q33/Q62*Q65 -> 121981.34 | R82: =R33/R62*R65 -> 124283.21 | S82: =S33/S62*S65 -> 130760.54 | T82: =T33/T62*T65 -> 138330.32 | ... V82: =V33/V62*V65 -> 152509.17
A84: Net Working Capital
A85: Trade Receivables | B85: ₹ Lakhs | H85: =H70 -> 139499 | I85: =I70 -> 125486 | J85: =J70 -> 140732 | K85: =K70 -> 231384 | L85: =L70 -> 286063 | M85: =M70 -> 245349.93 | N85: =N70 -> 262524.43 | O85: =O70 -> 278824.61 | ... V85: =V70 -> 410548.23
A86: Inventory | B86: ₹ Lakhs | H86: =H76 -> 113668 | I86: =I76 -> 93581 | J86: =J76 -> 142781 | K86: =K76 -> 136874 | L86: =L76 -> 161643 | M86: =M76 -> 180220.8 | N86: =N76 -> 189079.12 | O86: =O76 -> 191042.56 | ... V86: =V76 -> 249770.11
A87: Less: Trade Payables | B87: ₹ Lakhs | H87: =-H82 -> -61808 | I87: =-I82 -> -63800 | J87: =-J82 -> -71698 | K87: =-K82 -> -94845 | L87: =-L82 -> -114955 | M87: =-M82 -> -110042.49 | N87: =-N82 -> -115451.37 | O87: =-O82 -> -116650.24 | ... V87: =-V82 -> -152509.17
A88: Net Working Capital | B88: ₹ Lakhs | H88: =SUM(H85:H87) -> 191359 | I88: =SUM(I85:I87) -> 155267 | J88: =SUM(J85:J87) -> 211815 | K88: =SUM(K85:K87) -> 273413 | L88: =SUM(L85:L87) -> 332751 | M88: =SUM(M85:M87) -> 315528.24 | N88: =SUM(N85:N87) -> 336152.18 | O88: =SUM(O85:O87) -> 353216.93 | ... V88: =SUM(V85:V87) -> 507809.16
A89: Change in Net Working Capital | B89: ₹ Lakhs | I89: =I88-H88 -> -36092 | J89: =J88-I88 -> 56548 | K89: =K88-J88 -> 61598 | L89: =L88-K88 -> 59338 | M89: =M88-L88 -> -17222.762 | N89: =N88-M88 -> 20623.943 | O89: =O88-N88 -> 17064.752 | P89: =P88-O88 -> 20899.899 | ... V89: =V88-U88 -> 24181.389
A91: Capital Expenditure
A92: CAPEX
A93: CAPEX | B93: ₹ Lakhs | H93: =-H100 -> -20282 | I93: =-I100 -> -16174 | J93: =-J100 -> -11595 | K93: =-K100 -> -23200 | L93: =-L100 -> -28703 | M93: =M17*M94 -> -27666.509 | N93: =N17*N94 -> -29603.165 | O93: =O17*O94 -> -31527.37 | P93: =P17*P94 -> -33576.65 | Q93: =Q17*Q94 -> -35591.248 | R93: =R17*R94 -> -37726.723 | S93: =S17*S94 -> -39801.693 | T93: =T17*T94 -> -41990.786 | ... V93: =V17*V94 -> -46294.842
A94: CAPEX as % of Revenue | B94: % of Revenue | H94: =H93/H17 -> -0.019912113 | I94: =I93/I17 -> -0.012324062 | J94: =J93/J17 -> -0.0069635081 | K94: =K93/K17 -> -0.012622738 | L94: =L93/L17 -> -0.014788851 | M94: =AVERAGE(H94:L94) -> -0.013322254 | N94: =M94 -> -0.013322254 | O94: =N94 -> -0.013322254 | P94: =O94 -> -0.013322254 | Q94: =P94 -> -0.013322254 | R94: =Q94 -> -0.013322254 | S94: =R94 -> -0.013322254 | T94: =S94 -> -0.013322254 | U94: =T94 -> -0.013322254 | V94: =U94 -> -0.013322254
A96: Depreciation & Amortisation | B96: ₹ Lakhs | H96: =H48 -> 23201 | I96: =I48 -> 21719 | J96: =J48 -> 21059 | K96: =K48 -> 21190 | L96: =L48 -> 23298 | M96: =M17*M97 -> 31361.449 | N96: =N17*N97 -> 33556.751 | O96: =O17*O97 -> 35737.939 | P96: =P17*P97 -> 38060.905 | Q96: =Q17*Q97 -> 40344.56 | R96: =R17*R97 -> 42765.233 | S96: =S17*S97 -> 45117.321 | T96: =T17*T97 -> 47598.774 | ... V96: =V17*V97 -> 52477.648
A97: D&A as % of Revenue | B97: % of Revenue | H97: =H49 -> 0.022777878 | I97: =I49 -> 0.016549171 | J97: =J49 -> 0.01264722 | K97: =K49 -> 0.011529131 | L97: =L49 -> 0.012003994 | M97: =AVERAGE(H97:L97) -> 0.015101479 | N97: =M97 -> 0.015101479 | O97: =N97 -> 0.015101479 | P97: =O97 -> 0.015101479 | Q97: =P97 -> 0.015101479 | R97: =Q97 -> 0.015101479 | S97: =R97 -> 0.015101479 | T97: =S97 -> 0.015101479 | U97: =T97 -> 0.015101479 | V97: =U97 -> 0.015101479
A99: Beginning Net Fixed Assets | B99: ₹ Lakhs | H99: 210099 | I99: =H102 -> 207180 | J99: =I102 -> 201635 | K99: =J102 -> 192171 | L99: =K102 -> 194181 | M99: =L102 -> 199586 | N99: =M102 -> 195891.06 | O99: =N102 -> 191937.47 | P99: =O102 -> 187726.91 | ... V99: =U102 -> 156638.83
A100: Addition - CAPEX | B100: ₹ Lakhs | H100: =H102-H99-H101 -> 20282 | I100: =I102-I99-I101 -> 16174 | J100: =J102-J99-J101 -> 11595 | K100: =K102-K99-K101 -> 23200 | L100: =L102-L99-L101 -> 28703 | M100: =-M93 -> 27666.509 | N100: =-N93 -> 29603.165 | O100: =-O93 -> 31527.37 | P100: =-P93 -> 33576.65 | Q100: =-Q93 -> 35591.248 | R100: =-R93 -> 37726.723 | S100: =-S93 -> 39801.693 | T100: =-T93 -> 41990.786 | ... V100: =-V93 -> 46294.842
A101: Reduction – D&A | B101: ₹ Lakhs | H101: =-H48 -> -23201 | I101: =-I48 -> -21719 | J101: =-J48 -> -21059 | K101: =-K48 -> -21190 | L101: =-L48 -> -23298 | M101: =-M96 -> -31361.449 | N101: =-N96 -> -33556.751 | O101: =-O96 -> -35737.939 | P101: =-P96 -> -38060.905 | Q101: =-Q96 -> -40344.56 | R101: =-R96 -> -42765.233 | S101: =-S96 -> -45117.321 | T101: =-T96 -> -47598.774 | ... V101: =-V96 -> -52477.648
A102: Ending Net Fixed Assets | B102: ₹ Lakhs | H102: =H107 -> 207180 | I102: =I107 -> 201635 | J102: =J107 -> 192171 | K102: =K107 -> 194181 | L102: =L107 -> 199586 | M102: =SUM(M99:M101) -> 195891.06 | N102: =SUM(N99:N101) -> 191937.47 | O102: =SUM(O99:O101) -> 187726.91 | P102: =SUM(P99:P101) -> 183242.65 | Q102: =SUM(Q99:Q101) -> 178489.34 | R102: =SUM(R99:R101) -> 173450.83 | S102: =SUM(S99:S101) -> 168135.2 | T102: =SUM(T99:T101) -> 162527.21 | ... V102: =SUM(V99:V101) -> 150456.02
A104: PPE | B104: ₹ Lakhs | H104: ='Balance Sheet- Historic'!C10 -> 192203 | I104: ='Balance Sheet- Historic'!D10 -> 189008 | J104: ='Balance Sheet- Historic'!E10 -> 183235 | K104: ='Balance Sheet- Historic'!F10 -> 176009 | L104: ='Balance Sheet- Historic'!G10 -> 173512 | M104: =M102*AVERAGE($H$104/$H$107,$I$104/$I$107,$J$104/$J$107,$K$104/$K$107,$L$104/$L$107) -> 179998.95 | N104: =N102*AVERAGE($H$104/$H$107,$I$104/$I$107,$J$104/$J$107,$K$104/$K$107,$L$104/$L$107) -> 176366.11 | O104: =O102*AVERAGE($H$104/$H$107,$I$104/$I$107,$J$104/$J$107,$K$104/$K$107,$L$104/$L$107) -> 172497.13 | P104: =P102*AVERAGE($H$104/$H$107,$I$104/$I$107,$J$104/$J$107,$K$104/$K$107,$L$104/$L$107) -> 168376.67 | Q104: =Q102*AVERAGE($H$104/$H$107,$I$104/$I$107,$J$104/$J$107,$K$104/$K$107,$L$104/$L$107) -> 164008.99 | R104: =R102*AVERAGE($H$104/$H$107,$I$104/$I$107,$J$104/$J$107,$K$104/$K$107,$L$104/$L$107) -> 159379.24 | S104: =S102*AVERAGE($H$104/$H$107,$I$104/$I$107,$J$104/$J$107,$K$104/$K$107,$L$104/$L$107) -> 154494.85 | T104: =T102*AVERAGE($H$104/$H$107,$I$104/$I$107,$J$104/$J$107,$K$104/$K$107,$L$104/$L$107) -> 149341.82 | ... V104: =V102*AVERAGE($H$104/$H$107,$I$104/$I$107,$J$104/$J$107,$K$104/$K$107,$L$104/$L$107) -> 138249.93
A105: CWIP | B105: ₹ Lakhs | H105: ='Balance Sheet- Historic'!C11 -> 12879 | I105: ='Balance Sheet- Historic'!D11 -> 10989 | J105: ='Balance Sheet- Historic'!E11 -> 7713 | K105: ='Balance Sheet- Historic'!F11 -> 17268 | L105: ='Balance Sheet- Historic'!G11 -> 25337 | M105: =M102*AVERAGE($H$105/$H$107,$I$105/$I$107,$J$105/$J$107,$K$105/$K$107,$L$105/$L$107) -> 14600.703 | N105: =N102*AVERAGE($H$105/$H$107,$I$105/$I$107,$J$105/$J$107,$K$105/$K$107,$L$105/$L$107) -> 14306.023 | O105: =O102*AVERAGE($H$105/$H$107,$I$105/$I$107,$J$105/$J$107,$K$105/$K$107,$L$105/$L$107) -> 13992.189 | P105: =P102*AVERAGE($H$105/$H$107,$I$105/$I$107,$J$105/$J$107,$K$105/$K$107,$L$105/$L$107) -> 13657.956 | Q105: =Q102*AVERAGE($H$105/$H$107,$I$105/$I$107,$J$105/$J$107,$K$105/$K$107,$L$105/$L$107) -> 13303.669 | R105: =R102*AVERAGE($H$105/$H$107,$I$105/$I$107,$J$105/$J$107,$K$105/$K$107,$L$105/$L$107) -> 12928.125 | S105: =S102*AVERAGE($H$105/$H$107,$I$105/$I$107,$J$105/$J$107,$K$105/$K$107,$L$105/$L$107) -> 12531.925 | T105: =T102*AVERAGE($H$105/$H$107,$I$105/$I$107,$J$105/$J$107,$K$105/$K$107,$L$105/$L$107) -> 12113.935 | ... V105: =V102*AVERAGE($H$105/$H$107,$I$105/$I$107,$J$105/$J$107,$K$105/$K$107,$L$105/$L$107) -> 11214.211
A106: Intangible Assets | B106: ₹ Lakhs | H106: ='Balance Sheet- Historic'!C12 -> 2098 | I106: ='Balance Sheet- Historic'!D12 -> 1638 | J106: ='Balance Sheet- Historic'!E12 -> 1223 | K106: ='Balance Sheet- Historic'!F12 -> 904 | L106: ='Balance Sheet- Historic'!G12 -> 737 | M106: =M102*AVERAGE($H$106/$H$107,$I$106/$I$107,$J$106/$J$107,$K$106/$K$107,$L$106/$L$107) -> 1291.4027 | N106: =N102*AVERAGE($H$106/$H$107,$I$106/$I$107,$J$106/$J$107,$K$106/$K$107,$L$106/$L$107) -> 1265.3389 | O106: =O102*AVERAGE($H$106/$H$107,$I$106/$I$107,$J$106/$J$107,$K$106/$K$107,$L$106/$L$107) -> 1237.5809 | P106: =P102*AVERAGE($H$106/$H$107,$I$106/$I$107,$J$106/$J$107,$K$106/$K$107,$L$106/$L$107) -> 1208.0186 | Q106: =Q102*AVERAGE($H$106/$H$107,$I$106/$I$107,$J$106/$J$107,$K$106/$K$107,$L$106/$L$107) -> 1176.6827 | R106: =R102*AVERAGE($H$106/$H$107,$I$106/$I$107,$J$106/$J$107,$K$106/$K$107,$L$106/$L$107) -> 1143.4665 | S106: =S102*AVERAGE($H$106/$H$107,$I$106/$I$107,$J$106/$J$107,$K$106/$K$107,$L$106/$L$107) -> 1108.4235 | T106: =T102*AVERAGE($H$106/$H$107,$I$106/$I$107,$J$106/$J$107,$K$106/$K$107,$L$106/$L$107) -> 1071.4531 | ... V106: =V102*AVERAGE($H$106/$H$107,$I$106/$I$107,$J$106/$J$107,$K$106/$K$107,$L$106/$L$107) -> 991.87431
A107: Total Net Fixed Assets | B107: ₹ Lakhs | H107: =SUM(H104:H106) -> 207180 | I107: =SUM(I104:I106) -> 201635 | J107: =SUM(J104:J106) -> 192171 | K107: =SUM(K104:K106) -> 194181 | L107: =SUM(L104:L106) -> 199586 | M107: =SUM(M104:M106) -> 195891.06 | N107: =SUM(N104:N106) -> 191937.47 | O107: =SUM(O104:O106) -> 187726.91 | ... V107: =SUM(V104:V106) -> 150456.02
A109: Debt
A110: Debt Assumptions
A112: Borrowings
A113: Beginning Borrowings | H113: 0 | I113: =H117 -> 11541 | J113: =I117 -> 0 | K113: =J117 -> 0 | L113: =K117 -> 7741 | M113: =L117 -> 57485 | N113: =M117 -> 57485 | O113: =N117 -> 57485 | P113: =O117 -> 57485 | ... V113: =U117 -> 57485
A114: Addition – New Borrowings | H114: ='Cash flow-Historic'!B52+MAX('Cash flow-Historic'!B55,0) -> 25000 | I114: ='Cash flow-Historic'!C52+MAX('Cash flow-Historic'!C55,0) -> 0 | J114: ='Cash flow-Historic'!D52+MAX('Cash flow-Historic'!D55,0) -> 0 | K114: ='Cash flow-Historic'!E52+MAX('Cash flow-Historic'!E55,0) -> 7741 | L114: ='Cash flow-Historic'!F52+MAX('Cash flow-Historic'!F55,0) -> 49744 | M114: 0 | N114: 0 | O114: 0 | P114: 0 | Q114: 0 | R114: 0 | S114: 0 | T114: 0 | U114: 0 | V114: 0
A115: Reduction – Repayment | H115: ='Cash flow-Historic'!B53+MIN('Cash flow-Historic'!B55,0) -> -23541 | I115: ='Cash flow-Historic'!C53+MIN('Cash flow-Historic'!C55,0) -> -25017 | J115: ='Cash flow-Historic'!D53+MIN('Cash flow-Historic'!D55,0) -> 0 | K115: ='Cash flow-Historic'!E53+MIN('Cash flow-Historic'!E55,0) -> 0 | L115: ='Cash flow-Historic'!F53+MIN('Cash flow-Historic'!F55,0) -> 0 | M115: 0 | N115: 0 | O115: 0 | P115: 0 | Q115: 0 | R115: 0 | S115: 0 | T115: 0 | U115: 0 | V115: 0
A116: Other / Non-cash Changes | H116: =H117-H113-H114-H115 -> 10082 | I116: =I117-I113-I114-I115 -> 13476 | J116: =J117-J113-J114-J115 -> 0 | K116: =K117-K113-K114-K115 -> 0 | L116: =L117-L113-L114-L115 -> 0 | M116: 0 | N116: 0 | O116: 0 | P116: 0 | Q116: 0 | R116: 0 | S116: 0 | T116: 0 | U116: 0 | V116: 0
A117: Ending Borrowings | H117: ='Balance Sheet- Historic'!C44+'Balance Sheet- Historic'!C37 -> 11541 | I117: ='Balance Sheet- Historic'!D44+'Balance Sheet- Historic'!D37 -> 0 | J117: ='Balance Sheet- Historic'!E44+'Balance Sheet- Historic'!E37 -> 0 | K117: ='Balance Sheet- Historic'!F44+'Balance Sheet- Historic'!F37 -> 7741 | L117: ='Balance Sheet- Historic'!G44+'Balance Sheet- Historic'!G37 -> 57485 | M117: =SUM(M113:M116) -> 57485 | N117: =SUM(N113:N116) -> 57485 | O117: =SUM(O113:O116) -> 57485 | P117: =SUM(P113:P116) -> 57485 | Q117: =SUM(Q113:Q116) -> 57485 | R117: =SUM(R113:R116) -> 57485 | S117: =SUM(S113:S116) -> 57485 | T117: =SUM(T113:T116) -> 57485 | ... V117: =SUM(V113:V116) -> 57485
A119: Lease Liabilities
...

Sheet FS
A1: United Breweries Limited
A2: Financial Statements Forecasts
A4: Particulars | B4: Unit | C4: Period Type | D4: FY2021 | E4: FY2022 | F4: FY2023 | G4: FY2024 | H4: FY2025 | I4: FY2026 | J4: FY2027 | K4: FY2028 | L4: FY2029 | M4: FY2030 | N4: FY2031 | O4: FY2032 | P4: FY2033 | Q4: FY2034 | R4: FY2035
D5: Historical | E5: Historical | F5: Historical | G5: Historical | H5: Historical | I5: Forecast | J5: Forecast | K5: Forecast | L5: Forecast | M5: Forecast | N5: Forecast | O5: Forecast | P5: Forecast | Q5: Forecast | R5: Forecast
A7: Profit & Loss Statement
A8: Revenue from contracts with customers (including excise duty) | B8: ₹ Lakhs | D8: ='Income Statement-Historic'!C12 -> 1018576 | E8: ='Income Statement-Historic'!D12 -> 1312392 | F8: ='Income Statement-Historic'!E12 -> 1665109 | G8: ='Income Statement-Historic'!F12 -> 1837953 | H8: ='Income Statement-Historic'!G12 -> 1940854 | I8: ='Working '!M17 -> 2076713.8 | J8: ='Working '!N17 -> 2222083.7 | K8: ='Working '!O17 -> 2366519.2 | L8: ='Working '!P17 -> 2520342.9 | M8: ='Working '!Q17 -> 2671563.5 | N8: ='Working '!R17 -> 2831857.3 | O8: ='Working '!S17 -> 2987609.5 | P8: ='Working '!T17 -> 3151928 | ... R8: ='Working '!V17 -> 3475000.6
A9: Other income | B9: ₹ Lakhs | D9: ='Income Statement-Historic'!C13 -> 5025 | E9: ='Income Statement-Historic'!D13 -> 2979 | F9: ='Income Statement-Historic'!E13 -> 4943 | G9: ='Income Statement-Historic'!F13 -> 7374 | H9: ='Income Statement-Historic'!G13 -> 3590 | I9: ='Working '!M19 -> 6659.4424 | J9: ='Working '!N19 -> 7125.6034 | K9: ='Working '!O19 -> 7588.7676 | L9: ='Working '!P19 -> 8082.0375 | M9: ='Working '!Q19 -> 8566.9598 | N9: ='Working '!R19 -> 9080.9774 | O9: ='Working '!S19 -> 9580.4311 | P9: ='Working '!T19 -> 10107.355 | ... R9: ='Working '!V19 -> 11143.359
A10: Total Income | B10: ₹ Lakhs | D10: ='Income Statement-Historic'!C14 -> 1023601 | E10: ='Income Statement-Historic'!D14 -> 1315371 | F10: ='Income Statement-Historic'!E14 -> 1670052 | G10: ='Income Statement-Historic'!F14 -> 1845327 | H10: ='Income Statement-Historic'!G14 -> 1944444 | I10: =SUM(I8:I9) -> 2083373.2 | J10: =SUM(J8:J9) -> 2229209.3 | K10: =SUM(K8:K9) -> 2374108 | L10: =SUM(L8:L9) -> 2528425 | M10: =SUM(M8:M9) -> 2680130.5 | N10: =SUM(N8:N9) -> 2840938.3 | O10: =SUM(O8:O9) -> 2997189.9 | P10: =SUM(P8:P9) -> 3162035.4 | ... R10: =SUM(R8:R9) -> 3486144
A11: Cost of materials consumed | B11: ₹ Lakhs | D11: ='Income Statement-Historic'!C17 -> 196516 | E11: ='Income Statement-Historic'!D17 -> 270729 | F11: ='Income Statement-Historic'!E17 -> 422476 | G11: ='Income Statement-Historic'!F17 -> 456755 | H11: ='Income Statement-Historic'!G17 -> 493673 | I11: ='Working '!M25 -> 480058.57 | J11: ='Working '!N25 -> 503389.42 | K11: ='Working '!O25 -> 509304.25 | L11: ='Working '!P25 -> 520712.66 | M11: ='Working '!Q25 -> 529877.21 | N11: ='Working '!R25 -> 539203.04 | O11: ='Working '!S25 -> 568859.21 | P11: ='Working '!T25 -> 600146.47 | ... R11: ='Working '!V25 -> 661661.48
A12: Purchase of stock-in-trade / traded goods | B12: ₹ Lakhs | D12: ='Income Statement-Historic'!C18 -> 7371 | E12: ='Income Statement-Historic'!D18 -> 19582 | F12: ='Income Statement-Historic'!E18 -> 9247 | G12: ='Income Statement-Historic'!F18 -> 11825 | H12: ='Income Statement-Historic'!G18 -> 18174 | I12: ='Working '!M27 -> 18070.948 | J12: ='Working '!N27 -> 19335.914 | K12: ='Working '!O27 -> 20592.748 | L12: ='Working '!P27 -> 21931.277 | M12: ='Working '!Q27 -> 23247.154 | N12: ='Working '!R27 -> 24641.983 | O12: ='Working '!S27 -> 25997.292 | P12: ='Working '!T27 -> 27427.143 | ... R12: ='Working '!V27 -> 30238.425
A13: Changes in inventories | B13: ₹ Lakhs | D13: ='Income Statement-Historic'!C19 -> -950 | E13: ='Income Statement-Historic'!D19 -> 2301 | F13: ='Income Statement-Historic'!E19 -> -5187 | G13: ='Income Statement-Historic'!F19 -> -3345 | H13: ='Income Statement-Historic'!G19 -> -4996 | I13: ='Working '!M29 -> -5345.72 | J13: ='Working '!N29 -> -5719.9204 | K13: ='Working '!O29 -> -6091.7152 | L13: ='Working '!P29 -> -6487.6767 | M13: ='Working '!Q29 -> -6876.9373 | N13: ='Working '!R29 -> -7289.5536 | O13: ='Working '!S29 -> -7690.479 | P13: ='Working '!T29 -> -8113.4553 | ... R13: ='Working '!V29 -> -8945.0845
A14: Excise duty on sale of goods/products | B14: ₹ Lakhs | D14: ='Income Statement-Historic'!C20 -> 594267 | E14: ='Income Statement-Historic'!D20 -> 728548 | F14: ='Income Statement-Historic'!E20 -> 915117 | G14: ='Income Statement-Historic'!F20 -> 1025685 | H14: ='Income Statement-Historic'!G20 -> 1049345 | I14: ='Working '!M31 -> 1157503.3 | J14: ='Working '!N31 -> 1238528.5 | K14: ='Working '!O31 -> 1305842.5 | L14: ='Working '!P31 -> 1376815 | M14: ='Working '!Q31 -> 1444829.7 | N14: ='Working '!R31 -> 1516204.3 | O14: ='Working '!S31 -> 1583599.6 | P14: ='Working '!T31 -> 1653990.6 | ... R14: ='Working '!V31 -> 1787236.5
A15: Employee benefits expense | B15: ₹ Lakhs | D15: ='Income Statement-Historic'!C21 -> 48549 | E15: ='Income Statement-Historic'!D21 -> 52312 | F15: ='Income Statement-Historic'!E21 -> 41183 | G15: ='Income Statement-Historic'!F21 -> 45210 | H15: ='Income Statement-Historic'!G21 -> 52180 | I15: ='Working '!M36 -> 68008.077 | J15: ='Working '!N36 -> 72768.642 | K15: ='Working '!O36 -> 77498.604 | L15: ='Working '!P36 -> 82536.013 | M15: ='Working '!Q36 -> 87488.174 | N15: ='Working '!R36 -> 92737.464 | O15: ='Working '!S36 -> 97838.025 | P15: ='Working '!T36 -> 103219.12 | ... R15: ='Working '!V36 -> 113799.08
A16: Contract employee expense | B16: ₹ Lakhs | D16: ='Income Statement-Historic'!C22 -> — | E16: ='Income Statement-Historic'!D22 -> — | F16: ='Income Statement-Historic'!E22 -> 18368 | G16: ='Income Statement-Historic'!F22 -> 19525 | H16: ='Income Statement-Historic'!G22 -> 19666 | I16: ='Working '!M38 -> 22004.163 | J16: ='Working '!N38 -> 23544.454 | K16: ='Working '!O38 -> 25074.844 | L16: ='Working '!P38 -> 26704.709 | M16: ='Working '!Q38 -> 28306.991 | N16: ='Working '!R38 -> 30005.411 | O16: ='Working '!S38 -> 31655.708 | P16: ='Working '!T38 -> 33396.772 | ... R16: ='Working '!V38 -> 36819.941
A17: Finance costs | B17: ₹ Lakhs | D17: ='Income Statement-Historic'!C23 -> 2267 | E17: ='Income Statement-Historic'!D23 -> 1478 | F17: ='Income Statement-Historic'!E23 -> 464 | G17: ='Income Statement-Historic'!F23 -> 689 | H17: ='Income Statement-Historic'!G23 -> 1286 | I17: ='Working '!M45 -> 1938.8088 | J17: ='Working '!N45 -> 2074.5254 | K17: ='Working '!O45 -> 2209.3696 | L17: ='Working '!P45 -> 2352.9786 | M17: ='Working '!Q45 -> 2494.1573 | N17: ='Working '!R45 -> 2643.8067 | O17: ='Working '!S45 -> 2789.2161 | P17: ='Working '!T45 -> 2942.623 | ... R17: ='Working '!V45 -> 3244.2418
A18: Depreciation and amortisation expense | B18: ₹ Lakhs | D18: ='Income Statement-Historic'!C24 -> 23201 | E18: ='Income Statement-Historic'!D24 -> 21719 | F18: ='Income Statement-Historic'!E24 -> 21059 | G18: ='Income Statement-Historic'!F24 -> 21190 | H18: ='Income Statement-Historic'!G24 -> 23298 | I18: ='Working '!M48 -> 31361.449 | J18: ='Working '!N48 -> 33556.751 | K18: ='Working '!O48 -> 35737.939 | L18: ='Working '!P48 -> 38060.905 | M18: ='Working '!Q48 -> 40344.56 | N18: ='Working '!R48 -> 42765.233 | O18: ='Working '!S48 -> 45117.321 | P18: ='Working '!T48 -> 47598.774 | ... R18: ='Working '!V48 -> 52477.648
A19: Other expenses | B19: ₹ Lakhs | D19: ='Income Statement-Historic'!C25 -> 134717 | E19: ='Income Statement-Historic'!D25 -> 169258 | F19: ='Income Statement-Historic'!E25 -> 202282 | G19: ='Income Statement-Historic'!F25 -> 212679 | H19: ='Income Statement-Historic'!G25 -> 228731 | I19: ='Working '!M42 -> 255966.52 | J19: ='Working '!N42 -> 273884.18 | K19: ='Working '!O42 -> 288769.78 | L19: ='Working '!P42 -> 304464.42 | M19: ='Working '!Q42 -> 319504.96 | N19: ='Working '!R42 -> 335288.51 | O19: ='Working '!S42 -> 343117.5 | P19: ='Working '!T42 -> 351129.29 | ... R19: ='Working '!V42 -> 364241.25
A20: Total Expenses | B20: ₹ Lakhs | D20: =SUM(D11:D19) -> 1005938 | E20: =SUM(E11:E19) -> 1265927 | F20: =SUM(F11:F19) -> 1625009 | G20: =SUM(G11:G19) -> 1790213 | H20: =SUM(H11:H19) -> 1881357 | I20: =SUM(I11:I19) -> 2029566.1 | J20: =SUM(J11:J19) -> 2161362.5 | K20: =SUM(K11:K19) -> 2258938.3 | ... R20: =SUM(R11:R19) -> 3040773.5
A21: Profit before exceptional items and tax | B21: ₹ Lakhs | D21: =D10-D20 -> 17663 | E21: =E10-E20 -> 49444 | F21: =F10-F20 -> 45043 | G21: =G10-G20 -> 55114 | H21: =H10-H20 -> 63087 | I21: =I10-I20 -> 53807.144 | J21: =J10-J20 -> 67846.898 | K21: =K10-K20 -> 115169.63 | ... R21: =R10-R20 -> 445370.52
A22: Exceptional items | B22: ₹ Lakhs | D22: -722 | E22: 0 | F22: -3312 | G22: 0 | H22: -2576 | I22: 0 | J22: 0 | K22: 0 | L22: 0 | M22: 0 | N22: 0 | O22: 0 | P22: 0 | Q22: 0 | R22: 0
A23: Profit before tax | B23: ₹ Lakhs | D23: =SUM(D21:D22) -> 16941 | E23: =SUM(E21:E22) -> 49444 | F23: =SUM(F21:F22) -> 41731 | G23: =SUM(G21:G22) -> 55114 | H23: =SUM(H21:H22) -> 60511 | I23: =SUM(I21:I22) -> 53807.144 | J23: =SUM(J21:J22) -> 67846.898 | K23: =SUM(K21:K22) -> 115169.63 | ... R23: =SUM(R21:R22) -> 445370.52
A24: Total tax expense | B24: ₹ Lakhs | D24: ='Income Statement-Historic'!C35 -> -5558 | E24: ='Income Statement-Historic'!D35 -> -12836 | F24: ='Income Statement-Historic'!E35 -> -11263 | G24: ='Income Statement-Historic'!F35 -> -14028 | H24: ='Income Statement-Historic'!G35 -> -16270 | I24: =-I23*Assumptions!$C$107 -> -16142.143 | J24: =-J23*Assumptions!$C$107 -> -20354.069 | K24: =-K23*Assumptions!$C$107 -> -34550.888 | L24: =-L23*Assumptions!$C$107 -> -48400.391 | M24: =-M23*Assumptions!$C$107 -> -63274.348 | N24: =-N23*Assumptions!$C$107 -> -79421.431 | O24: =-O23*Assumptions!$C$107 -> -91771.961 | P24: =-P23*Assumptions!$C$107 -> -105089.41 | ... R24: =-R23*Assumptions!$C$107 -> -133611.16
A25: Profit for the year | B25: ₹ Lakhs | D25: =SUM(D23:D24) -> 11383 | E25: =SUM(E23:E24) -> 36608 | F25: =SUM(F23:F24) -> 30468 | G25: =SUM(G23:G24) -> 41086 | H25: =SUM(H23:H24) -> 44241 | I25: =SUM(I23:I24) -> 37665.001 | J25: =SUM(J23:J24) -> 47492.828 | K25: =SUM(K23:K24) -> 80618.739 | ... R25: =SUM(R23:R24) -> 311759.37
A26: EBIT | B26: ₹ Lakhs | D26: =D17+D23 -> 19208 | E26: =E17+E23 -> 50922 | F26: =F17+F23 -> 42195 | G26: =G17+G23 -> 55803 | H26: =H17+H23 -> 61797 | I26: =I17+I23 -> 55745.953 | J26: =J17+J23 -> 69921.423 | K26: =K17+K23 -> 117379 | ... R26: =R17+R23 -> 448614.76
A28: Balance Sheet
A29: Cash and cash equivalents | B29: ₹ Lakhs | D29: ='Working '!H154 -> 40940 | E29: ='Working '!I154 -> 86260 | F29: ='Working '!J154 -> 32986 | G29: ='Working '!K154 -> 12915 | H29: ='Working '!L154 -> 34192 | I29: =I99 -> 61133.119 | J29: =J99 -> 69306.314 | K29: =K99 -> 93794.651 | L29: =L99 -> 131703.5 | M29: =M99 -> 184905.32 | N29: =N99 -> 252426.4 | O29: =O99 -> 341863.57 | P29: =P99 -> 442676.86 | ... R29: =R99 -> 694373.05
A31: Trade receivables | B31: ₹ Lakhs | D31: ='Balance Sheet- Historic'!C21 -> 139499 | E31: ='Balance Sheet- Historic'!D21 -> 125486 | F31: ='Balance Sheet- Historic'!E21 -> 140732 | G31: ='Balance Sheet- Historic'!F21 -> 231384 | H31: ='Balance Sheet- Historic'!G21 -> 286063 | I31: ='Working '!M70 -> 245349.93 | J31: ='Working '!N70 -> 262524.43 | K31: ='Working '!O70 -> 278824.61 | L31: ='Working '!P70 -> 297761.77 | M31: ='Working '!Q70 -> 315627.48 | N31: ='Working '!R70 -> 334565.13 | O31: ='Working '!S70 -> 352001.82 | P31: ='Working '!T70 -> 372379.35 | ... R31: ='Working '!V70 -> 410548.23
A32: Inventories | B32: ₹ Lakhs | D32: ='Balance Sheet- Historic'!C20 -> 113668 | E32: ='Balance Sheet- Historic'!D20 -> 93581 | F32: ='Balance Sheet- Historic'!E20 -> 142781 | G32: ='Balance Sheet- Historic'!F20 -> 136874 | H32: ='Balance Sheet- Historic'!G20 -> 161643 | I32: ='Working '!M76 -> 180220.8 | J32: ='Working '!N76 -> 189079.12 | K32: ='Working '!O76 -> 191042.56 | L32: ='Working '!P76 -> 196082.97 | M32: ='Working '!Q76 -> 199773.5 | N32: ='Working '!R76 -> 203543.36 | O32: ='Working '!S76 -> 214151.53 | P32: ='Working '!T76 -> 226548.85 | ... R32: ='Working '!V76 -> 249770.11
A34: Other current assets | B34: ₹ Lakhs | D34: ='Balance Sheet- Historic'!C25 -> 31689 | E34: ='Balance Sheet- Historic'!D25 -> 27275 | F34: ='Balance Sheet- Historic'!E25 -> 45013 | G34: ='Balance Sheet- Historic'!F25 -> 51122 | H34: ='Balance Sheet- Historic'!G25 -> 52423 | I34: =2.68%*I8 -> 55655.929 | J34: =2.68%*J8 -> 59551.844 | K34: =2.68%*K8 -> 63422.714 | L34: =2.68%*L8 -> 67545.191 | M34: =2.68%*M8 -> 71597.902 | N34: =2.68%*N8 -> 75893.776 | O34: =2.68%*O8 -> 80067.934 | P34: =2.68%*P8 -> 84471.67 | ... R34: =2.68%*R8 -> 93130.016
A35: Total Current Assets | B35: ₹ Lakhs | D35: =SUM(D29:D34) -> 325796 | E35: =SUM(E29:E34) -> 332602 | F35: =SUM(F29:F34) -> 361512 | G35: =SUM(G29:G34) -> 432295 | H35: =SUM(H29:H34) -> 534321 | I35: =SUM(I29:I34) -> 542359.78 | J35: =SUM(J29:J34) -> 580461.71 | K35: =SUM(K29:K34) -> 627084.54 | ... R35: =SUM(R29:R34) -> 1447821.4
A36: Property, plant and equipment | B36: ₹ Lakhs | D36: ='Balance Sheet- Historic'!C10 -> 192203 | E36: ='Balance Sheet- Historic'!D10 -> 189008 | F36: ='Balance Sheet- Historic'!E10 -> 183235 | G36: ='Balance Sheet- Historic'!F10 -> 176009 | H36: ='Balance Sheet- Historic'!G10 -> 173512 | I36: ='Working '!M104 -> 179998.95 | J36: ='Working '!N104 -> 176366.11 | K36: ='Working '!O104 -> 172497.13 | L36: ='Working '!P104 -> 168376.67 | M36: ='Working '!Q104 -> 164008.99 | N36: ='Working '!R104 -> 159379.24 | O36: ='Working '!S104 -> 154494.85 | P36: ='Working '!T104 -> 149341.82 | ... R36: ='Working '!V104 -> 138249.93
A37: Capital work-in-progress | B37: ₹ Lakhs | D37: ='Balance Sheet- Historic'!C11 -> 12879 | E37: ='Balance Sheet- Historic'!D11 -> 10989 | F37: ='Balance Sheet- Historic'!E11 -> 7713 | G37: ='Balance Sheet- Historic'!F11 -> 17268 | H37: ='Balance Sheet- Historic'!G11 -> 25337 | I37: ='Working '!M105 -> 14600.703 | J37: ='Working '!N105 -> 14306.023 | K37: ='Working '!O105 -> 13992.189 | L37: ='Working '!P105 -> 13657.956 | M37: ='Working '!Q105 -> 13303.669 | N37: ='Working '!R105 -> 12928.125 | O37: ='Working '!S105 -> 12531.925 | P37: ='Working '!T105 -> 12113.935 | ... R37: ='Working '!V105 -> 11214.211
A38: Intangible assets | B38: ₹ Lakhs | D38: ='Balance Sheet- Historic'!C12 -> 2098 | E38: ='Balance Sheet- Historic'!D12 -> 1638 | F38: ='Balance Sheet- Historic'!E12 -> 1223 | G38: ='Balance Sheet- Historic'!F12 -> 904 | H38: ='Balance Sheet- Historic'!G12 -> 737 | I38: ='Working '!M106 -> 1291.4027 | J38: ='Working '!N106 -> 1265.3389 | K38: ='Working '!O106 -> 1237.5809 | L38: ='Working '!P106 -> 1208.0186 | M38: ='Working '!Q106 -> 1176.6827 | N38: ='Working '!R106 -> 1143.4665 | O38: ='Working '!S106 -> 1108.4235 | P38: ='Working '!T106 -> 1071.4531 | ... R38: ='Working '!V106 -> 991.87431
A39: Goodwill on consolidation | B39: ₹ Lakhs | D39: ='Balance Sheet- Historic'!C13 -> 645 | E39: ='Balance Sheet- Historic'!D13 -> 645 | F39: ='Balance Sheet- Historic'!E13 -> 645 | G39: ='Balance Sheet- Historic'!F13 -> 645 | H39: ='Balance Sheet- Historic'!G13 -> 645 | I39: 0 | J39: 0 | K39: 0 | L39: 0 | M39: 0 | N39: 0 | O39: 0 | P39: 0 | Q39: 0 | R39: 0
A40: Investments | B40: ₹ Lakhs | D40: ='Balance Sheet- Historic'!C14 -> 606 | E40: ='Balance Sheet- Historic'!D14 -> 835 | F40: ='Balance Sheet- Historic'!E14 -> 805 | G40: ='Balance Sheet- Historic'!F14 -> 797 | H40: ='Balance Sheet- Historic'!G14 -> 785 | I40: 0 | J40: 0 | K40: 0 | L40: 0 | M40: 0 | N40: 0 | O40: 0 | P40: 0 | Q40: 0 | R40: 0
A41: Income tax assets (net) | B41: ₹ Lakhs | D41: ='Balance Sheet- Historic'!C16 -> 20395 | E41: ='Balance Sheet- Historic'!D16 -> 20199 | F41: ='Balance Sheet- Historic'!E16 -> 22138 | G41: ='Balance Sheet- Historic'!F16 -> 21135 | H41: ='Balance Sheet- Historic'!G16 -> 22596 | I41: =H41 -> 22596 | J41: =I41 -> 22596 | K41: =J41 -> 22596 | L41: =K41 -> 22596 | M41: =L41 -> 22596 | N41: =M41 -> 22596 | O41: =N41 -> 22596 | P41: =O41 -> 22596 | ... R41: =Q41 -> 22596
A42: Deferred tax asset (net) | B42: ₹ Lakhs | D42: ='Balance Sheet- Historic'!C17 -> 3497 | E42: ='Balance Sheet- Historic'!D17 -> 3844 | F42: ='Balance Sheet- Historic'!E17 -> 4501 | G42: ='Balance Sheet- Historic'!F17 -> 5293 | H42: ='Balance Sheet- Historic'!G17 -> 6674 | I42: =H42 -> 6674 | J42: =I42 -> 6674 | K42: =J42 -> 6674 | L42: =K42 -> 6674 | M42: =L42 -> 6674 | N42: =M42 -> 6674 | O42: =N42 -> 6674 | P42: =O42 -> 6674 | ... R42: =Q42 -> 6674
A43: Other financial assets | B43: ₹ Lakhs | D43: ='Balance Sheet- Historic'!C15 -> 4711 | E43: ='Balance Sheet- Historic'!D15 -> 4816 | F43: ='Balance Sheet- Historic'!E15 -> 4676 | G43: ='Balance Sheet- Historic'!F15 -> 3937 | H43: ='Balance Sheet- Historic'!G15 -> 4498 | I43: =H43 -> 4498 | J43: =I43 -> 4498 | K43: =J43 -> 4498 | L43: =K43 -> 4498 | M43: =L43 -> 4498 | N43: =M43 -> 4498 | O43: =N43 -> 4498 | P43: =O43 -> 4498 | ... R43: =Q43 -> 4498
A44: Other non-current assets | B44: ₹ Lakhs | D44: ='Balance Sheet- Historic'!C18 -> 15826 | E44: ='Balance Sheet- Historic'!D18 -> 25044 | F44: ='Balance Sheet- Historic'!E18 -> 34458 | G44: ='Balance Sheet- Historic'!F18 -> 37802 | H44: ='Balance Sheet- Historic'!G18 -> 42203 | I44: =H44 -> 42203 | J44: =I44 -> 42203 | K44: =J44 -> 42203 | L44: =K44 -> 42203 | M44: =L44 -> 42203 | N44: =M44 -> 42203 | O44: =N44 -> 42203 | P44: =O44 -> 42203 | ... R44: =Q44 -> 42203
A45: Total Non-Current Assets | B45: ₹ Lakhs | D45: =SUM(D36:D44) -> 252860 | E45: =SUM(E36:E44) -> 257018 | F45: =SUM(F36:F44) -> 259394 | G45: =SUM(G36:G44) -> 263790 | H45: =SUM(H36:H44) -> 276987 | I45: =SUM(I36:I44) -> 271862.06 | J45: =SUM(J36:J44) -> 267908.47 | K45: =SUM(K36:K44) -> 263697.91 | ... R45: =SUM(R36:R44) -> 226427.02
A46: Assets held for sale | B46: ₹ Lakhs | D46: ='Balance Sheet- Historic'!C27 -> 488 | E46: ='Balance Sheet- Historic'!D27 -> 488 | F46: ='Balance Sheet- Historic'!E27 -> 486 | G46: ='Balance Sheet- Historic'!F27 -> 493 | H46: ='Balance Sheet- Historic'!G27 -> 486 | I46: =AVERAGE(D46:H46) -> 488.2 | J46: =AVERAGE(E46:I46) -> 488.24 | K46: =AVERAGE(F46:J46) -> 488.288 | L46: =AVERAGE(G46:K46) -> 488.7456 | M46: =AVERAGE(H46:L46) -> 487.89472 | N46: =AVERAGE(I46:M46) -> 488.27366 | O46: =AVERAGE(J46:N46) -> 488.2884 | P46: =AVERAGE(K46:O46) -> 488.29808 | ... R46: =AVERAGE(M46:Q46) -> 488.21099
A47: Total Assets | B47: ₹ Lakhs | D47: ='Balance Sheet- Historic'!C28 -> 585216 | E47: ='Balance Sheet- Historic'!D28 -> 594931 | F47: ='Balance Sheet- Historic'!E28 -> 628039 | G47: ='Balance Sheet- Historic'!F28 -> 705337 | H47: ='Balance Sheet- Historic'!G28 -> 822279 | I47: =SUM(I45,I35,I46) -> 814710.04 | J47: =SUM(J45,J35,J46) -> 848858.42 | K47: =SUM(K45,K35,K46) -> 891270.73 | L47: =SUM(L45,L35,L46) -> 952795.82 | M47: =SUM(M45,M35,M46) -> 1026852.4 | N47: =SUM(N45,N35,N46) -> 1116338.8 | O47: =SUM(O45,O35,O46) -> 1232679.3 | P47: =SUM(P45,P35,P46) -> 1365063.2 | ... R47: =SUM(R45,R35,R46) -> 1674736.6
A48: Equity Share Capital | B48: ₹ Lakhs | D48: ='Balance Sheet- Historic'!C30 -> 2644 | E48: ='Balance Sheet- Historic'!D30 -> 2644 | F48: ='Balance Sheet- Historic'!E30 -> 2644 | G48: ='Balance Sheet- Historic'!F30 -> 2644 | H48: ='Balance Sheet- Historic'!G30 -> 2644 | I48: =H48 -> 2644 | J48: =I48 -> 2644 | K48: =J48 -> 2644 | L48: =K48 -> 2644 | M48: =L48 -> 2644 | N48: =M48 -> 2644 | O48: =N48 -> 2644 | P48: =O48 -> 2644 | ... R48: =Q48 -> 2644
A49: Other Equity | B49: ₹ Lakhs | D49: ='Working '!H161 -> 355584 | E49: ='Working '!I161 -> 390868 | F49: ='Working '!J161 -> 393845 | G49: ='Working '!K161 -> 415190 | H49: ='Working '!L161 -> 433748 | I49: ='Working '!M161 -> 451676.54 | J49: ='Working '!N161 -> 474283.13 | K49: ='Working '!O161 -> 512657.65 | ... R49: ='Working '!V161 -> 1223973.9
A50: Equity attributable to owners of the parent | B50: ₹ Lakhs | D50: =SUM(D48:D49) -> 358228 | E50: =SUM(E48:E49) -> 393512 | F50: =SUM(F48:F49) -> 396489 | G50: =SUM(G48:G49) -> 417834 | H50: =SUM(H48:H49) -> 436392 | I50: =SUM(I48:I49) -> 454320.54 | J50: =SUM(J48:J49) -> 476927.13 | K50: =SUM(K48:K49) -> 515301.65 | ... R50: =SUM(R48:R49) -> 1226617.9
A51: Non-controlling interests | B51: ₹ Lakhs | D51: ='Balance Sheet- Historic'!C33 -> 375 | E51: ='Balance Sheet- Historic'!D33 -> 414 | F51: ='Balance Sheet- Historic'!E33 -> 461 | G51: ='Balance Sheet- Historic'!F33 -> 522 | H51: ='Balance Sheet- Historic'!G33 -> 572 | I51: =H51 -> 572 | J51: =I51 -> 572 | K51: =J51 -> 572 | L51: =K51 -> 572 | M51: =L51 -> 572 | N51: =M51 -> 572 | O51: =N51 -> 572 | P51: =O51 -> 572 | ... R51: =Q51 -> 572
A52: Total Equity | B52: ₹ Lakhs | D52: =SUM(D50:D51) -> 358603 | E52: =SUM(E50:E51) -> 393926 | F52: =SUM(F50:F51) -> 396950 | G52: =SUM(G50:G51) -> 418356 | H52: =SUM(H50:H51) -> 436964 | I52: =SUM(I50:I51) -> 454892.54 | J52: =SUM(J50:J51) -> 477499.13 | K52: =SUM(K50:K51) -> 515873.65 | ... R52: =SUM(R50:R51) -> 1227189.9
A53: Borrowings | B53: ₹ Lakhs | D53: ='Balance Sheet- Historic'!C37 -> 11524 | E53: ='Balance Sheet- Historic'!D37 -> 0 | F53: ='Balance Sheet- Historic'!E37 -> 0 | G53: ='Balance Sheet- Historic'!F37 -> 0 | H53: ='Balance Sheet- Historic'!G37 -> 0 | I53: 0 | J53: 0 | K53: 0 | L53: 0 | M53: 0 | N53: 0 | O53: 0 | P53: 0 | Q53: 0 | R53: 0
A54: Lease Liabilities | B54: ₹ Lakhs | D54: ='Balance Sheet- Historic'!C38 -> — | E54: ='Balance Sheet- Historic'!D38 -> 606 | F54: ='Balance Sheet- Historic'!E38 -> 1074 | G54: ='Balance Sheet- Historic'!F38 -> 1690 | H54: ='Balance Sheet- Historic'!G38 -> 3569 | I54: 0 | J54: 0 | K54: 0 | L54: 0 | M54: 0 | N54: 0 | O54: 0 | P54: 0 | Q54: 0 | R54: 0
A55: Other Financial Liabilities | B55: ₹ Lakhs | D55: ='Balance Sheet- Historic'!C39 -> 1109 | E55: ='Balance Sheet- Historic'!D39 -> 2497 | F55: ='Balance Sheet- Historic'!E39 -> 1845 | G55: ='Balance Sheet- Historic'!F39 -> 1461 | H55: ='Balance Sheet- Historic'!G39 -> 2040 | I55: =H55 -> 2040 | J55: =I55 -> 2040 | K55: =J55 -> 2040 | L55: =K55 -> 2040 | M55: =L55 -> 2040 | N55: =M55 -> 2040 | O55: =N55 -> 2040 | P55: =O55 -> 2040 | ... R55: =Q55 -> 2040
A56: Provisions | B56: ₹ Lakhs | D56: ='Balance Sheet- Historic'!C40 -> 160 | E56: ='Balance Sheet- Historic'!D40 -> 441 | F56: ='Balance Sheet- Historic'!E40 -> 424 | G56: ='Balance Sheet- Historic'!F40 -> 917 | H56: ='Balance Sheet- Historic'!G40 -> 1405 | I56: =H56 -> 1405 | J56: =I56 -> 1405 | K56: =J56 -> 1405 | L56: =K56 -> 1405 | M56: =L56 -> 1405 | N56: =M56 -> 1405 | O56: =N56 -> 1405 | P56: =O56 -> 1405 | ... R56: =Q56 -> 1405
A57: Total Non-Current Liabilities | B57: ₹ Lakhs | D57: =SUM(D53:D56) -> 12793 | E57: 3544 | F57: 3343 | G57: 4068 | H57: 7014 | I57: =SUM(I53:I56) -> 3445 | J57: =SUM(J53:J56) -> 3445 | K57: =SUM(K53:K56) -> 3445 | L57: =SUM(L53:L56) -> 3445 | M57: =SUM(M53:M56) -> 3445 | N57: =SUM(N53:N56) -> 3445 | O57: =SUM(O53:O56) -> 3445 | P57: =SUM(P53:P56) -> 3445 | ... R57: =SUM(R53:R56) -> 3445
A58: Current Borrowings | B58: ₹ Lakhs | D58: ='Balance Sheet- Historic'!C44 -> 17 | E58: ='Balance Sheet- Historic'!D44 -> 0 | F58: ='Balance Sheet- Historic'!E44 -> 0 | G58: ='Balance Sheet- Historic'!F44 -> 7741 | H58: ='Balance Sheet- Historic'!G44 -> 57485 | I58: ='Working '!M117 -> 57485 | J58: ='Working '!N117 -> 57485 | K58: ='Working '!O117 -> 57485 | L58: ='Working '!P117 -> 57485 | M58: ='Working '!Q117 -> 57485 | N58: ='Working '!R117 -> 57485 | O58: ='Working '!S117 -> 57485 | P58: ='Working '!T117 -> 57485 | ... R58: ='Working '!V117 -> 57485
A59: Current Lease Liabilities | B59: ₹ Lakhs | D59: ='Balance Sheet- Historic'!C45 -> — | E59: ='Balance Sheet- Historic'!D45 -> 368 | F59: ='Balance Sheet- Historic'!E45 -> 488 | G59: ='Balance Sheet- Historic'!F45 -> 772 | H59: ='Balance Sheet- Historic'!G45 -> 944 | I59: ='Working '!M124 -> 5415.6 | J59: ='Working '!N124 -> 6498.72 | K59: ='Working '!O124 -> 7603.664 | L59: ='Working '!P124 -> 8811.9968 | M59: ='Working '!Q124 -> 10081.996 | N59: ='Working '!R124 -> 11195.795 | O59: ='Working '!S124 -> 12351.834 | P59: ='Working '!T124 -> 13522.457 | ... R59: ='Working '!V124 -> 15885.06
A60: Trade Payables | B60: ₹ Lakhs | D60: 61808 | E60: 63800 | F60: 71698 | G60: 94845 | H60: 114955 | I60: ='Working '!M82 -> 110042.49 | J60: ='Working '!N82 -> 115451.37 | K60: ='Working '!O82 -> 116650.24 | L60: ='Working '!P82 -> 119727.9 | M60: ='Working '!Q82 -> 121981.34 | N60: ='Working '!R82 -> 124283.21 | O60: ='Working '!S82 -> 130760.54 | P60: ='Working '!T82 -> 138330.32 | ... R60: ='Working '!V82 -> 152509.17
A61: Other Financial Liabilities | D61: ='Balance Sheet- Historic'!C48 -> 68177 | E61: ='Balance Sheet- Historic'!D48 -> 55810 | F61: ='Balance Sheet- Historic'!E48 -> 77835 | G61: ='Balance Sheet- Historic'!F48 -> 86664 | H61: ='Balance Sheet- Historic'!G48 -> 100578 | I61: =I8*5.1% -> 105912.4 | J61: =J8*5.1% -> 113326.27 | K61: =K8*5.1% -> 120692.48 | L61: =L8*5.1% -> 128537.49 | M61: =M8*5.1% -> 136249.74 | N61: =N8*5.1% -> 144424.72 | O61: =O8*5.1% -> 152368.08 | P61: =P8*5.1% -> 160748.33 | ... R61: =R8*5.1% -> 177225.03
A62: Other Current Liabilities | B62: ₹ Lakhs | D62: 74710 | E62: 67261 | F62: 67518 | G62: 83327 | H62: 94769 | I62: =AVERAGE(D62:H62) -> 77517 | J62: =AVERAGE(E62:I62) -> 78078.4 | K62: =AVERAGE(F62:J62) -> 80241.88 | L62: =AVERAGE(G62:K62) -> 82786.656 | M62: =AVERAGE(H62:L62) -> 82678.587 | N62: =AVERAGE(I62:M62) -> 80260.505 | O62: =AVERAGE(J62:N62) -> 80809.206 | P62: =AVERAGE(K62:O62) -> 81355.367 | ... R62: =AVERAGE(M62:Q62) -> 81336.346
A63: Current Provisions | B63: ₹ Lakhs | D63: 9108 | E63: 10222 | F63: 10207 | G63: 9564 | H63: 9570 | I63: 0 | J63: 0 | K63: 0 | L63: 0 | M63: 0 | N63: 0 | O63: 0 | P63: 0 | Q63: 0 | R63: 0
A64: Total Current Liabilities | B64: ₹ Lakhs | D64: ='Balance Sheet- Historic'!C51 -> 213820 | E64: ='Balance Sheet- Historic'!D51 -> 197461 | F64: ='Balance Sheet- Historic'!E51 -> 227746 | G64: ='Balance Sheet- Historic'!F51 -> 282913 | H64: ='Balance Sheet- Historic'!G51 -> 378301 | I64: =SUM(I58:I63) -> 356372.5 | J64: =SUM(J58:J63) -> 370839.76 | K64: =SUM(K58:K63) -> 382673.27 | L64: =SUM(L58:L63) -> 397349.05 | M64: =SUM(M58:M63) -> 408476.66 | N64: =SUM(N58:N63) -> 417649.23 | O64: =SUM(O58:O63) -> 433774.66 | P64: =SUM(P58:P63) -> 451441.47 | ... R64: =SUM(R58:R63) -> 484440.61
A65: Total Liabilities | B65: ₹ Lakhs | D65: ='Balance Sheet- Historic'!C52 -> 226613 | E65: ='Balance Sheet- Historic'!D52 -> 201005 | F65: ='Balance Sheet- Historic'!E52 -> 231089 | G65: ='Balance Sheet- Historic'!F52 -> 286981 | H65: ='Balance Sheet- Historic'!G52 -> 385315 | I65: =SUM(I64,I57) -> 359817.5 | J65: =SUM(J64,J57) -> 374284.76 | K65: =SUM(K64,K57) -> 386118.27 | L65: =SUM(L64,L57) -> 400794.05 | M65: =SUM(M64,M57) -> 411921.66 | N65: =SUM(N64,N57) -> 421094.23 | O65: =SUM(O64,O57) -> 437219.66 | P65: =SUM(P64,P57) -> 454886.47 | ... R65: =SUM(R64,R57) -> 487885.61
A66: Total Equity & Liabilities | B66: ₹ Lakhs | D66: ='Balance Sheet- Historic'!C53 -> 585216 | E66: ='Balance Sheet- Historic'!D53 -> 594931 | F66: ='Balance Sheet- Historic'!E53 -> 628039 | G66: ='Balance Sheet- Historic'!F53 -> 705337 | H66: ='Balance Sheet- Historic'!G53 -> 822279 | I66: =SUM(I65,I52) -> 814710.04 | J66: =SUM(J65,J52) -> 851783.89 | K66: =SUM(K65,K52) -> 901991.91 | L66: =SUM(L65,L52) -> 970424.39 | M66: =SUM(M65,M52) -> 1051828.7 | N66: =SUM(N65,N52) -> 1149212 | O66: =SUM(O65,O52) -> 1267265.5 | P66: =SUM(P65,P52) -> 1401651.6 | ... R66: =SUM(R65,R52) -> 1715075.5
D67: =D47-D66 -> 0 | E67: =E47-E66 -> 0 | F67: =F47-F66 -> 0 | G67: =G47-G66 -> 0 | H67: =H47-H66 -> 0 | I67: =I47-I66 -> 0.0033419642 | J67: =J47-J66 -> -2925.4646 | K67: =K47-K66 -> -10721.178 | ... R67: =R47-R66 -> -40338.899
J68: =J67-I67 -> -2925.468 | K68: =K67-J67 -> -7795.713 | L68: =L67-K67 -> -6907.3931 | M68: =M67-L67 -> -7347.7093 | N68: =N67-M67 -> -7896.978 | O68: =O67-N67 -> -1712.9091 | P68: =P67-O67 -> -2002.2189 | Q68: =Q67-P67 -> -1829.8868 | R68: =R67-Q67 -> -1920.6262
A69: Cash Flow Statement
A70: CASH FLOW FROM OPERATING ACTIVITIES | B70: ₹ Lakhs
A72: Profit before tax | B72: ₹ Lakhs | D72: ='Cash flow-Historic'!B14 -> 16941 | E72: ='Cash flow-Historic'!C14 -> 49444 | F72: ='Cash flow-Historic'!D14 -> 41731 | G72: ='Cash flow-Historic'!E14 -> 55114 | H72: ='Cash flow-Historic'!F14 -> 60511 | I72: =I23 -> 53807.144 | J72: =J23 -> 67846.898 | K72: =K23 -> 115169.63 | L72: =L23 -> 161334.64 | M72: =M23 -> 210914.49 | N72: =N23 -> 264738.1 | O72: =O23 -> 305906.54 | P72: =P23 -> 350298.04 | ... R72: =R23 -> 445370.52
A73: Depreciation and amortisation expense | B73: ₹ Lakhs | D73: ='Working '!H48 -> 23201 | E73: ='Working '!I48 -> 21719 | F73: ='Working '!J48 -> 21059 | G73: ='Working '!K48 -> 21190 | H73: ='Working '!L48 -> 23298 | I73: ='Working '!M48 -> 31361.449 | J73: ='Working '!N48 -> 33556.751 | K73: ='Working '!O48 -> 35737.939 | ... R73: ='Working '!V48 -> 52477.648
A74: Other operating adjustments | B74: ₹ Lakhs | D74: ='Working '!H132 -> 30114 | E74: ='Working '!I132 -> 67898 | F74: ='Working '!J132 -> -117321 | G74: ='Working '!K132 -> -117076 | H74: ='Working '!L132 -> -100450 | I74: ='Working '!M132 -> 23345 | J74: ='Working '!N132 -> -38216 | K74: ='Working '!O132 -> -34306 | ... R74: ='Working '!V132 -> -44507
A75: Change in working capital | B75: ₹ Lakhs | D75: 0 | E75: ='Working '!I89 -> -36092 | F75: ='Working '!J89 -> 56548 | G75: ='Working '!K89 -> 61598 | H75: ='Working '!L89 -> 59338 | I75: ='Working '!M89 -> -17222.762 | J75: ='Working '!N89 -> 20623.943 | K75: ='Working '!O89 -> 17064.752 | L75: ='Working '!P89 -> 20899.899 | ... R75: ='Working '!V89 -> 24181.389
A76: Cash generated from operations | B76: ₹ Lakhs | D76: ='Cash flow-Historic'!B37 -> 70256 | E76: ='Cash flow-Historic'!C37 -> 102969 | F76: ='Cash flow-Historic'!D37 -> 2017 | G76: ='Cash flow-Historic'!E37 -> 20826 | H76: ='Cash flow-Historic'!F37 -> 42697 | I76: =SUM('Working '!M130:M133) -> 91290.832 | J76: =SUM('Working '!N130:N133) -> 83811.591 | K76: =SUM('Working '!O130:O133) -> 133666.32 | L76: =SUM('Working '!P130:P133) -> 179890.44 | M76: =SUM('Working '!Q130:Q133) -> 230277.86 | N76: =SUM('Working '!R130:R133) -> 282600.97 | O76: =SUM(O72:O75) -> 334047.39 | P76: =SUM(P72:P75) -> 377219.88 | Q76: =SUM(Q72:Q75) -> 427413.02 | R76: =SUM(R72:R75) -> 477522.56
A77: Direct taxes paid | B77: ₹ Lakhs | D77: ='Income Statement-Historic'!C35 -> -5558 | E77: ='Income Statement-Historic'!D35 -> -12836 | F77: ='Income Statement-Historic'!E35 -> -11263 | G77: ='Income Statement-Historic'!F35 -> -14028 | H77: ='Income Statement-Historic'!G35 -> -16270 | I77: =-I23*Assumptions!$C$107 -> -16142.143 | J77: =-J23*Assumptions!$C$107 -> -20354.069 | K77: =-K23*Assumptions!$C$107 -> -34550.888 | L77: =-L23*Assumptions!$C$107 -> -48400.391 | M77: =-M23*Assumptions!$C$107 -> -63274.348 | N77: =-N23*Assumptions!$C$107 -> -79421.431 | O77: =-O23*Assumptions!$C$107 -> -91771.961 | P77: =-P23*Assumptions!$C$107 -> -105089.41 | ... R77: =-R23*Assumptions!$C$107 -> -133611.16
A78: Net Cash Flow from Operating Activities | B78: ₹ Lakhs | D78: ='Cash flow-Historic'!B39 -> 62028 | E78: ='Cash flow-Historic'!C39 -> 89962 | F78: ='Cash flow-Historic'!D39 -> -11957 | G78: ='Cash flow-Historic'!E39 -> 6950 | H78: ='Cash flow-Historic'!F39 -> 23505 | I78: ='Working '!M135 -> 75148.688 | J78: =J76+J77 -> 63457.521 | K78: =K76+K77 -> 99115.431 | L78: =L76+L77 -> 131490.05 | M78: =M76+M77 -> 167003.51 | N78: =N76+N77 -> 203179.54 | O78: =O76+O77 -> 242275.43 | P78: =P76+P77 -> 272130.47 | Q78: =Q76+Q77 -> 308540.9 | R78: =R76+R77 -> 343911.4
B79: ₹ Lakhs
B80: ₹ Lakhs
A81: CASH FLOW FROM INVESTING ACTIVITIES | B81: ₹ Lakhs
B82: ₹ Lakhs
A83: Capital Expenditure | B83: ₹ Lakhs | D83: ='Working '!H93 -> -20282 | E83: ='Working '!I93 -> -16174 | F83: ='Working '!J93 -> -11595 | G83: ='Working '!K93 -> -23200 | H83: ='Working '!L93 -> -28703 | I83: ='Working '!M93 -> -27666.509 | J83: ='Working '!N93 -> -29603.165 | K83: ='Working '!O93 -> -31527.37 | ... R83: ='Working '!V93 -> -46294.842
A84: Other Investing Cash Flows | B84: ₹ Lakhs | D84: ='Cash flow-Historic'!B49-'Cash flow-Historic'!B42 -> 4911 | E84: ='Cash flow-Historic'!C49-'Cash flow-Historic'!C42 -> 1348 | F84: ='Cash flow-Historic'!D49-'Cash flow-Historic'!D42 -> 3545 | G84: ='Cash flow-Historic'!E49-'Cash flow-Historic'!E42 -> 4369 | H84: ='Cash flow-Historic'!F49-'Cash flow-Historic'!F42 -> 1888 | I84: 0 | J84: 0 | K84: 0 | L84: 0 | M84: 0 | N84: 0 | O84: 0 | P84: 0 | Q84: 0 | R84: 0
A85: Net Cash Flow from Investing Activities | B85: ₹ Lakhs | D85: ='Cash flow-Historic'!B49 -> -15155 | E85: ='Cash flow-Historic'!C49 -> -16007 | F85: ='Cash flow-Historic'!D49 -> -12083 | G85: ='Cash flow-Historic'!E49 -> -14781 | H85: ='Cash flow-Historic'!F49 -> -23942 | I85: =SUM(I83:I84) -> -27666.509 | J85: =SUM(J83:J84) -> -29603.165 | K85: =SUM(K83:K84) -> -31527.37 | L85: =SUM(L83:L84) -> -33576.65 | M85: =SUM(M83:M84) -> -35591.248 | N85: =SUM(N83:N84) -> -37726.723 | O85: =SUM(O83:O84) -> -39801.693 | P85: =SUM(P83:P84) -> -41990.786 | ... R85: =SUM(R83:R84) -> -46294.842
A88: CASH FLOW FROM FINANCING ACTIVITIES | B88: ₹ Lakhs
A90: Debt Drawdown / (Repayment) | B90: ₹ Lakhs | D90: =SUM('Cash flow-Historic'!B52:B53,'Cash flow-Historic'!B55) -> 1459 | E90: =SUM('Cash flow-Historic'!C52:C53,'Cash flow-Historic'!C55) -> -25017 | F90: =SUM('Cash flow-Historic'!D52:D53,'Cash flow-Historic'!D55) -> 0 | G90: =SUM('Cash flow-Historic'!E52:E53,'Cash flow-Historic'!E55) -> 7741 | H90: =SUM('Cash flow-Historic'!F52:F53,'Cash flow-Historic'!F55) -> 49744 | I90: ='Working '!M114+'Working '!M115 -> 0 | J90: ='Working '!N114+'Working '!N115 -> 0 | K90: ='Working '!O114+'Working '!O115 -> 0 | L90: ='Working '!P114+'Working '!P115 -> 0 | M90: ='Working '!Q114+'Working '!Q115 -> 0 | N90: ='Working '!R114+'Working '!R115 -> 0 | O90: ='Working '!S114+'Working '!S115 -> 0 | P90: ='Working '!T114+'Working '!T115 -> 0 | ... R90: ='Working '!V114+'Working '!V115 -> 0
A91: Lease Payments | B91: ₹ Lakhs | D91: ='Cash flow-Historic'!B54 -> -853 | E91: ='Cash flow-Historic'!C54 -> -492 | F91: ='Cash flow-Historic'!D54 -> -998 | G91: ='Cash flow-Historic'!E54 -> -727 | H91: ='Cash flow-Historic'!F54 -> -953 | I91: ='Working '!M122 -> -804.6 | J91: ='Working '!N122 -> -794.92 | K91: ='Working '!O122 -> -855.504 | L91: ='Working '!P122 -> -827.0048 | M91: ='Working '!Q122 -> -847.00576 | N91: ='Working '!R122 -> -825.80691 | O91: ='Working '!S122 -> -830.04829 | P91: ='Working '!T122 -> -837.07395 | ... R91: ='Working '!V122 -> -834.66457
A92: Dividends Paid | B92: ₹ Lakhs | D92: ='Cash flow-Historic'!B57 -> -6610 | E92: ='Cash flow-Historic'!C57 -> -1344 | F92: ='Cash flow-Historic'!D57 -> -27785 | G92: ='Cash flow-Historic'!E57 -> -19852 | H92: ='Cash flow-Historic'!F57 -> -26463 | I92: ='Working '!M159 -> -19736.46 | J92: ='Working '!N159 -> -24886.242 | K92: ='Working '!O159 -> -42244.219 | L92: ='Working '!P159 -> -59177.544 | M92: ='Working '!Q159 -> -77363.436 | N92: ='Working '!R159 -> -97105.936 | O92: ='Working '!S159 -> -112206.52 | P92: ='Working '!T159 -> -128489.32 | ... R92: ='Working '!V159 -> -163361.91
A93: Other Financing Cash Flows | B93: ₹ Lakhs | D93: =-'Working '!H45 -> -2267 | E93: =-'Working '!I45 -> -1478 | F93: =-'Working '!J45 -> -464 | G93: =-'Working '!K45 -> -689 | H93: =-'Working '!L45 -> -1286 | I93: 0 | J93: 0 | K93: 0 | L93: 0 | M93: 0 | N93: 0 | O93: 0 | P93: 0 | Q93: 0 | R93: 0
A94: Net Cash Flow from Financing Activities | B94: ₹ Lakhs | D94: ='Cash flow-Historic'!B59 -> -8817 | E94: ='Cash flow-Historic'!C59 -> -28665 | F94: ='Cash flow-Historic'!D59 -> -29234 | G94: ='Cash flow-Historic'!E59 -> -12240 | H94: ='Cash flow-Historic'!F59 -> 21714 | I94: =SUM(I90:I93) -> -20541.06 | J94: =SUM(J90:J93) -> -25681.162 | K94: =SUM(K90:K93) -> -43099.723 | L94: =SUM(L90:L93) -> -60004.549 | M94: =SUM(M90:M93) -> -78210.442 | N94: =SUM(N90:N93) -> -97931.743 | O94: =SUM(O90:O93) -> -113036.57 | P94: =SUM(P90:P93) -> -129326.39 | ... R94: =SUM(R90:R93) -> -164196.57
A97: Net Increase / (Decrease) in Cash | B97: ₹ Lakhs | D97: ='Cash flow-Historic'!B61 -> 38041 | E97: ='Cash flow-Historic'!C61 -> 45290 | F97: ='Cash flow-Historic'!D61 -> -53274 | G97: ='Cash flow-Historic'!E61 -> -20071 | H97: ='Cash flow-Historic'!F61 -> 21277 | I97: =SUM(I94,I85,I78) -> 26941.119 | J97: =SUM(J94,J85,J78) -> 8173.1947 | K97: =SUM(K94,K85,K78) -> 24488.337 | L97: =SUM(L94,L85,L78) -> 37908.85 | M97: =SUM(M94,M85,M78) -> 53201.822 | N97: =SUM(N94,N85,N78) -> 67521.077 | O97: =SUM(O94,O85,O78) -> 89437.171 | P97: =SUM(P94,P85,P78) -> 100813.29 | ... R97: =SUM(R94,R85,R78) -> 133419.99
A98: Beginning Cash Balance | B98: ₹ Lakhs | D98: ='Cash flow-Historic'!B62 -> 2899 | E98: ='Cash flow-Historic'!C62 -> 40970 | F98: ='Cash flow-Historic'!D62 -> 86260 | G98: ='Cash flow-Historic'!E62 -> 32986 | H98: ='Cash flow-Historic'!F62 -> 12915 | I98: =H99 -> 34192 | J98: =I99 -> 61133.119 | K98: =J99 -> 69306.314 | L98: =K99 -> 93794.651 | M98: =L99 -> 131703.5 | N98: =M99 -> 184905.32 | O98: =N99 -> 252426.4 | P98: =O99 -> 341863.57 | ... R98: =Q99 -> 560953.06
A99: Ending Cash Balance | B99: ₹ Lakhs | D99: ='Cash flow-Historic'!B63 -> 40940 | E99: ='Cash flow-Historic'!C63 -> 86260 | F99: ='Cash flow-Historic'!D63 -> 32986 | G99: ='Cash flow-Historic'!E63 -> 12915 | H99: ='Cash flow-Historic'!F63 -> 34192 | I99: =SUM(I97:I98) -> 61133.119 | J99: =SUM(J97:J98) -> 69306.314 | K99: =SUM(K97:K98) -> 93794.651 | L99: =SUM(L97:L98) -> 131703.5 | M99: =SUM(M97:M98) -> 184905.32 | N99: =SUM(N97:N98) -> 252426.4 | O99: =SUM(O97:O98) -> 341863.57 | P99: =SUM(P97:P98) -> 442676.86 | ... R99: =SUM(R97:R98) -> 694373.05

Sheet Valuation
A1: United Breweries Limited
A2: Discounted Cash Flow Analysis
A4: Calculation of PV of FCFF
B5: FY2021 H | C5: FY2022` H | D5: FY2023 H | E5: FY2024 H | F5: FY2025 H | G5: FY2026 | H5: FY2027 | I5: FY2028 | J5: FY2029 | K5: FY2030 | L5: FY2031 | M5: FY2032 | N5: FY2033 | O5: FY2034 | P5: FY2035
A6: EBIT | B6: =FS!D26 -> 19208 | C6: =FS!E26 -> 50922 | D6: =FS!F26 -> 42195 | E6: =FS!G26 -> 55803 | F6: =FS!H26 -> 61797 | G6: =FS!I26 -> 55745.953 | H6: =FS!J26 -> 69921.423 | I6: =FS!K26 -> 117379 | ... P6: =FS!R26 -> 448614.76
A7: Tax Rate | B7: =-B6*Assumptions!$C$107 -> -5762.4 | C7: =-C6*Assumptions!$C$107 -> -15276.6 | D7: =-D6*Assumptions!$C$107 -> -12658.5 | E7: =-E6*Assumptions!$C$107 -> -16740.9 | F7: =-F6*Assumptions!$C$107 -> -18539.1 | G7: =-G6*Assumptions!$C$107 -> -16723.786 | H7: =-H6*Assumptions!$C$107 -> -20976.427 | I7: =-I6*Assumptions!$C$107 -> -35213.699 | ... P7: =-P6*Assumptions!$C$107 -> -134584.43
A8: EBIT (1-Tax) | B8: =SUM(B6:B7) -> 13445.6 | C8: =SUM(C6:C7) -> 35645.4 | D8: =SUM(D6:D7) -> 29536.5 | E8: =SUM(E6:E7) -> 39062.1 | F8: =SUM(F6:F7) -> 43257.9 | G8: =SUM(G6:G7) -> 39022.167 | H8: =SUM(H6:H7) -> 48944.996 | I8: =SUM(I6:I7) -> 82165.298 | ... P8: =SUM(P6:P7) -> 314030.34
A9: Add: D&A | B9: =FS!D18 -> 23201 | C9: =FS!E18 -> 21719 | D9: =FS!F18 -> 21059 | E9: =FS!G18 -> 21190 | F9: =FS!H18 -> 23298 | G9: =FS!I18 -> 31361.449 | H9: =FS!J18 -> 33556.751 | I9: =FS!K18 -> 35737.939 | ... P9: =FS!R18 -> 52477.648
A10: Less: CAPEX | B10: ='Working '!H93 -> -20282 | C10: ='Working '!I93 -> -16174 | D10: ='Working '!J93 -> -11595 | E10: ='Working '!K93 -> -23200 | F10: ='Working '!L93 -> -28703 | G10: ='Working '!M93 -> -27666.509 | H10: ='Working '!N93 -> -29603.165 | I10: ='Working '!O93 -> -31527.37 | ... P10: ='Working '!V93 -> -46294.842
A11: Less: Change in NWC | B11: =-'Working '!H89 -> 0 | C11: =-'Working '!I89 -> 36092 | D11: =-'Working '!J89 -> -56548 | E11: =-'Working '!K89 -> -61598 | F11: =-'Working '!L89 -> -59338 | G11: =-'Working '!M89 -> 17222.762 | H11: =-'Working '!N89 -> -20623.943 | I11: =-'Working '!O89 -> -17064.752 | ... P11: =-'Working '!V89 -> -24181.389
A12: Free Cash Flow to Firm (FCFF) | B12: =SUM(B8:B11) -> 16364.6 | C12: =SUM(C8:C11) -> 77282.4 | D12: =SUM(D8:D11) -> -17547.5 | E12: =SUM(E8:E11) -> -24545.9 | F12: =SUM(F8:F11) -> -21485.1 | G12: =SUM(G8:G11) -> 59939.869 | H12: =SUM(H8:H11) -> 32274.639 | I12: =SUM(I8:I11) -> 69311.114 | ... P12: =SUM(P8:P11) -> 296031.75
A13: Mid-Year Convention | G13: 0.5 | H13: 1.5 | I13: =H13+0.5 -> 2 | J13: =I13+0.5 -> 2.5 | K13: =J13+0.5 -> 3 | L13: =K13+0.5 -> 3.5 | M13: =L13+0.5 -> 4 | N13: =M13+0.5 -> 4.5 | O13: =N13+0.5 -> 5 | P13: =O13+0.5 -> 5.5
A14: Discounting Factor | G14: =1/(1+$B$49)^(G13) -> 0.94121154 | H14: =1/(1+$B$49)^(H13) -> 0.8337997 | I14: =1/(1+$B$49)^(I13) -> 0.7847819 | J14: =1/(1+$B$49)^(J13) -> 0.73864578 | K14: =1/(1+$B$49)^(K13) -> 0.69522193 | L14: =1/(1+$B$49)^(L13) -> 0.65435091 | M14: =1/(1+$B$49)^(M13) -> 0.61588263 | N14: =1/(1+$B$49)^(N13) -> 0.57967584 | ... P14: =1/(1+$B$49)^(P13) -> 0.51352275
A15: PV of FCFF | B15: =B12 -> 16364.6 | C15: =C12 -> 77282.4 | D15: =D12 -> -17547.5 | E15: =E12 -> -24545.9 | F15: =F12 -> -21485.1 | G15: =G12*G14 -> 56416.096 | H15: =H12*H14 -> 26910.585 | I15: =I12*I14 -> 54394.108 | J15: =J12*J14 -> 72509.67 | K15: =K12*K14 -> 93741.333 | L15: =L12*L14 -> 112417.62 | M15: =M12*M14 -> 123074.98 | N15: =N12*N14 -> 131975.6 | ... P15: =P12*P14 -> 152019.04
A17: FCFE Valuation
A18: Net Income | B18: =FS!D25 -> 11383 | C18: =FS!E25 -> 36608 | D18: =FS!F25 -> 30468 | E18: =FS!G25 -> 41086 | F18: =FS!H25 -> 44241 | G18: =FS!I25 -> 37665.001 | H18: =FS!J25 -> 47492.828 | I18: =FS!K25 -> 80618.739 | ... P18: =FS!R25 -> 311759.37
A19: + Depreciation & Amortisation | B19: =B9 -> 23201 | C19: =C9 -> 21719 | D19: =D9 -> 21059 | E19: =E9 -> 21190 | F19: =F9 -> 23298 | G19: =G9 -> 31361.449 | H19: =H9 -> 33556.751 | I19: =I9 -> 35737.939 | ... P19: =P9 -> 52477.648
A20: - Capital Expenditure | B20: =B10 -> -20282 | C20: =C10 -> -16174 | D20: =D10 -> -11595 | E20: =E10 -> -23200 | F20: =F10 -> -28703 | G20: =G10 -> -27666.509 | H20: =H10 -> -29603.165 | I20: =I10 -> -31527.37 | ... P20: =P10 -> -46294.842
A21: - Change in Working Capital | B21: =B11 -> 0 | C21: =C11 -> 36092 | D21: =D11 -> -56548 | E21: =E11 -> -61598 | F21: =F11 -> -59338 | G21: =G11 -> 17222.762 | H21: =H11 -> -20623.943 | I21: =I11 -> -17064.752 | ... P21: =P11 -> -24181.389
A22: + Net Borrowing | B22: ='Working '!H114+'Working '!H115 -> 1459 | C22: ='Working '!I114+'Working '!I115 -> -25017 | D22: ='Working '!J114+'Working '!J115 -> 0 | E22: ='Working '!K114+'Working '!K115 -> 7741 | F22: ='Working '!L114+'Working '!L115 -> 49744 | G22: ='Working '!M114+'Working '!M115 -> 0 | H22: ='Working '!N114+'Working '!N115 -> 0 | I22: ='Working '!O114+'Working '!O115 -> 0 | ... P22: ='Working '!V114+'Working '!V115 -> 0
A23: FCFE | B23: =SUM(B18:B22) -> 15761 | C23: =SUM(C18:C22) -> 53228 | D23: =SUM(D18:D22) -> -16616 | E23: =SUM(E18:E22) -> -14781 | F23: =SUM(F18:F22) -> 29242 | G23: =SUM(G18:G22) -> 58582.702 | H23: =SUM(H18:H22) -> 30822.472 | I23: =SUM(I18:I22) -> 67764.556 | ... P23: =SUM(P18:P22) -> 293760.78
A24: Mid-Year Convention | G24: 0.5 | H24: 1.5 | I24: =H24+0.5 -> 2 | J24: =I24+0.5 -> 2.5 | K24: =J24+0.5 -> 3 | L24: =K24+0.5 -> 3.5 | M24: =L24+0.5 -> 4 | N24: =M24+0.5 -> 4.5 | O24: =N24+0.5 -> 5 | P24: =O24+0.5 -> 5.5
A25: Discounting Factor | G25: =1/(1+$B$49)^(G24) -> 0.94121154 | H25: =1/(1+$B$49)^(H24) -> 0.8337997 | I25: =1/(1+$B$49)^(I24) -> 0.7847819 | J25: =1/(1+$B$49)^(J24) -> 0.73864578 | K25: =1/(1+$B$49)^(K24) -> 0.69522193 | L25: =1/(1+$B$49)^(L24) -> 0.65435091 | M25: =1/(1+$B$49)^(M24) -> 0.61588263 | N25: =1/(1+$B$49)^(N24) -> 0.57967584 | ... P25: =1/(1+$B$49)^(P24) -> 0.51352275
A26: PV of FCFE | B26: =B23 -> 15761 | C26: =C23 -> 53228 | D26: =D23 -> -16616 | E26: =E23 -> -14781 | F26: =F23 -> 29242 | G26: =G23*G25 -> 55138.716 | H26: =H23*H25 -> 25699.767 | I26: =I23*I25 -> 53180.397 | J26: =J23*J25 -> 71293.058 | K26: =K23*K25 -> 92527.538 | L26: =L23*L25 -> 111206.64 | M26: =M23*M25 -> 121872.5 | N26: =N23*N25 -> 130781.56 | ... P26: =P23*P25 -> 150852.84
A28: WACC CALCULATION | E28: Calculation of Terminal Value | I28: Calculation of Equity Value Per Share | O28: Sensitivity Analysis - Value of Operating Assets
A29: Risk-Free Rate | C29: 0.071 | E29: FCFF (n) | F29: =P12 -> 296031.75 | I29: PV of FCFF | J29: =SUM(G15:P15) -> 966618.17 | M29: WACC / Terminal Growth | N29: 0.03 | O29: 0.035 | P29: 0.04 | Q29: 0.045 | R29: 0.05
A30: Beta | C30: =Assumptions!C104 -> 0.92 | E30: WACC | F30: =B49 -> 0.12882212 | I30: PV of Terminal Value | J30: =F33*P14 -> 1779959.8 | M30: 0.09 | N30: =SUM($C$15:$L$15)+(($L$12*(1+N$29)/($M30-N$29)))*$L$14 -> 2359929.2 | O30: =SUM($C$15:$L$15)+(($L$12*(1+O$29)/($M30-O$29)))*$L$14 -> 2545588.6 | P30: =SUM($C$15:$L$15)+(($L$12*(1+P$29)/($M30-P$29)))*$L$14 -> 2768379.9 | Q30: =SUM($C$15:$L$15)+(($L$12*(1+Q$29)/($M30-Q$29)))*$L$14 -> 3040680.3 | R30: =SUM($C$15:$L$15)+(($L$12*(1+R$29)/($M30-R$29)))*$L$14 -> 3381055.9
A31: Market Risk Premium | C31: =Assumptions!C103 -> 0.065 | E31: Terminal Growth | F31: =B48 -> 0.04 | I31: EV | J31: =J29+J30 -> 2746577.9 | M31: 0.095 | N31: =SUM($C$15:$L$15)+(($L$12*(1+N$29)/($M31-N$29)))*$L$14 -> 2211480.3 | O31: =SUM($C$15:$L$15)+(($L$12*(1+O$29)/($M31-O$29)))*$L$14 -> 2369297.3 | P31: =SUM($C$15:$L$15)+(($L$12*(1+P$29)/($M31-P$29)))*$L$14 -> 2555808.4 | Q31: =SUM($C$15:$L$15)+(($L$12*(1+Q$29)/($M31-Q$29)))*$L$14 -> 2779621.6 | R31: =SUM($C$15:$L$15)+(($L$12*(1+R$29)/($M31-R$29)))*$L$14 -> 3053171.2
A32: Cost of Equity | C32: =C29+(C30*C31) -> 0.1308 | E32: FCFF (n+1) | F32: =F29*(1+F31) -> 307873.02 | I32: Add: Cash | J32: =FS!H29 -> 34192 | M32: 0.1 | N32: =SUM($C$15:$L$15)+(($L$12*(1+N$29)/($M32-N$29)))*$L$14 -> 2084238.3 | O32: =SUM($C$15:$L$15)+(($L$12*(1+O$29)/($M32-O$29)))*$L$14 -> 2220127.8 | P32: =SUM($C$15:$L$15)+(($L$12*(1+P$29)/($M32-P$29)))*$L$14 -> 2378665.4 | Q32: =SUM($C$15:$L$15)+(($L$12*(1+Q$29)/($M32-Q$29)))*$L$14 -> 2566028.1 | R32: =SUM($C$15:$L$15)+(($L$12*(1+R$29)/($M32-R$29)))*$L$14 -> 2790863.4
E33: Terminal Value | F33: =F32/(F30-F31) -> 3466175.1 | I33: Add: Investments | J33: =FS!H40 -> 785 | M33: 0.105 | N33: =SUM($C$15:$L$15)+(($L$12*(1+N$29)/($M33-N$29)))*$L$14 -> 1973962 | O33: =SUM($C$15:$L$15)+(($L$12*(1+O$29)/($M33-O$29)))*$L$14 -> 2092268.2 | P33: =SUM($C$15:$L$15)+(($L$12*(1+P$29)/($M33-P$29)))*$L$14 -> 2228775.3 | Q33: =SUM($C$15:$L$15)+(($L$12*(1+Q$29)/($M33-Q$29)))*$L$14 -> 2388033.6 | R33: =SUM($C$15:$L$15)+(($L$12*(1+R$29)/($M33-R$29)))*$L$14 -> 2576247.9
A34: Pre-Tax Cost of Debt | C34: =(FS!H17)/(('Working '!L113+'Working '!L117)/2) -> 0.039432128 | I34: Less: Debt | J34: ='Working '!L126 -> 61998 | M34: 0.11 | N34: =SUM($C$15:$L$15)+(($L$12*(1+N$29)/($M34-N$29)))*$L$14 -> 1877470.2 | O34: =SUM($C$15:$L$15)+(($L$12*(1+O$29)/($M34-O$29)))*$L$14 -> 1981456.5 | P34: =SUM($C$15:$L$15)+(($L$12*(1+P$29)/($M34-P$29)))*$L$14 -> 2100298 | Q34: =SUM($C$15:$L$15)+(($L$12*(1+Q$29)/($M34-Q$29)))*$L$14 -> 2237422.8 | R34: =SUM($C$15:$L$15)+(($L$12*(1+R$29)/($M34-R$29)))*$L$14 -> 2397401.7
A35: Tax Rate | C35: =Assumptions!C107 -> 0.3 | I35: Value of Equity | J35: =J31+J32+J33-J34 -> 2719556.9 | M35: =M34+0.5% -> 0.115 | N35: =SUM($C$15:$L$15)+(($L$12*(1+N$29)/($M35-N$29)))*$L$14 -> 1792330.4 | O35: =SUM($C$15:$L$15)+(($L$12*(1+O$29)/($M35-O$29)))*$L$14 -> 1884496.3 | P35: =SUM($C$15:$L$15)+(($L$12*(1+P$29)/($M35-P$29)))*$L$14 -> 1988951 | Q35: =SUM($C$15:$L$15)+(($L$12*(1+Q$29)/($M35-Q$29)))*$L$14 -> 2108327.8 | R35: =SUM($C$15:$L$15)+(($L$12*(1+R$29)/($M35-R$29)))*$L$14 -> 2246070.3
A36: After-Tax Cost of Debt | C36: =C34*(1-C35) -> 0.02760249 | I36: No. of Shares | J36: 2644 | M36: =M35+0.5% -> 0.12 | N36: =SUM($C$15:$L$15)+(($L$12*(1+N$29)/($M36-N$29)))*$L$14 -> 1716650.5 | O36: =SUM($C$15:$L$15)+(($L$12*(1+O$29)/($M36-O$29)))*$L$14 -> 1798943.2 | P36: =SUM($C$15:$L$15)+(($L$12*(1+P$29)/($M36-P$29)))*$L$14 -> 1891522.4 | Q36: =SUM($C$15:$L$15)+(($L$12*(1+Q$29)/($M36-Q$29)))*$L$14 -> 1996445.5 | R36: =SUM($C$15:$L$15)+(($L$12*(1+R$29)/($M36-R$29)))*$L$14 -> 2116357.7
I37: Equity Value Per Share | J37: =J35/J36 -> 1028.5768 | M37: =M36+0.5% -> 0.125 | N37: =SUM($C$15:$L$15)+(($L$12*(1+N$29)/($M37-N$29)))*$L$14 -> 1648937 | O37: =SUM($C$15:$L$15)+(($L$12*(1+O$29)/($M37-O$29)))*$L$14 -> 1722896 | P37: =SUM($C$15:$L$15)+(($L$12*(1+P$29)/($M37-P$29)))*$L$14 -> 1805556 | Q37: =SUM($C$15:$L$15)+(($L$12*(1+Q$29)/($M37-Q$29)))*$L$14 -> 1898548.5 | R37: =SUM($C$15:$L$15)+(($L$12*(1+R$29)/($M37-R$29)))*$L$14 -> 2003940
A38: Market Value of Equity | B38: ₹ Lakhs | C38: =2644*1200 -> 3172800 | I38: Current Share Price | J38: 1210 | M38: =M37+0.5% -> 0.13 | N38: =SUM($C$15:$L$15)+(($L$12*(1+N$29)/($M38-N$29)))*$L$14 -> 1587994.8 | O38: =SUM($C$15:$L$15)+(($L$12*(1+O$29)/($M38-O$29)))*$L$14 -> 1654853.7 | P38: =SUM($C$15:$L$15)+(($L$12*(1+P$29)/($M38-P$29)))*$L$14 -> 1729141.4 | Q38: =SUM($C$15:$L$15)+(($L$12*(1+Q$29)/($M38-Q$29)))*$L$14 -> 1812168.8 | R38: =SUM($C$15:$L$15)+(($L$12*(1+R$29)/($M38-R$29)))*$L$14 -> 1905574.6
A39: Market Value of Debt | B39: ₹ Lakhs | C39: ='Working '!L126 -> 61998 | I39: Discount / Premium | J39: =(J37-J38)/J38 -> -0.14993657 | M39: =M38+0.5% -> 0.135 | N39: =SUM($C$15:$L$15)+(($L$12*(1+N$29)/($M39-N$29)))*$L$14 -> 1532856.7 | O39: =SUM($C$15:$L$15)+(($L$12*(1+O$29)/($M39-O$29)))*$L$14 -> 1593615.7 | P39: =SUM($C$15:$L$15)+(($L$12*(1+P$29)/($M39-P$29)))*$L$14 -> 1660770.4 | Q39: =SUM($C$15:$L$15)+(($L$12*(1+Q$29)/($M39-Q$29)))*$L$14 -> 1735386.8 | R39: =SUM($C$15:$L$15)+(($L$12*(1+R$29)/($M39-R$29)))*$L$14 -> 1818781.6
A40: Total Capital | C40: =SUM(C38:C39) -> 3234798 | M40: =M39+0.5% -> 0.14 | N40: =SUM($C$15:$L$15)+(($L$12*(1+N$29)/($M40-N$29)))*$L$14 -> 1482731.1 | O40: =SUM($C$15:$L$15)+(($L$12*(1+O$29)/($M40-O$29)))*$L$14 -> 1538209.9 | P40: =SUM($C$15:$L$15)+(($L$12*(1+P$29)/($M40-P$29)))*$L$14 -> 1599236.6 | Q40: =SUM($C$15:$L$15)+(($L$12*(1+Q$29)/($M40-Q$29)))*$L$14 -> 1666687.2 | R40: =SUM($C$15:$L$15)+(($L$12*(1+R$29)/($M40-R$29)))*$L$14 -> 1741632.2
M41: =M40+0.5% -> 0.145 | N41: =SUM($C$15:$L$15)+(($L$12*(1+N$29)/($M41-N$29)))*$L$14 -> 1436964.2 | O41: =SUM($C$15:$L$15)+(($L$12*(1+O$29)/($M41-O$29)))*$L$14 -> 1487840.9 | P41: =SUM($C$15:$L$15)+(($L$12*(1+P$29)/($M41-P$29)))*$L$14 -> 1543563.1 | Q41: =SUM($C$15:$L$15)+(($L$12*(1+Q$29)/($M41-Q$29)))*$L$14 -> 1604857.5 | R41: =SUM($C$15:$L$15)+(($L$12*(1+R$29)/($M41-R$29)))*$L$14 -> 1672603.9
A42: Equity Weight | C42: =C38/C40 -> 0.98083404 | M42: =M41+0.5% -> 0.15 | N42: =SUM($C$15:$L$15)+(($L$12*(1+N$29)/($M42-N$29)))*$L$14 -> 1395011.2 | O42: =SUM($C$15:$L$15)+(($L$12*(1+O$29)/($M42-O$29)))*$L$14 -> 1441851.9 | P42: =SUM($C$15:$L$15)+(($L$12*(1+P$29)/($M42-P$29)))*$L$14 -> 1492950.8 | Q42: =SUM($C$15:$L$15)+(($L$12*(1+Q$29)/($M42-Q$29)))*$L$14 -> 1548916.3 | R42: =SUM($C$15:$L$15)+(($L$12*(1+R$29)/($M42-R$29)))*$L$14 -> 1610478.4
A43: Debt Weight | C43: =C39/C40 -> 0.019165957 | M43: =M42+0.5% -> 0.155 | N43: =SUM($C$15:$L$15)+(($L$12*(1+N$29)/($M43-N$29)))*$L$14 -> 1356414.5 | O43: =SUM($C$15:$L$15)+(($L$12*(1+O$29)/($M43-O$29)))*$L$14 -> 1399695.3 | P43: =SUM($C$15:$L$15)+(($L$12*(1+P$29)/($M43-P$29)))*$L$14 -> 1446739.6 | Q43: =SUM($C$15:$L$15)+(($L$12*(1+Q$29)/($M43-Q$29)))*$L$14 -> 1498060.7 | R43: =SUM($C$15:$L$15)+(($L$12*(1+R$29)/($M43-R$29)))*$L$14 -> 1554269.5
M44: =M43+0.5% -> 0.16 | N44: =SUM($C$15:$L$15)+(($L$12*(1+N$29)/($M44-N$29)))*$L$14 -> 1320786.8 | O44: =SUM($C$15:$L$15)+(($L$12*(1+O$29)/($M44-O$29)))*$L$14 -> 1360911.2 | P44: =SUM($C$15:$L$15)+(($L$12*(1+P$29)/($M44-P$29)))*$L$14 -> 1404379.4 | Q44: =SUM($C$15:$L$15)+(($L$12*(1+Q$29)/($M44-Q$29)))*$L$14 -> 1451627.4 | R44: =SUM($C$15:$L$15)+(($L$12*(1+R$29)/($M44-R$29)))*$L$14 -> 1503170.6
A45: WACC | C45: =C42*C32+C43*C36 -> 0.12882212
A46: DCF Assumptions
A47: Expected Growth | B47: 0.06
A48: Terminal Growth Rate | B48: =Assumptions!C109 -> 0.04
A49: WACC | B49: =C45 -> 0.12882212
A89: All figures in ₹ Lakhs except per-share data, percentages and multiples.

Sheet CCA
F2: United Breweries Limited
F3: Comparable Company Analysis
F5: Market Data Date | G5: =TODAY() -> 46297 | I5: Financial Year | J5: FY2025A | L5: Currency | M5: ₹ Lakhs
F7: A. Peer Selection
F8: Company | G8: Business | H8: Reason for Inclusion
F9: United Breweries Ltd. | G9: Beer / Alcoholic Beverages | H9: Target company
F10: United Spirits Ltd. | G10: Spirits / Alcoholic Beverages | H10: Listed Indian alcoholic-beverage peer
F11: Radico Khaitan Ltd. | G11: Spirits / Alcoholic Beverages | H11: Listed Indian alcoholic-beverage peer
F12: Globus Spirits Ltd. | G12: Spirits / Alcoholic Beverages | H12: Listed Indian alcoholic-beverage peer
F13: Allied Blenders & Distillers Ltd. | G13: Spirits / Alcoholic Beverages | H13: Listed Indian alcoholic-beverage peer
F14: Som Distilleries & Breweries Ltd. | G14: Beer & Spirits | H14: Listed company with beer exposure
F15: Peer Selection Note | G15: UBL operates primarily in beer. Because directly comparable listed Indian beer peers are limited, the peer set includes alcoholic-beverage companies with differences in product mix, scale and profitability. Multiples should be interpreted accordingly.
F18: B. Market & Financial Data
F19: ₹ Cr except per-share data | G19: #VALUE! | H19: #VALUE! | I19: #VALUE! | J19: #VALUE! | K19: #VALUE! | L19: #VALUE!
F20: Share Price | G20: {=_FV(G19,"Price")} -> 1188.8 | H20: {=_FV(H19,"Price")} -> 1338.2 | I20: {=_FV(I19,"Price")} -> 4237 | J20: {=_FV(J19,"Price")} -> 786.9 | K20: {=_FV(K19,"Price")} -> 679.45 | L20: {=_FV(L19,"Price")} -> 74.94
F21: Shares Outstanding (Lakhs) | G21: {=_FV(G19,"Shares outstanding",TRUE)/100000} -> 2644.052 | H21: {=_FV(H19,"Shares outstanding",TRUE)/100000} -> 7273.508 | I21: {=_FV(I19,"Shares outstanding",TRUE)/100000} -> 1339.891 | J21: {=_FV(J19,"Shares outstanding",TRUE)/100000} -> 314.6129 | K21: {=_FV(K19,"Shares outstanding",TRUE)/100000} -> 2797.101 | L21: {=_FV(L19,"Shares outstanding",TRUE)/100000} -> 2079.013
F22: Market Capitalization | G22: =IFERROR(G20*G21,"") -> 3143249 | H22: =IFERROR(H20*H21,"") -> 9733408.4 | I22: =IFERROR(I20*I21,"") -> 5677118.2 | J22: =IFERROR(J20*J21,"") -> 247568.89 | K22: =IFERROR(K20*K21,"") -> 1900490.3 | L22: =IFERROR(L20*L21,"") -> 155801.23
F23: Total Debt | G23: ='Working '!L126 -> 61998 | H23: 2500 | I23: 32000 | J23: 48000 | K23: 115000 | L23: 32000
F24: Cash & Cash Equivalents | G24: =FS!H29 -> 34192 | H24: 185000 | I24: 21000 | J24: 8500 | K24: 18000 | L24: 4500
F25: Net Debt | G25: =IFERROR(G23-G24,"") -> 27806 | H25: =IFERROR(H23-H24,"") -> -182500 | I25: =IFERROR(I23-I24,"") -> 11000 | J25: =IFERROR(J23-J24,"") -> 39500 | K25: =IFERROR(K23-K24,"") -> 97000 | L25: =IFERROR(L23-L24,"") -> 27500
F26: Enterprise Value | G26: =IFERROR(G22+G25,"") -> 3171055 | H26: =IFERROR(H22+H25,"") -> 9550908.4 | I26: =IFERROR(I22+I25,"") -> 5688118.2 | J26: =IFERROR(J22+J25,"") -> 287068.89 | K26: =IFERROR(K22+K25,"") -> 1997490.3 | L26: =IFERROR(L22+L25,"") -> 183301.23
F27: Revenue | G27: ='Working '!L21 -> 1944444 | H27: 2850000 | I27: 1250000 | J27: 380000 | K27: 550000 | L27: 180000
F28: EBITDA | G28: ='Working '!L56 -> 85095 | H28: 450000 | I28: 220000 | J28: 55000 | K28: 85000 | L28: 35000
F29: EBIT | G29: ='Working '!L54 -> 61797 | H29: 380000 | I29: 180000 | J29: 40000 | K29: 60000 | L29: 25000
F30: PAT | G30: ='Working '!L52 -> 44241 | H30: 280000 | I30: 145000 | J30: 28000 | K30: 35000 | L30: 15000
F34: C. Trading Multiples
F35: Multiple | G35: UBL | H35: United Spirits | I35: Radico Khaitan | J35: Globus Spirits | K35: Allied Blenders | L35: Som Distilleries
F36: EV / Revenue | G36: =IFERROR(G26/G27,"") -> 1.6308287 | H36: =IFERROR(H26/H27,"") -> 3.3511959 | I36: =IFERROR(I26/I27,"") -> 4.5504945 | J36: =IFERROR(J26/J27,"") -> 0.75544445 | K36: =IFERROR(K26/K27,"") -> 3.6318005 | L36: =IFERROR(L26/L27,"") -> 1.0183402
F37: EV / EBITDA | G37: =IFERROR(G26/G28,"") -> 37.264881 | H37: =IFERROR(H26/H28,"") -> 21.224241 | I37: =IFERROR(I26/I28,"") -> 25.855083 | J37: =IFERROR(J26/J28,"") -> 5.2194344 | K37: =IFERROR(K26/K28,"") -> 23.499886 | L37: =IFERROR(L26/L28,"") -> 5.2371781
F38: EV / EBIT | G38: =IFERROR(G26/G29,"") -> 51.314061 | H38: =IFERROR(H26/H29,"") -> 25.133969 | I38: =IFERROR(I26/I29,"") -> 31.600656 | J38: =IFERROR(J26/J29,"") -> 7.1767223 | K38: =IFERROR(K26/K29,"") -> 33.291505 | L38: =IFERROR(L26/L29,"") -> 7.3320494
F39: P / E | G39: =IFERROR(G22/G30,"") -> 71.048327 | H39: =IFERROR(H22/H30,"") -> 34.762173 | I39: =IFERROR(I22/I30,"") -> 39.152539 | J39: =IFERROR(J22/J30,"") -> 8.8417461 | K39: =IFERROR(K22/K30,"") -> 54.299722 | L39: =IFERROR(L22/L30,"") -> 10.386749
F42: D. Peer Statistics
F43: Statistic | G43: EV / Revenue | H43: EV / EBITDA | I43: EV / EBIT | J43: P / E
F44: Mean | G44: =IFERROR(AVERAGE(H36:L36),"") -> 2.6614551 | H44: =IFERROR(AVERAGE(H37:L37),"") -> 16.207164 | I44: =IFERROR(AVERAGE(H38:L38),"") -> 20.90698 | J44: =IFERROR(AVERAGE(H39:L39),"") -> 29.488586
F45: Median | G45: =IFERROR(MEDIAN(H36:L36),"") -> 3.3511959 | H45: =IFERROR(MEDIAN(H37:L37),"") -> 21.224241 | I45: =IFERROR(MEDIAN(H38:L38),"") -> 25.133969 | J45: =IFERROR(MEDIAN(H39:L39),"") -> 34.762173
F46: Minimum | G46: =IFERROR(MIN(H36:L36),"") -> 0.75544445 | H46: =IFERROR(MIN(H37:L37),"") -> 5.2194344 | I46: =IFERROR(MIN(H38:L38),"") -> 7.1767223 | J46: =IFERROR(MIN(H39:L39),"") -> 8.8417461
F47: Maximum | G47: =IFERROR(MAX(H36:L36),"") -> 4.5504945 | H47: =IFERROR(MAX(H37:L37),"") -> 25.855083 | I47: =IFERROR(MAX(H38:L38),"") -> 33.291505 | J47: =IFERROR(MAX(H39:L39),"") -> 54.299722
F50: E. Implied Valuation of UBL
F51: Method | G51: UBL Metric | H51: Peer Median Multiple | I51: Implied EV | J51: Implied Equity Value | K51: Implied Value / Share
F52: EV / Revenue | G52: =G27 -> 1944444 | H52: =G45 -> 3.3511959 | I52: =G52*H52 -> 6516212.8 | J52: =I52-G25+G24 -> 6522598.8 | K52: =IFERROR(J52/G21,"") -> 2466.8951
F53: EV / EBITDA | G53: =G28 -> 85095 | H53: =H45 -> 21.224241 | I53: =G53*H53 -> 1806076.8 | J53: =I53-G25+G24 -> 1812462.8 | K53: =IFERROR(J53/G21,"") -> 685.48681
F54: EV / EBIT | G54: =G29 -> 61797 | H54: =I45 -> 25.133969 | I54: =G54*H54 -> 1553203.9 | J54: =I54-G25+G24 -> 1559589.9 | K54: =IFERROR(J54/G21,"") -> 589.84843
F55: P / E | G55: =G30 -> 44241 | H55: =J45 -> 34.762173 | I55: N/A | J55: =G55*H55 -> 1537913.3 | K55: =IFERROR(J55/G21,"") -> 581.65017
F59: F. Valuation Summary
F60: Valuation Method | G60: Implied Value / Share | H60: Reference
F61: DCF | G61: =Valuation!J37 -> 1028.5768 | H61: Primary DCF valuation
F62: EV / Revenue | G62: =K52 -> 2466.8951 | H62: Peer median multiple
F63: EV / EBITDA | G63: =K53 -> 685.48681 | H63: Peer median multiple
F64: EV / EBIT | G64: =K54 -> 589.84843 | H64: Peer median multiple
F65: P / E | G65: =K55 -> 581.65017 | H65: Peer median multiple

Sheet Ratio 
B1: United Breweries Limited
B2: Ratio Analysis
B4: Historical Performance & Forecast Ratio Analysis
C5: Historical Period | H5: Forecast Period | R5: Model Notes
B6: Ratio | C6: FY2021A | D6: FY2022A | E6: FY2023A | F6: FY2024A | G6: FY2025A | H6: FY2026E | I6: FY2027E | J6: FY2028E | K6: FY2029E | L6: FY2030E | M6: FY2031E | N6: FY2032E | O6: FY2033E | P6: FY2034E | Q6: FY2035E | R6: Unit | S6: Interpretation / Driver
B7: A. GROWTH RATIOS
B8: Revenue Growth | C8: ='Working '!H18 -> 0 | D8: ='Working '!I18 -> 0.28845761 | E8: ='Working '!J18 -> 0.26875888 | F8: ='Working '!K18 -> 0.10380341 | G8: ='Working '!L18 -> 0.055986742 | H8: ='Working '!M18 -> 0.07 | I8: ='Working '!N18 -> 0.07 | J8: ='Working '!O18 -> 0.065 | ... Q8: ='Working '!V18 -> 0.05 | R8: % | S8: Revenue growth accelerated with volume recovery, pricing and favourable state mix; UBL reported 6% volume growth and 10% net-sales growth in FY2025.
B9: EBITDA Growth | C9: ='Working '!H57 -> 0 | D9: ='Working '!I57 -> 0.71286755 | E9: ='Working '!J57 -> -0.12922454 | F9: ='Working '!K57 -> 0.21720366 | G9: ='Working '!L57 -> 0.10523035 | H9: ='Working '!M57 -> 0.023648886 | I9: ='Working '!N57 -> 0.18793778 | J9: ='Working '!O57 -> 0.47970273 | ... Q9: ='Working '!V57 -> 0.11525152 | R9: % | S9: EBITDA growth reflects higher sales, premiumisation and operating efficiencies; UBL reported ~32% premium-segment growth and cited revenue-management and cost initiatives.
B10: EBIT Growth | C10: ='Working '!H55 -> 0 | D10: ='Working '!I55 -> 1.6510829 | E10: ='Working '!J55 -> -0.17137976 | F10: ='Working '!K55 -> 0.32250267 | G10: ='Working '!L55 -> 0.10741358 | H10: ='Working '!M55 -> -0.097918139 | I10: ='Working '!N55 -> 0.25428698 | J10: ='Working '!O55 -> 0.67872723 | ... Q10: ='Working '!V55 -> 0.12341816 | R10: % | S10: EBIT growth strengthens as revenue growth combines with better gross margins and operating-cost control; UBL reported EBIT improvement of 35 bps in FY2025.
B11: PAT Growth | C11: ='Working '!H53 -> 0 | D11: ='Working '!I53 -> 2.2160239 | E11: ='Working '!J53 -> -0.1677229 | F11: ='Working '!K53 -> 0.34849678 | G11: ='Working '!L53 -> 0.076790147 | H11: ='Working '!M53 -> -0.14864038 | I11: ='Working '!N53 -> 0.26092731 | J11: ='Working '!O53 -> 0.69749291 | ... Q11: ='Working '!V53 -> 0.12399065 | R11: % | S11: PAT growth reflects improved operating profitability flowing through to earnings, although the growth rate normalises as the earnings base becomes larger. UBL's PAT increased to ₹441 crore in FY2025 from ₹409 crore
B12: B. PROFITABILITY RATIOS
B13: Gross Margin | C13: =FS!D21/FS!D10 -> 0.017255747 | D13: =FS!E21/FS!E10 -> 0.037589395 | E13: =FS!F21/FS!F10 -> 0.026971016 | F13: =FS!G21/FS!G10 -> 0.029866793 | G13: =FS!H21/FS!H10 -> 0.03244475 | H13: =FS!I21/FS!I10 -> 0.025826935 | I13: =FS!J21/FS!J10 -> 0.030435409 | J13: =FS!K21/FS!K10 -> 0.048510695 | ... Q13: =FS!R21/FS!R10 -> 0.12775448 | R13: % | S13: Margin expansion is supported by pricing, state mix, revenue management and cost initiatives; UBL reported ~44 bps gross-margin improvement in FY2025.
B14: EBITDA Margin | C14: ='Working '!H56/'Working '!H21 -> 0.041431183 | D14: ='Working '!I56/'Working '!I21 -> 0.055224724 | E14: ='Working '!J56/'Working '!J21 -> 0.037875467 | F14: ='Working '!K56/'Working '!K21 -> 0.041723228 | G14: ='Working '!L56/'Working '!L21 -> 0.043763153 | H14: ='Working '!M56/'Working '!M21 -> 0.041810752 | I14: ='Working '!N56/'Working '!N21 -> 0.046419226 | J14: ='Working '!O56/'Working '!O21 -> 0.064494513 | ... Q14: ='Working '!V56/'Working '!V21 -> 0.1437383 | R14: % | S14: EBITDA margin improves as premiumisation and operating efficiencies provide better operating leverage; UBL reported EBITDA margin rising to 9.8% in FY2025.
B15: EBIT Margin | C15: ='Working '!H54/'Working '!H21 -> 0.018765124 | D15: ='Working '!I54/'Working '!I21 -> 0.038713032 | E15: ='Working '!J54/'Working '!J21 -> 0.02526568 | F15: ='Working '!K54/'Working '!K21 -> 0.030240169 | G15: ='Working '!L54/'Working '!L21 -> 0.031781322 | H15: ='Working '!M54/'Working '!M21 -> 0.026757545 | I15: ='Working '!N54/'Working '!N21 -> 0.031366019 | J15: ='Working '!O54/'Working '!O21 -> 0.049441306 | ... Q15: ='Working '!V54/'Working '!V21 -> 0.12868509 | R15: % | S15: EBIT margin expands as gross-margin gains and cost efficiencies flow through after depreciation; UBL reported 35 bps EBIT improvement in FY2025.
B16: PAT Margin | C16: ='Working '!H52/'Working '!H21 -> 0.011120544 | D16: ='Working '!I52/'Working '!I21 -> 0.027830931 | E16: ='Working '!J52/'Working '!J21 -> 0.018243743 | F16: ='Working '!K52/'Working '!K21 -> 0.022264889 | G16: ='Working '!L52/'Working '!L21 -> 0.022752519 | H16: ='Working '!M52/'Working '!M21 -> 0.018078854 | I16: ='Working '!N52/'Working '!N21 -> 0.021304786 | J16: ='Working '!O52/'Working '!O21 -> 0.033957487 | ... Q16: ='Working '!V52/'Working '!V21 -> 0.089428138 | R16: % | S16: PAT margin remained broadly stable at 2.2%–2.3% in FY2024–FY2025 as improved operating profitability was partly offset by tax and other expenses
B17: C. LIQUIDITY RATIOS
B18: Current Ratio | C18: =FS!D35/FS!D64 -> 1.5236928 | D18: =FS!E35/FS!E64 -> 1.6843934 | E18: =FS!F35/FS!F64 -> 1.5873473 | F18: =FS!G35/FS!G64 -> 1.5280139 | G18: =FS!H35/FS!H64 -> 1.4124229 | H18: =FS!I35/FS!I64 -> 1.5218901 | I18: =FS!J35/FS!J64 -> 1.5652629 | J18: =FS!K35/FS!K64 -> 1.6386944 | ... Q18: =FS!R35/FS!R64 -> 2.9886458 | R18: x | S18: Liquidity remains comfortable in the forecast as current assets grow faster than current liabilities; the model reflects increasing cash generation and limited financial leverage.
B19: Quick Ratio | C19: =(FS!D35-FS!D32)/FS!D64 -> 0.9920868 | D19: =(FS!E35-FS!E32)/FS!E64 -> 1.2104719 | E19: =(FS!F35-FS!F32)/FS!F64 -> 0.96041643 | F19: =(FS!G35-FS!G32)/FS!G64 -> 1.0442115 | G19: =(FS!H35-FS!H32)/FS!H64 -> 0.98513617 | H19: =(FS!I35-FS!I32)/FS!I64 -> 1.0161811 | I19: =(FS!J35-FS!J32)/FS!J64 -> 1.0553954 | J19: =(FS!K35-FS!K32)/FS!K64 -> 1.1394629 | ... Q19: =(FS!R35-FS!R32)/FS!R64 -> 2.4730612 | R19: x | S19: Quick liquidity improves steadily as cash and receivables increase relative to current liabilities, reducing dependence on inventory for short-term obligations.
B20: Cash Ratio | C20: =FS!D29/FS!D64 -> 0.19146946 | D20: =FS!E29/FS!E64 -> 0.43684576 | E20: =FS!F29/FS!F64 -> 0.14483679 | F20: =FS!G29/FS!G64 -> 0.045650076 | G20: =FS!H29/FS!H64 -> 0.090383055 | H20: =FS!I29/FS!I64 -> 0.17154275 | I20: =FS!J29/FS!J64 -> 0.18689019 | J20: =FS!K29/FS!K64 -> 0.24510375 | ... Q20: =FS!R29/FS!R64 -> 1.4333502 | R20: x | S20: The sharp forecast improvement reflects increasing cash balances alongside relatively low debt requirements in the model.
B21: D. LEVERAGE & COVERAGE
B22: Debt / Equity | C22: ='Working '!H126/'Working '!H161 -> 0.032456466 | D22: ='Working '!I126/'Working '!I161 -> 0.0024918898 | E22: ='Working '!J126/'Working '!J161 -> 0.0039660272 | F22: ='Working '!K126/'Working '!K161 -> 0.024574291 | G22: ='Working '!L126/'Working '!L161 -> 0.14293553 | H22: ='Working '!M126/'Working '!M161 -> 0.13926028 | I22: ='Working '!N126/'Working '!N161 -> 0.13490617 | J22: ='Working '!O126/'Working '!O161 -> 0.12696322 | ... Q22: ='Working '!V126/'Working '!V161 -> 0.059944137 | R22: x | S22: Leverage remains low because the forecast assumes limited incremental borrowing relative to growing equity; UBL's FY2025 reported ROE/ROCE remained supported despite a relatively low debt base.
B23: Net Debt / EBITDA | C23: ='Working '!H126/'Working '!H56 -> 0.27213563 | D23: ='Working '!I126/'Working '!I56 -> 0.013408406 | E23: ='Working '!J126/'Working '!J56 -> 0.02469409 | F23: ='Working '!K126/'Working '!K56 -> 0.13251854 | G23: ='Working '!L126/'Working '!L56 -> 0.72857395 | H23: ='Working '!M126/'Working '!M56 -> 0.72210396 | I23: ='Working '!N126/'Working '!N56 -> 0.61833059 | J23: ='Working '!O126/'Working '!O56 -> 0.42509121 | ... Q23: ='Working '!V126/'Working '!V56 -> 0.14642022 | R23: x | S23: Net leverage declines as EBITDA and cash generation grow faster than debt; this indicates increasing debt-servicing capacity in the forecast.
B24: Interest Coverage | C24: ='Working '!H56/'Working '!H45 -> 18.707102 | D24: ='Working '!I56/'Working '!I45 -> 49.148173 | E24: ='Working '!J56/'Working '!J45 -> 136.32328 | F24: ='Working '!K56/'Working '!K45 -> 111.74601 | G24: ='Working '!L56/'Working '!L45 -> 66.170295 | H24: ='Working '!M56/'Working '!M45 -> 44.92831 | I24: ='Working '!N56/'Working '!N45 -> 49.880408 | J24: ='Working '!O56/'Working '!O45 -> 69.303452 | ... Q24: ='Working '!V56/'Working '!V45 -> 154.45594 | R24: x | S24: Coverage rises sharply because EBIT grows while finance costs remain relatively small; UBL's FY2025 annual report also shows strong debt-service capacity.
B25: E. EFFICIENCY / WORKING CAPITAL
B26: Inventory Days | C26: =Assumptions!H67 -> 204.44187 | D26: =Assumptions!I67 -> 116.73159 | E26: =Assumptions!J67 -> 122.1821 | F26: =Assumptions!K67 -> 107.67867 | G26: =Assumptions!L67 -> 116.40442 | H26: =Assumptions!M67 -> 133.48773 | I26: =Assumptions!N67 -> 133.48773 | J26: =Assumptions!O67 -> 133.48773 | ... Q26: =Assumptions!V67 -> 133.48773 | R26: Days | S26: Historical inventory days remain elevated due to the nature of beer production and the need to maintain raw materials, packaging and finished-goods inventory; the forecast assumes a higher steady-state inventory requirement. UBL confirms inventories include raw materials, packing materials, bottles, stores and spares.
B27: Receivable Days | C27: =Assumptions!H65 -> 49.988548 | D27: =Assumptions!I65 -> 34.899931 | E27: =Assumptions!J65 -> 30.84914 | F27: =Assumptions!K65 -> 46.076556 | G27: =Assumptions!L65 -> 53.797449 | H27: =Assumptions!M65 -> 43.122325 | I27: =Assumptions!N65 -> 43.122325 | J27: =Assumptions!O65 -> 43.122325 | ... Q27: =Assumptions!V65 -> 43.122325 | R27: Days | S27: Receivable days increased historically, indicating slower collection; UBL specifically noted delays in collections from certain state government corporations in FY2025.
B28: Payable Days | C28: =Assumptions!H69 -> 110.64913 | D28: =Assumptions!I69 -> 80.213977 | E28: =Assumptions!J69 -> 60.617039 | F28: =Assumptions!K69 -> 74.081843 | G28: =Assumptions!L69 -> 81.974838 | H28: =Assumptions!M69 -> 81.507366 | I28: =Assumptions!N69 -> 81.507366 | J28: =Assumptions!O69 -> 81.507366 | ... Q28: =Assumptions!V69 -> 81.507366 | R28: Days | S28: Payable days remain elevated in the forecast as supplier credit continues to support working-capital requirements and partially offsets inventory and receivable funding needs.
B29: Cash Conversion Cycle | C29: =C26+C27-C28 -> 143.78128 | D29: =D26+D27-D28 -> 71.417547 | E29: =E26+E27-E28 -> 92.414202 | F29: =F26+F27-F28 -> 79.673378 | G29: =G26+G27-G28 -> 88.227028 | H29: =H26+H27-H28 -> 95.102688 | I29: =I26+I27-I28 -> 95.102688 | J29: =J26+J27-J28 -> 95.102688 | ... Q29: =Q26+Q27-Q28 -> 95.102688 | R29: Days | S29: CCC increases in the forecast because inventory days remain elevated while receivable days stay above historical pre-FY2025 levels; the model therefore assumes continued working-capital investment.
B30: F. RETURN RATIOS
B31: ROA | C31: ='Working '!H52/FS!D47 -> 0.019450938 | D31: ='Working '!I52/FS!E47 -> 0.061533186 | E31: ='Working '!J52/FS!F47 -> 0.048512911 | F31: ='Working '!K52/FS!G47 -> 0.05825017 | G31: ='Working '!L52/FS!H47 -> 0.053802906 | H31: ='Working '!M52/FS!I47 -> 0.046231173 | I31: ='Working '!N52/FS!J47 -> 0.055949057 | J31: ='Working '!O52/FS!K47 -> 0.090453704 | ... Q31: ='Working '!V52/FS!R47 -> 0.18615426 | R31: % | S31: ROA improves as forecast earnings grow faster than the asset base, supported by higher margins and operating leverage.
B32: ROE | C32: ='Working '!H52/FS!D52 -> 0.031742623 | D32: ='Working '!I52/FS!E52 -> 0.09293116 | E32: ='Working '!J52/FS!F52 -> 0.076755259 | F32: ='Working '!K52/FS!G52 -> 0.098208225 | G32: ='Working '!L52/FS!H52 -> 0.10124633 | H32: ='Working '!M52/FS!I52 -> 0.082799777 | I32: ='Working '!N52/FS!J52 -> 0.099461602 | J32: ='Working '!O52/FS!K52 -> 0.15627613 | ... Q32: ='Working '!V52/FS!R52 -> 0.25404329 | R32: % | S32: ROE improves with rising PAT and relatively moderate growth in equity. UBL's reported ROE increased from 7.7% in FY2023 to 10.1% in FY2024 and 10.3% in FY2025.
B33: ROCE | C33: ='Working '!H54/(FS!D47-FS!D64) -> 0.051718381 | D33: ='Working '!I54/(FS!E47-FS!E64) -> 0.12811533 | E33: ='Working '!J54/(FS!F47-FS!F64) -> 0.10541029 | F33: ='Working '!K54/(FS!G47-FS!G64) -> 0.13210187 | G33: ='Working '!L54/(FS!H47-FS!H64) -> 0.13918933 | H33: ='Working '!M54/(FS!I47-FS!I64) -> 0.12162642 | I33: ='Working '!N54/(FS!J47-FS!J64) -> 0.14627342 | J33: ='Working '!O54/(FS!K47-FS!K64) -> 0.23078958 | ... Q33: ='Working '!V54/(FS!R47-FS!R64) -> 0.37689344 | R33: % | S33: ROCE improves materially in the forecast as EBIT expands relative to capital employed. Historically, UBL reported 13.1% in FY2024 and 13.0% in FY2025, indicating a stable pre-forecast capital return base.
